Workbook

Sheet Painel
B1: 💰 CONTROLE FINANCEIRO TOTAL — MENTE MILIONÁRIA 2026
B4: 🏦 SALDO EM TEMPO REAL | E4: 💵 TOTAL ENTRADAS ANO | H4: 💸 TOTAL SAÍDAS ANO | K4: 📊 TAXA DE POUPANÇA
B5: ='Configuração'!D6+E5-H5 -> -9463.78 | E5: =O23 -> 6393 | H5: =O26 -> 15856.78 | K5: =IF(E5=0,0,(E5-H5)/E5) -> -1.4803347
B7: 💵 DE ONDE VEM O DINHEIRO — POR FONTE DE RECEITA
B8: Fonte de Receita | C8: Jan | D8: Fev | E8: Mar | F8: Abr | G8: Mai | H8: Jun | I8: Jul | J8: Ago | K8: Set | L8: Out | M8: Nov | N8: Dez | O8: TOTAL
B9: Salário CLT | C9: =Janeiro!M7 -> 0 | D9: =Fevereiro!M7 -> 0 | E9: ='Março'!M7 -> 0 | F9: =Abril!M7 -> 0 | G9: =Maio!M7 -> 0 | H9: =Junho!M7 -> 0 | I9: =Julho!M7 -> 0 | J9: =Agosto!M7 -> 0 | K9: =Setembro!M7 -> 0 | L9: =Outubro!M7 -> 0 | M9: =Novembro!M7 -> 0 | N9: =Dezembro!M7 -> 0 | O9: =SUM(C9:N9) -> 0 | P9: Salário CLT
B10: Freelance / Projetos | C10: =Janeiro!M8 -> 0 | D10: =Fevereiro!M8 -> 0 | E10: ='Março'!M8 -> 0 | F10: =Abril!M8 -> 0 | G10: =Maio!M8 -> 0 | H10: =Junho!M8 -> 0 | I10: =Julho!M8 -> 0 | J10: =Agosto!M8 -> 0 | K10: =Setembro!M8 -> 0 | L10: =Outubro!M8 -> 0 | M10: =Novembro!M8 -> 0 | N10: =Dezembro!M8 -> 0 | O10: =SUM(C10:N10) -> 0 | P10: Freelance / Projetos
B11: Vendas Online | C11: =Janeiro!M9 -> 0 | D11: =Fevereiro!M9 -> 0 | E11: ='Março'!M9 -> 0 | F11: =Abril!M9 -> 0 | G11: =Maio!M9 -> 0 | H11: =Junho!M9 -> 0 | I11: =Julho!M9 -> 0 | J11: =Agosto!M9 -> 0 | K11: =Setembro!M9 -> 0 | L11: =Outubro!M9 -> 0 | M11: =Novembro!M9 -> 0 | N11: =Dezembro!M9 -> 0 | O11: =SUM(C11:N11) -> 0 | P11: Vendas Online
B12: Consultoria | C12: =Janeiro!M10 -> 0 | D12: =Fevereiro!M10 -> 0 | E12: ='Março'!M10 -> 0 | F12: =Abril!M10 -> 0 | G12: =Maio!M10 -> 0 | H12: =Junho!M10 -> 0 | I12: =Julho!M10 -> 0 | J12: =Agosto!M10 -> 0 | K12: =Setembro!M10 -> 0 | L12: =Outubro!M10 -> 0 | M12: =Novembro!M10 -> 0 | N12: =Dezembro!M10 -> 0 | O12: =SUM(C12:N12) -> 0 | P12: Consultoria
B13: Rendimentos / Investimentos | C13: =Janeiro!M11 -> 0 | D13: =Fevereiro!M11 -> 0 | E13: ='Março'!M11 -> 0 | F13: =Abril!M11 -> 0 | G13: =Maio!M11 -> 0 | H13: =Junho!M11 -> 0 | I13: =Julho!M11 -> 0 | J13: =Agosto!M11 -> 0 | K13: =Setembro!M11 -> 0 | L13: =Outubro!M11 -> 0 | M13: =Novembro!M11 -> 0 | N13: =Dezembro!M11 -> 0 | O13: =SUM(C13:N13) -> 0 | P13: Rendimentos / Investimentos
B14: Aluguel Recebido | C14: =Janeiro!M12 -> 0 | D14: =Fevereiro!M12 -> 0 | E14: ='Março'!M12 -> 0 | F14: =Abril!M12 -> 0 | G14: =Maio!M12 -> 0 | H14: =Junho!M12 -> 0 | I14: =Julho!M12 -> 0 | J14: =Agosto!M12 -> 0 | K14: =Setembro!M12 -> 0 | L14: =Outubro!M12 -> 0 | M14: =Novembro!M12 -> 0 | N14: =Dezembro!M12 -> 0 | O14: =SUM(C14:N14) -> 0 | P14: Aluguel Recebido
B15: Comissões | C15: =Janeiro!M13 -> 0 | D15: =Fevereiro!M13 -> 0 | E15: ='Março'!M13 -> 0 | F15: =Abril!M13 -> 0 | G15: =Maio!M13 -> 0 | H15: =Junho!M13 -> 0 | I15: =Julho!M13 -> 0 | J15: =Agosto!M13 -> 0 | K15: =Setembro!M13 -> 0 | L15: =Outubro!M13 -> 0 | M15: =Novembro!M13 -> 0 | N15: =Dezembro!M13 -> 0 | O15: =SUM(C15:N15) -> 0 | P15: Comissões
B16: Bônus / Participação | C16: =Janeiro!M14 -> 0 | D16: =Fevereiro!M14 -> 0 | E16: ='Março'!M14 -> 0 | F16: =Abril!M14 -> 0 | G16: =Maio!M14 -> 0 | H16: =Junho!M14 -> 0 | I16: =Julho!M14 -> 0 | J16: =Agosto!M14 -> 0 | K16: =Setembro!M14 -> 0 | L16: =Outubro!M14 -> 0 | M16: =Novembro!M14 -> 0 | N16: =Dezembro!M14 -> 0 | O16: =SUM(C16:N16) -> 0 | P16: Bônus / Participação
B17: Renda Extra / Bico | C17: =Janeiro!M15 -> 0 | D17: =Fevereiro!M15 -> 0 | E17: ='Março'!M15 -> 0 | F17: =Abril!M15 -> 0 | G17: =Maio!M15 -> 0 | H17: =Junho!M15 -> 0 | I17: =Julho!M15 -> 0 | J17: =Agosto!M15 -> 0 | K17: =Setembro!M15 -> 0 | L17: =Outubro!M15 -> 0 | M17: =Novembro!M15 -> 0 | N17: =Dezembro!M15 -> 0 | O17: =SUM(C17:N17) -> 0 | P17: Renda Extra / Bico
B18: Outros | C18: =Janeiro!M16 -> 0 | D18: =Fevereiro!M16 -> 0 | E18: ='Março'!M16 -> 0 | F18: =Abril!M16 -> 0 | G18: =Maio!M16 -> 0 | H18: =Junho!M16 -> 0 | I18: =Julho!M16 -> 0 | J18: =Agosto!M16 -> 0 | K18: =Setembro!M16 -> 0 | L18: =Outubro!M16 -> 0 | M18: =Novembro!M16 -> 0 | N18: =Dezembro!M16 -> 0 | O18: =SUM(C18:N18) -> 0 | P18: Outros
B19: 📊 TOTAL | C19: =SUM(C9:C18) -> 0 | D19: =SUM(D9:D18) -> 0 | E19: =SUM(E9:E18) -> 0 | F19: =SUM(F9:F18) -> 0 | G19: =SUM(G9:G18) -> 0 | H19: =SUM(H9:H18) -> 0 | I19: =SUM(I9:I18) -> 0 | J19: =SUM(J9:J18) -> 0 | ... O19: =SUM(O9:O18) -> 0
B21: 📊 FLUXO DE CAIXA — ENTRADAS vs SAÍDAS vs SALDO MENSAL
C22: Jan | D22: Fev | E22: Mar | F22: Abr | G22: Mai | H22: Jun | I22: Jul | J22: Ago | K22: Set | L22: Out | M22: Nov | N22: Dez | O22: TOTAL
B23: 💵 Total Entradas | C23: =Janeiro!D5 -> 0 | D23: =Fevereiro!D5 -> 6393 | E23: ='Março'!D5 -> 0 | F23: =Abril!D5 -> 0 | G23: =Maio!D5 -> 0 | H23: =Junho!D5 -> 0 | I23: =Julho!D5 -> 0 | J23: =Agosto!D5 -> 0 | K23: =Setembro!D5 -> 0 | L23: =Outubro!D5 -> 0 | M23: =Novembro!D5 -> 0 | N23: =Dezembro!D5 -> 0 | O23: =SUM(C23:N23) -> 6393
B24: 🔒 Despesas Fixas | C24: =Janeiro!D6 -> 1184.9 | D24: =Fevereiro!D6 -> 1184.9 | E24: ='Março'!D6 -> 1184.9 | F24: =Abril!D6 -> 1184.9 | G24: =Maio!D6 -> 1184.9 | H24: =Junho!D6 -> 1184.9 | I24: =Julho!D6 -> 1184.9 | J24: =Agosto!D6 -> 1184.9 | K24: =Setembro!D6 -> 1184.9 | L24: =Outubro!D6 -> 1184.9 | M24: =Novembro!D6 -> 1184.9 | N24: =Dezembro!D6 -> 1184.9 | O24: =SUM(C24:N24) -> 14218.8
B25: 🛒 Despesas Variáveis | C25: =Janeiro!D7 -> 0 | D25: =Fevereiro!D7 -> 1637.98 | E25: ='Março'!D7 -> 0 | F25: =Abril!D7 -> 0 | G25: =Maio!D7 -> 0 | H25: =Junho!D7 -> 0 | I25: =Julho!D7 -> 0 | J25: =Agosto!D7 -> 0 | K25: =Setembro!D7 -> 0 | L25: =Outubro!D7 -> 0 | M25: =Novembro!D7 -> 0 | N25: =Dezembro!D7 -> 0 | O25: =SUM(C25:N25) -> 1637.98
B26: 💸 Total Saídas | C26: =C24+C25 -> 1184.9 | D26: =D24+D25 -> 2822.88 | E26: =E24+E25 -> 1184.9 | F26: =F24+F25 -> 1184.9 | G26: =G24+G25 -> 1184.9 | H26: =H24+H25 -> 1184.9 | I26: =I24+I25 -> 1184.9 | J26: =J24+J25 -> 1184.9 | ... N26: =N24+N25 -> 1184.9 | O26: =SUM(C26:N26) -> 15856.78
B27: 📈 Saldo do Mês | C27: =C23-C26 -> -1184.9 | D27: =D23-D26 -> 3570.12 | E27: =E23-E26 -> -1184.9 | F27: =F23-F26 -> -1184.9 | G27: =G23-G26 -> -1184.9 | H27: =H23-H26 -> -1184.9 | I27: =I23-I26 -> -1184.9 | J27: =J23-J26 -> -1184.9 | ... N27: =N23-N26 -> -1184.9 | O27: =SUM(C27:N27) -> -9463.78
B28: 💰 Saldo Acumulado | C28: ='Configuração'!D6+C27 -> -1184.9 | D28: =C28+D27 -> 2385.22 | E28: =D28+E27 -> 1200.32 | F28: =E28+F27 -> 15.42 | G28: =F28+G27 -> -1169.48 | H28: =G28+H27 -> -2354.38 | I28: =H28+I27 -> -3539.28 | J28: =I28+J27 -> -4724.18 | K28: =J28+K27 -> -5909.08 | ... N28: =M28+N27 -> -9463.78 | O28: =N28 -> -9463.78
B29: 📊 % Poupança Mês | C29: =IF(C23=0,0,C27/C23) -> 0 | D29: =IF(D23=0,0,D27/D23) -> 0.55844205 | E29: =IF(E23=0,0,E27/E23) -> 0 | F29: =IF(F23=0,0,F27/F23) -> 0 | G29: =IF(G23=0,0,G27/G23) -> 0 | H29: =IF(H23=0,0,H27/H23) -> 0 | I29: =IF(I23=0,0,I27/I23) -> 0 | J29: =IF(J23=0,0,J27/J23) -> 0 | ... O29: =IF(O23=0,0,O27/O23) -> -1.4803347
I34: 💸 ONDE VAI O DINHEIRO — POR CATEGORIA
I35: Categoria | J35: Total Ano | K35: % Gasto | L35: % Renda | M35: Alerta
I36: Moradia | J36: =Janeiro!M22+Fevereiro!M22+'Março'!M22+Abril!M22+Maio!M22+Junho!M22+Julho!M22+Agosto!M22+Setembro!M22+Outubro!M22+Novembro!M22+Dezembro!M22 -> 2400 | K36: =IF(H5=0,0,J36/H5) -> 0.15135481 | L36: =IF(E5=0,0,J36/E5) -> 0.37541061 | M36: =IF(L36>0.2,"🔴 Alto",IF(L36>0.1,"🟡 Médio","🟢 OK")) -> 🔴 Alto | N36: Moradia
I37: Alimentação | J37: =Janeiro!M23+Fevereiro!M23+'Março'!M23+Abril!M23+Maio!M23+Junho!M23+Julho!M23+Agosto!M23+Setembro!M23+Outubro!M23+Novembro!M23+Dezembro!M23 -> 584.98 | K37: =IF(H5=0,0,J37/H5) -> 0.036891475 | L37: =IF(E5=0,0,J37/E5) -> 0.091503207 | M37: =IF(L37>0.2,"🔴 Alto",IF(L37>0.1,"🟡 Médio","🟢 OK")) -> 🟢 OK | N37: Alimentação
I38: Transporte | J38: =Janeiro!M24+Fevereiro!M24+'Março'!M24+Abril!M24+Maio!M24+Junho!M24+Julho!M24+Agosto!M24+Setembro!M24+Outubro!M24+Novembro!M24+Dezembro!M24 -> 2510 | K38: =IF(H5=0,0,J38/H5) -> 0.15829191 | L38: =IF(E5=0,0,J38/E5) -> 0.39261692 | M38: =IF(L38>0.2,"🔴 Alto",IF(L38>0.1,"🟡 Médio","🟢 OK")) -> 🔴 Alto | N38: Transporte
I39: Saúde | J39: =Janeiro!M25+Fevereiro!M25+'Março'!M25+Abril!M25+Maio!M25+Junho!M25+Julho!M25+Agosto!M25+Setembro!M25+Outubro!M25+Novembro!M25+Dezembro!M25 -> 101 | K39: =IF(H5=0,0,J39/H5) -> 0.0063695151 | L39: =IF(E5=0,0,J39/E5) -> 0.01579853 | M39: =IF(L39>0.2,"🔴 Alto",IF(L39>0.1,"🟡 Médio","🟢 OK")) -> 🟢 OK | N39: Saúde
I40: Educação | J40: =Janeiro!M26+Fevereiro!M26+'Março'!M26+Abril!M26+Maio!M26+Junho!M26+Julho!M26+Agosto!M26+Setembro!M26+Outubro!M26+Novembro!M26+Dezembro!M26 -> 5640 | K40: =IF(H5=0,0,J40/H5) -> 0.35568381 | L40: =IF(E5=0,0,J40/E5) -> 0.88221492 | M40: =IF(L40>0.2,"🔴 Alto",IF(L40>0.1,"🟡 Médio","🟢 OK")) -> 🔴 Alto | N40: Educação
I41: Lazer / Diversão | J41: =Janeiro!M27+Fevereiro!M27+'Março'!M27+Abril!M27+Maio!M27+Junho!M27+Julho!M27+Agosto!M27+Setembro!M27+Outubro!M27+Novembro!M27+Dezembro!M27 -> 718.8 | K41: =IF(H5=0,0,J41/H5) -> 0.045330767 | L41: =IF(E5=0,0,J41/E5) -> 0.11243548 | M41: =IF(L41>0.2,"🔴 Alto",IF(L41>0.1,"🟡 Médio","🟢 OK")) -> 🟡 Médio | N41: Lazer / Diversão
I42: Vestuário | J42: =Janeiro!M28+Fevereiro!M28+'Março'!M28+Abril!M28+Maio!M28+Junho!M28+Julho!M28+Agosto!M28+Setembro!M28+Outubro!M28+Novembro!M28+Dezembro!M28 -> 142 | K42: =IF(H5=0,0,J42/H5) -> 0.0089551599 | L42: =IF(E5=0,0,J42/E5) -> 0.022211794 | M42: =IF(L42>0.2,"🔴 Alto",IF(L42>0.1,"🟡 Médio","🟢 OK")) -> 🟢 OK | N42: Vestuário
I43: Tecnologia | J43: =Janeiro!M29+Fevereiro!M29+'Março'!M29+Abril!M29+Maio!M29+Junho!M29+Julho!M29+Agosto!M29+Setembro!M29+Outubro!M29+Novembro!M29+Dezembro!M29 -> 1920 | K43: =IF(H5=0,0,J43/H5) -> 0.12108385 | L43: =IF(E5=0,0,J43/E5) -> 0.30032848 | M43: =IF(L43>0.2,"🔴 Alto",IF(L43>0.1,"🟡 Médio","🟢 OK")) -> 🔴 Alto | N43: Tecnologia
I44: Assinaturas | J44: =Janeiro!M30+Fevereiro!M30+'Março'!M30+Abril!M30+Maio!M30+Junho!M30+Julho!M30+Agosto!M30+Setembro!M30+Outubro!M30+Novembro!M30+Dezembro!M30 -> 0 | K44: =IF(H5=0,0,J44/H5) -> 0 | L44: =IF(E5=0,0,J44/E5) -> 0 | M44: =IF(L44>0.2,"🔴 Alto",IF(L44>0.1,"🟡 Médio","🟢 OK")) -> 🟢 OK | N44: Assinaturas
I45: Seguros | J45: =Janeiro!M31+Fevereiro!M31+'Março'!M31+Abril!M31+Maio!M31+Junho!M31+Julho!M31+Agosto!M31+Setembro!M31+Outubro!M31+Novembro!M31+Dezembro!M31 -> 0 | K45: =IF(H5=0,0,J45/H5) -> 0 | L45: =IF(E5=0,0,J45/E5) -> 0 | M45: =IF(L45>0.2,"🔴 Alto",IF(L45>0.1,"🟡 Médio","🟢 OK")) -> 🟢 OK | N45: Seguros
I46: Impostos | J46: =Janeiro!M32+Fevereiro!M32+'Março'!M32+Abril!M32+Maio!M32+Junho!M32+Julho!M32+Agosto!M32+Setembro!M32+Outubro!M32+Novembro!M32+Dezembro!M32 -> 0 | K46: =IF(H5=0,0,J46/H5) -> 0 | L46: =IF(E5=0,0,J46/E5) -> 0 | M46: =IF(L46>0.2,"🔴 Alto",IF(L46>0.1,"🟡 Médio","🟢 OK")) -> 🟢 OK | N46: Impostos
I47: Investimentos | J47: =Janeiro!M33+Fevereiro!M33+'Março'!M33+Abril!M33+Maio!M33+Junho!M33+Julho!M33+Agosto!M33+Setembro!M33+Outubro!M33+Novembro!M33+Dezembro!M33 -> 0 | K47: =IF(H5=0,0,J47/H5) -> 0 | L47: =IF(E5=0,0,J47/E5) -> 0 | M47: =IF(L47>0.2,"🔴 Alto",IF(L47>0.1,"🟡 Médio","🟢 OK")) -> 🟢 OK | N47: Investimentos
I48: Doações | J48: =Janeiro!M34+Fevereiro!M34+'Março'!M34+Abril!M34+Maio!M34+Junho!M34+Julho!M34+Agosto!M34+Setembro!M34+Outubro!M34+Novembro!M34+Dezembro!M34 -> 0 | K48: =IF(H5=0,0,J48/H5) -> 0 | L48: =IF(E5=0,0,J48/E5) -> 0 | M48: =IF(L48>0.2,"🔴 Alto",IF(L48>0.1,"🟡 Médio","🟢 OK")) -> 🟢 OK | N48: Doações
I49: Outros | J49: =Janeiro!M35+Fevereiro!M35+'Março'!M35+Abril!M35+Maio!M35+Junho!M35+Julho!M35+Agosto!M35+Setembro!M35+Outubro!M35+Novembro!M35+Dezembro!M35 -> 0 | K49: =IF(H5=0,0,J49/H5) -> 0 | L49: =IF(E5=0,0,J49/E5) -> 0 | M49: =IF(L49>0.2,"🔴 Alto",IF(L49>0.1,"🟡 Médio","🟢 OK")) -> 🟢 OK | N49: Outros
I50: 📊 TOTAL | J50: =SUM(J36:J49) -> 14016.78 | K50: =IF(J50=0,0,1) -> 1 | L50: =IF(E5=0,0,J50/E5) -> 2.1925199
B64: 🏺 SISTEMA DE JARROS — ALOCAÇÃO vs REAL | J64: 🎯 JORNADA LIBERDADE FINANCEIRA
B65: Jarro | C65: % Ideal | D65: Alocado Ano | E65: % Real | F65: Diferença | G65: Status | H65: Meta Ano | J65: Indicador | K65: Atual | L65: Meta | M65: Progresso | N65: Status
B66: 🏠 Necessidades | C66: 0.55 | D66: =Janeiro!N7+Fevereiro!N7+'Março'!N7+Abril!N7+Maio!N7+Junho!N7+Julho!N7+Agosto!N7+Setembro!N7+Outubro!N7+Novembro!N7+Dezembro!N7 -> 3516.15 | E66: =IF(E5=0,0,D66/E5) -> 0.55 | F66: =E66-C66 -> 0 | G66: =IF(ABS(F66)<=0.03,"✅ OK",IF(F66>0,"⬆️ Acima","⬇️ Abaixo")) -> ✅ OK | H66: =E5*C66 -> 3516.15 | I66: NEC | J66: 🛡️ Reserva Emergência | K66: =(O24+O25)/12*6 -> 7928.39 | L66: ='Configuração'!D8 -> 30000 | M66: =IF(L66=0,0,MIN(K66/L66,1)) -> 0.26427967 | N66: =IF(M66>=1,"✅ Atingida!",IF(M66>=0.7,"🔥 Quase!",IF(M66>=0.3,"⚡ Progresso","🚀 Comece!"))) -> 🚀 Comece!
B67: 💎 Liberdade Financeira | C67: 0.1 | D67: =Janeiro!N8+Fevereiro!N8+'Março'!N8+Abril!N8+Maio!N8+Junho!N8+Julho!N8+Agosto!N8+Setembro!N8+Outubro!N8+Novembro!N8+Dezembro!N8 -> 639.3 | E67: =IF(E5=0,0,D67/E5) -> 0.1 | F67: =E67-C67 -> 0 | G67: =IF(ABS(F67)<=0.03,"✅ OK",IF(F67>0,"⬆️ Acima","⬇️ Abaixo")) -> ✅ OK | H67: =E5*C67 -> 639.3 | I67: CFL | J67: 💎 Patrimônio Investido | K67: =N28 -> -9463.78 | L67: ='Configuração'!D9 -> 12000 | M67: =IF(L67=0,0,MIN(K67/L67,1)) -> -0.78864833 | N67: =IF(M67>=1,"✅ Atingida!",IF(M67>=0.7,"🔥 Quase!",IF(M67>=0.3,"⚡ Progresso","🚀 Comece!"))) -> 🚀 Comece!
B68: 🏦 Poupança LP | C68: 0.1 | D68: =Janeiro!N9+Fevereiro!N9+'Março'!N9+Abril!N9+Maio!N9+Junho!N9+Julho!N9+Agosto!N9+Setembro!N9+Outubro!N9+Novembro!N9+Dezembro!N9 -> 639.3 | E68: =IF(E5=0,0,D68/E5) -> 0.1 | F68: =E68-C68 -> 0 | G68: =IF(ABS(F68)<=0.03,"✅ OK",IF(F68>0,"⬆️ Acima","⬇️ Abaixo")) -> ✅ OK | H68: =E5*C68 -> 639.3 | I68: PELP | J68: 📊 Renda Passiva | K68: ='Configuração'!D11 -> 0 | L68: ='Configuração'!D12 -> 1000 | M68: =IF(L68=0,0,MIN(K68/L68,1)) -> 0 | N68: =IF(M68>=1,"✅ Atingida!",IF(M68>=0.7,"🔥 Quase!",IF(M68>=0.3,"⚡ Progresso","🚀 Comece!"))) -> 🚀 Comece!
B69: 📚 Educação | C69: 0.1 | D69: =Janeiro!N10+Fevereiro!N10+'Março'!N10+Abril!N10+Maio!N10+Junho!N10+Julho!N10+Agosto!N10+Setembro!N10+Outubro!N10+Novembro!N10+Dezembro!N10 -> 639.3 | E69: =IF(E5=0,0,D69/E5) -> 0.1 | F69: =E69-C69 -> 0 | G69: =IF(ABS(F69)<=0.03,"✅ OK",IF(F69>0,"⬆️ Acima","⬇️ Abaixo")) -> ✅ OK | H69: =E5*C69 -> 639.3 | I69: EDU | J69: 💰 Patrimônio Total | K69: =B5 -> -9463.78 | L69: ='Configuração'!D10 -> 50000 | M69: =IF(L69=0,0,MIN(K69/L69,1)) -> -0.1892756 | N69: =IF(M69>=1,"✅ Atingida!",IF(M69>=0.7,"🔥 Quase!",IF(M69>=0.3,"⚡ Progresso","🚀 Comece!"))) -> 🚀 Comece!
B70: 🎉 Diversão | C70: 0.1 | D70: =Janeiro!N11+Fevereiro!N11+'Março'!N11+Abril!N11+Maio!N11+Junho!N11+Julho!N11+Agosto!N11+Setembro!N11+Outubro!N11+Novembro!N11+Dezembro!N11 -> 639.3 | E70: =IF(E5=0,0,D70/E5) -> 0.1 | F70: =E70-C70 -> 0 | G70: =IF(ABS(F70)<=0.03,"✅ OK",IF(F70>0,"⬆️ Acima","⬇️ Abaixo")) -> ✅ OK | H70: =E5*C70 -> 639.3 | I70: DIV | J70: 📉 Custo de Vida/Mês | K70: =(O24+O25)/12 -> 1321.3983 | L70: — | M70: — | N70: 📊 Monitorar
B71: 🤝 Doações | C71: 0.05 | D71: =Janeiro!N12+Fevereiro!N12+'Março'!N12+Abril!N12+Maio!N12+Junho!N12+Julho!N12+Agosto!N12+Setembro!N12+Outubro!N12+Novembro!N12+Dezembro!N12 -> 319.65 | E71: =IF(E5=0,0,D71/E5) -> 0.05 | F71: =E71-C71 -> 0 | G71: =IF(ABS(F71)<=0.03,"✅ OK",IF(F71>0,"⬆️ Acima","⬇️ Abaixo")) -> ✅ OK | H71: =E5*C71 -> 319.65 | I71: DOA

Sheet Configuração
B1: ⚙️ CONFIGURAÇÃO — EDITE TUDO EM AZUL
B4: 💰 SEUS DADOS FINANCEIROS — RENDA VARIÁVEL
B5: # | C5: Parâmetro | D5: Valor | E5: Descrição
B6: 1 | C6: Saldo Inicial (todo dinheiro que você tem HOJE) | D6: 0 | E6: Soma de tudo: contas, carteira, poupança, investimentos
B7: 2 | C7: Renda Mensal ESTIMADA (referência para jarros) | D7: 0 | E7: Estimativa — seu real vem das receitas do mês
B8: 3 | C8: Meta: Reserva de Emergência (R$) | D8: 30000 | E8: Ideal = 6x seu custo de vida mensal
B9: 4 | C9: Meta: Patrimônio Investido em 12 meses | D9: 12000 | E9: Quanto quer ter investido no jarro CFL
B10: 5 | C10: Meta: Patrimônio Total em 12 meses | D10: 50000 | E10: Todo seu dinheiro acumulado
B11: 6 | C11: Renda Passiva ATUAL (mensal) | D11: 0 | E11: Quanto já recebe sem trabalhar
B12: 7 | C12: Meta: Renda Passiva em 12 meses | D12: 1000 | E12: Quanto quer receber de renda passiva por mês
B14: 💵 FONTES DE RENDA — CONFIGURE SUAS FONTES
B15: # | C15: Fonte de Receita | D15: Ativa? | E15: Frequência
B16: 1 | C16: Salário CLT | D16: Sim | E16: Mensal fixo
B17: 2 | C17: Freelance / Projetos | D17: Sim | E17: Variável/projeto
B18: 3 | C18: Vendas Online | D18: Não | E18: Variável
B19: 4 | C19: Consultoria | D19: Não | E19: Por demanda
B20: 5 | C20: Rendimentos / Investimentos | D20: Não | E20: Mensal (juros)
B21: 6 | C21: Aluguel Recebido | D21: Não | E21: Mensal fixo
B22: 7 | C22: Comissões | D22: Não | E22: Variável
B23: 8 | C23: Bônus / Participação | D23: Não | E23: Semestral
B24: 9 | C24: Renda Extra / Bico | D24: Não | E24: Esporádico
B25: 10 | C25: Outros | D25: Não | E25: Esporádico
B27: 🏺 PERCENTUAIS DOS JARROS — PERSONALIZE
B28: Jarro | C28: % do Total | D28: Valor Estimado | E28: Regra de Ouro
B29: 🏠 | C29: Necessidades (NEC) | D29: 0.55 | E29: =D7*D29 -> 0 | F29: 💡 Máx 55%! Se ultrapassa, CORTE custos
B30: 💎 | C30: Liberdade Financeira (CFL) | D30: 0.1 | E30: =D7*D30 -> 0 | F30: 💡 SAGRADO — NUNCA gaste, só invista
B31: 🏦 | C31: Poupança LP (PELP) | D31: 0.1 | E31: =D7*D31 -> 0 | F31: 💡 Para compras acima de R$500
B32: 📚 | C32: Educação (EDU) | D32: 0.1 | E32: =D7*D32 -> 0 | F32: 💡 Investir em VOCÊ = melhor ROI
B33: 🎉 | C33: Diversão (DIV) | D33: 0.1 | E33: =D7*D33 -> 0 | F33: 💡 GASTE TUDO todo mês!
B34: 🤝 | C34: Doações (DOA) | D34: 0.05 | E34: =D7*D34 -> 0 | F34: 💡 Doar ativa reciprocidade
B35: ✅ | C35: TOTAL | D35: =SUM(D29:D34) -> 1 | E35: =SUM(E29:E34) -> 0 | F35: =IF(D35=1,"✅ 100%","⚠️ ERRO: deve somar 100%!") -> ✅ 100%
B37: 🔒 CUSTOS FIXOS MENSAIS — REPLICADOS EM TODOS OS MESES AUTOMATICAMENTE
B38: # | C38: Descrição do Custo Fixo | D38: Valor (R$) | E38: Categoria | F38: Vencimento
B39: 1 | C39: Aluguel / Financiamento | E39: Moradia | F39: 5
B40: 2 | C40: Condomínio | E40: Moradia | F40: 10
B41: 3 | C41: IPTU (parcela) | E41: Impostos | F41: 15
B42: 4 | C42: Energia Elétrica | D42: 200 | E42: Moradia | F42: 10
B43: 5 | C43: Água / Saneamento | E43: Moradia | F43: 15
B44: 6 | C44: Gás | E44: Moradia | F44: 20
B45: 7 | C45: Internet | D45: 100 | E45: Tecnologia | F45: 10
B46: 8 | C46: Celular | D46: 60 | E46: Tecnologia | F46: 12
B47: 9 | C47: Plano de Saúde | E47: Saúde | F47: 5
B48: 10 | C48: Seguro (carro/vida) | E48: Seguros | F48: 15
B49: 11 | C49: Transporte / Combustível | D49: 200 | E49: Transporte | F49: 1
B50: 12 | C50: Supermercado (base) | E50: Alimentação | F50: 1
B51: 13 | C51: Farmácia / Medicamentos | E51: Saúde | F51: 1
B52: 14 | C52: Academia | E52: Saúde | F52: 5
B53: 15 | C53: Streaming / Entretenimento | D53: 59.9 | E53: Lazer / Diversão | F53: 1
B54: 16 | C54: Assinaturas / SaaS | E54: Assinaturas | F54: 1
B55: 17 | C55: Educação / Cursos | E55: Educação | F55: 1
B56: 18 | C56: Investimento Automático (CFL) | D56: 0 | E56: Investimentos | F56: 1
B57: 19 | C57: Poupança LP (PELP) | D57: 0 | E57: Investimentos | F57: 1
B58: 20 | C58: Doações Fixas | D58: 0 | E58: Doações | F58: 1
B59: 21 | C59: Escola Aurora | D59: 470 | E59: Educação | F59: 28
B60: 22 | C60: Serasa | D60: 95 | E60: Dívida
B61: 23
B62: 24
B63: 25
B64: 26
B65: 27
B66: 28
B67: 29
B68: 30
B69: 💸 | C69: TOTAL CUSTOS FIXOS | D69: =SUM(D39:D68) -> 1184.9 | E69: =IF(D69>D7*D29,"🔴 ACIMA do NEC!","✅ Dentro do limite") -> 🔴 ACIMA do NEC! | F69: =IF(D7>0,D69/D7,0) -> 0

Sheet Janeiro
B1: 📅 JANEIRO 2026 — CONTROLE COMPLETO
B3: 🏦 SALDO EM TEMPO REAL | F3: 🏺 JARROS DO MÊS
B4: 🔙 | C4: Saldo Inicial | D4: ='Configuração'!D6 -> 0 | E4: =D5 -> 0 | F4: 🏠 | G4: NEC (55%) | H4: =D5*'Configuração'!D29 -> 0
B5: 💵 | C5: Total Entradas | D5: =E29 -> 0 | E5: =D5 -> 0 | F5: 💎 | G5: CFL (10%) | H5: =D5*'Configuração'!D30 -> 0
B6: 🔒 | C6: Despesas Fixas | D6: =E63 -> 1184.9 | F6: 🏦 | G6: PELP (10%) | H6: =D5*'Configuração'!D31 -> 0
B7: 🛒 | C7: Despesas Variáveis | D7: =E102 -> 0 | F7: 📚 | G7: EDU (10%) | H7: =D5*'Configuração'!D32 -> 0 | J7: =H4 -> 0 | M7: =C109 -> 0 | N7: =H4 -> 0
B8: 💸 | C8: Total Saídas | D8: =D6+D7 -> 1184.9 | E8: =IF(D5=0,0,D8/D5) -> 0 | F8: 🎉 | G8: DIV (10%) | H8: =D5*'Configuração'!D33 -> 0 | J8: =H5 -> 0 | M8: =C110 -> 0 | N8: =H5 -> 0
B9: 📈 | C9: Saldo do Mês | D9: =D5-D8 -> -1184.9 | E9: =IF(D5=0,0,D9/D5) -> 0 | F9: 🤝 | G9: DOA (5%) | H9: =D5*'Configuração'!D34 -> 0 | J9: =H6 -> 0 | M9: =C111 -> 0 | N9: =H6 -> 0
B10: 🏦 | C10: SALDO FINAL | D10: =D4+D9 -> -1184.9 | E10: =D10 -> -1184.9 | J10: =H7 -> 0 | M10: =C112 -> 0 | N10: =H7 -> 0
J11: =H8 -> 0 | M11: =C113 -> 0 | N11: =H8 -> 0
B12: 💰 RECEITAS DO MÊS — DE ONDE VEM SEU DINHEIRO | J12: =H9 -> 0 | M12: =C114 -> 0 | N12: =H9 -> 0
B13: # | C13: Data | D13: Descrição da Receita | E13: Valor (R$) | F13: Fonte de Receita | G13: Recebido? | H13: Observação | M13: =C115 -> 0
B14: 1 | M14: =C116 -> 0
B15: 2 | M15: =C117 -> 0
B16: 3 | M16: =C118 -> 0
B17: 4
B18: 5
B19: 6
B20: 7
B21: 8
B22: 9 | M22: =G109 -> 200
B23: 10 | M23: =G110 -> 0
B24: 11 | M24: =G111 -> 200
B25: 12 | M25: =G112 -> 0
B26: 13 | M26: =G113 -> 470
B27: 14 | M27: =G114 -> 59.9
B28: 15 | M28: =G115 -> 0
B29: 💰 | C29: TOTAL RECEITAS DO MÊS | E29: =SUM(E14:E28) -> 0 | M29: =G116 -> 160
M30: =G117 -> 0
B31: 🔒 DESPESAS FIXAS — AUTOMÁTICAS DA CONFIGURAÇÃO (edite valores se precisar) | M31: =G118 -> 0
B32: # | C32: Venc. | D32: Descrição | E32: Valor (R$) | F32: Categoria | G32: Pago? ✅/❌ | H32: Observação | M32: =G119 -> 0
B33: 1 | C33: ='Configuração'!F39 -> 5 | D33: ='Configuração'!C39 -> Aluguel / Financiamento | E33: ='Configuração'!D39 | F33: ='Configuração'!E39 -> Moradia | M33: =G120 -> 0
B34: 2 | C34: ='Configuração'!F40 -> 10 | D34: ='Configuração'!C40 -> Condomínio | E34: ='Configuração'!D40 | F34: ='Configuração'!E40 -> Moradia | M34: =G121 -> 0
B35: 3 | C35: ='Configuração'!F41 -> 15 | D35: ='Configuração'!C41 -> IPTU (parcela) | E35: ='Configuração'!D41 | F35: ='Configuração'!E41 -> Impostos | M35: =G122 -> 0
B36: 4 | C36: ='Configuração'!F42 -> 10 | D36: ='Configuração'!C42 -> Energia Elétrica | E36: ='Configuração'!D42 -> 200 | F36: ='Configuração'!E42 -> Moradia
B37: 5 | C37: ='Configuração'!F43 -> 15 | D37: ='Configuração'!C43 -> Água / Saneamento | E37: ='Configuração'!D43 | F37: ='Configuração'!E43 -> Moradia
B38: 6 | C38: ='Configuração'!F44 -> 20 | D38: ='Configuração'!C44 -> Gás | E38: ='Configuração'!D44 | F38: ='Configuração'!E44 -> Moradia
B39: 7 | C39: ='Configuração'!F45 -> 10 | D39: ='Configuração'!C45 -> Internet | E39: ='Configuração'!D45 -> 100 | F39: ='Configuração'!E45 -> Tecnologia
B40: 8 | C40: ='Configuração'!F46 -> 12 | D40: ='Configuração'!C46 -> Celular | E40: ='Configuração'!D46 -> 60 | F40: ='Configuração'!E46 -> Tecnologia
B41: 9 | C41: ='Configuração'!F47 -> 5 | D41: ='Configuração'!C47 -> Plano de Saúde | E41: ='Configuração'!D47 | F41: ='Configuração'!E47 -> Saúde
B42: 10 | C42: ='Configuração'!F48 -> 15 | D42: ='Configuração'!C48 -> Seguro (carro/vida) | E42: ='Configuração'!D48 | F42: ='Configuração'!E48 -> Seguros
B43: 11 | C43: ='Configuração'!F49 -> 1 | D43: ='Configuração'!C49 -> Transporte / Combustível | E43: ='Configuração'!D49 -> 200 | F43: ='Configuração'!E49 -> Transporte
B44: 12 | C44: ='Configuração'!F50 -> 1 | D44: ='Configuração'!C50 -> Supermercado (base) | E44: ='Configuração'!D50 | F44: ='Configuração'!E50 -> Alimentação
B45: 13 | C45: ='Configuração'!F51 -> 1 | D45: ='Configuração'!C51 -> Farmácia / Medicamentos | E45: ='Configuração'!D51 | F45: ='Configuração'!E51 -> Saúde
B46: 14 | C46: ='Configuração'!F52 -> 5 | D46: ='Configuração'!C52 -> Academia | E46: ='Configuração'!D52 | F46: ='Configuração'!E52 -> Saúde
B47: 15 | C47: ='Configuração'!F53 -> 1 | D47: ='Configuração'!C53 -> Streaming / Entretenimento | E47: ='Configuração'!D53 -> 59.9 | F47: ='Configuração'!E53 -> Lazer / Diversão
... B62: 30 | C62: ='Configuração'!F68 | D62: ='Configuração'!C68 | E62: ='Configuração'!D68 | F62: ='Configuração'!E68
B63: 🔒 | C63: TOTAL DESPESAS FIXAS | E63: =SUM(E33:E62) -> 1184.9
B65: 🛒 DESPESAS VARIÁVEIS — ANOTE AQUI TODAS AS SUAS DESPESAS DO DIA A DIA
B66: 👉 ANOTE AQUI: compras, alimentação fora, uber, café, roupas, presentes... TUDO que não é fixo. Cada real anotado deduz do seu saldo!
B67: # | C67: Data | D67: Descrição da Despesa | E67: Valor (R$) | F67: Categoria | G67: Jarro | H67: Forma Pgto | I67: Obs
B68: 1
B69: 2
B70: 3
B71: 4
B72: 5
B73: 6
B74: 7
B75: 8
B76: 9
B77: 10
B78: 11
B79: 12
... B101: 34
B102: 🛒 | C102: TOTAL DESPESAS VARIÁVEIS | E102: =SUM(E68:E101) -> 0
B104: 🏦 SALDO FINAL DO MÊS | D104: =D10 -> -1184.9 | F104: =IF(D9>=0,"✅ Mês positivo! Parabéns!","⚠️ Gastou mais do que ganhou — revise seus gastos") -> ⚠️ Gastou mais do que ganhou — revise seus gastos
B107: 💵 RECEITAS POR FONTE | F107: 💸 DESPESAS POR CATEGORIA
B108: Fonte | C108: Valor | D108: % Total | F108: Categoria | G108: Valor | H108: % Desp. | I108: Alerta
B109: Salário CLT | C109: =SUMIF(F14:F28,"Salário CLT",E14:E28) -> 0 | D109: =IF(E29=0,0,C109/E29) -> 0 | F109: Moradia | G109: =SUMIF(F33:F62,"Moradia",E33:E62)+SUMIF(F68:F101,"Moradia",E68:E101) -> 200 | H109: =IF(D8=0,0,G109/D8) -> 0.16879062 | I109: =IF(H109>0.25,"🔴",IF(H109>0.1,"🟡","🟢")) -> 🟡
B110: Freelance / Projetos | C110: =SUMIF(F14:F28,"Freelance / Projetos",E14:E28) -> 0 | D110: =IF(E29=0,0,C110/E29) -> 0 | F110: Alimentação | G110: =SUMIF(F33:F62,"Alimentação",E33:E62)+SUMIF(F68:F101,"Alimentação",E68:E101) -> 0 | H110: =IF(D8=0,0,G110/D8) -> 0 | I110: =IF(H110>0.25,"🔴",IF(H110>0.1,"🟡","🟢")) -> 🟢
B111: Vendas Online | C111: =SUMIF(F14:F28,"Vendas Online",E14:E28) -> 0 | D111: =IF(E29=0,0,C111/E29) -> 0 | F111: Transporte | G111: =SUMIF(F33:F62,"Transporte",E33:E62)+SUMIF(F68:F101,"Transporte",E68:E101) -> 200 | H111: =IF(D8=0,0,G111/D8) -> 0.16879062 | I111: =IF(H111>0.25,"🔴",IF(H111>0.1,"🟡","🟢")) -> 🟡
B112: Consultoria | C112: =SUMIF(F14:F28,"Consultoria",E14:E28) -> 0 | D112: =IF(E29=0,0,C112/E29) -> 0 | F112: Saúde | G112: =SUMIF(F33:F62,"Saúde",E33:E62)+SUMIF(F68:F101,"Saúde",E68:E101) -> 0 | H112: =IF(D8=0,0,G112/D8) -> 0 | I112: =IF(H112>0.25,"🔴",IF(H112>0.1,"🟡","🟢")) -> 🟢
B113: Rendimentos / Investimentos | C113: =SUMIF(F14:F28,"Rendimentos / Investimentos",E14:E28) -> 0 | D113: =IF(E29=0,0,C113/E29) -> 0 | F113: Educação | G113: =SUMIF(F33:F62,"Educação",E33:E62)+SUMIF(F68:F101,"Educação",E68:E101) -> 470 | H113: =IF(D8=0,0,G113/D8) -> 0.39665795 | I113: =IF(H113>0.25,"🔴",IF(H113>0.1,"🟡","🟢")) -> 🔴
B114: Aluguel Recebido | C114: =SUMIF(F14:F28,"Aluguel Recebido",E14:E28) -> 0 | D114: =IF(E29=0,0,C114/E29) -> 0 | F114: Lazer / Diversão | G114: =SUMIF(F33:F62,"Lazer / Diversão",E33:E62)+SUMIF(F68:F101,"Lazer / Diversão",E68:E101) -> 59.9 | H114: =IF(D8=0,0,G114/D8) -> 0.050552789 | I114: =IF(H114>0.25,"🔴",IF(H114>0.1,"🟡","🟢")) -> 🟢
B115: Comissões | C115: =SUMIF(F14:F28,"Comissões",E14:E28) -> 0 | D115: =IF(E29=0,0,C115/E29) -> 0 | F115: Vestuário | G115: =SUMIF(F33:F62,"Vestuário",E33:E62)+SUMIF(F68:F101,"Vestuário",E68:E101) -> 0 | H115: =IF(D8=0,0,G115/D8) -> 0 | I115: =IF(H115>0.25,"🔴",IF(H115>0.1,"🟡","🟢")) -> 🟢
B116: Bônus / Participação | C116: =SUMIF(F14:F28,"Bônus / Participação",E14:E28) -> 0 | D116: =IF(E29=0,0,C116/E29) -> 0 | F116: Tecnologia | G116: =SUMIF(F33:F62,"Tecnologia",E33:E62)+SUMIF(F68:F101,"Tecnologia",E68:E101) -> 160 | H116: =IF(D8=0,0,G116/D8) -> 0.13503249 | I116: =IF(H116>0.25,"🔴",IF(H116>0.1,"🟡","🟢")) -> 🟡
B117: Renda Extra / Bico | C117: =SUMIF(F14:F28,"Renda Extra / Bico",E14:E28) -> 0 | D117: =IF(E29=0,0,C117/E29) -> 0 | F117: Assinaturas | G117: =SUMIF(F33:F62,"Assinaturas",E33:E62)+SUMIF(F68:F101,"Assinaturas",E68:E101) -> 0 | H117: =IF(D8=0,0,G117/D8) -> 0 | I117: =IF(H117>0.25,"🔴",IF(H117>0.1,"🟡","🟢")) -> 🟢
B118: Outros | C118: =SUMIF(F14:F28,"Outros",E14:E28) -> 0 | D118: =IF(E29=0,0,C118/E29) -> 0 | F118: Seguros | G118: =SUMIF(F33:F62,"Seguros",E33:E62)+SUMIF(F68:F101,"Seguros",E68:E101) -> 0 | H118: =IF(D8=0,0,G118/D8) -> 0 | I118: =IF(H118>0.25,"🔴",IF(H118>0.1,"🟡","🟢")) -> 🟢
F119: Impostos | G119: =SUMIF(F33:F62,"Impostos",E33:E62)+SUMIF(F68:F101,"Impostos",E68:E101) -> 0 | H119: =IF(D8=0,0,G119/D8) -> 0 | I119: =IF(H119>0.25,"🔴",IF(H119>0.1,"🟡","🟢")) -> 🟢
F120: Investimentos | G120: =SUMIF(F33:F62,"Investimentos",E33:E62)+SUMIF(F68:F101,"Investimentos",E68:E101) -> 0 | H120: =IF(D8=0,0,G120/D8) -> 0 | I120: =IF(H120>0.25,"🔴",IF(H120>0.1,"🟡","🟢")) -> 🟢
F121: Doações | G121: =SUMIF(F33:F62,"Doações",E33:E62)+SUMIF(F68:F101,"Doações",E68:E101) -> 0 | H121: =IF(D8=0,0,G121/D8) -> 0 | I121: =IF(H121>0.25,"🔴",IF(H121>0.1,"🟡","🟢")) -> 🟢
F122: Outros | G122: =SUMIF(F33:F62,"Outros",E33:E62)+SUMIF(F68:F101,"Outros",E68:E101) -> 0 | H122: =IF(D8=0,0,G122/D8) -> 0 | I122: =IF(H122>0.25,"🔴",IF(H122>0.1,"🟡","🟢")) -> 🟢

Sheet Fevereiro
B1: 📅 FEVEREIRO 2026 — CONTROLE COMPLETO
B3: 🏦 SALDO EM TEMPO REAL | F3: 🏺 JARROS DO MÊS
B4: 🔙 | C4: Saldo Inicial | D4: =Janeiro!E10 -> -1184.9 | E4: =D5 -> 6393 | F4: 🏠 | G4: NEC (55%) | H4: =D5*'Configuração'!D29 -> 3516.15
B5: 💵 | C5: Total Entradas | D5: =E29 -> 6393 | E5: =D5 -> 6393 | F5: 💎 | G5: CFL (10%) | H5: =D5*'Configuração'!D30 -> 639.3
B6: 🔒 | C6: Despesas Fixas | D6: =E63 -> 1184.9 | F6: 🏦 | G6: PELP (10%) | H6: =D5*'Configuração'!D31 -> 639.3
B7: 🛒 | C7: Despesas Variáveis | D7: =E102 -> 1637.98 | F7: 📚 | G7: EDU (10%) | H7: =D5*'Configuração'!D32 -> 639.3 | J7: =H4 -> 3516.15 | M7: =C109 -> 0 | N7: =H4 -> 3516.15
B8: 💸 | C8: Total Saídas | D8: =D6+D7 -> 2822.88 | E8: =IF(D5=0,0,D8/D5) -> 0.44155795 | F8: 🎉 | G8: DIV (10%) | H8: =D5*'Configuração'!D33 -> 639.3 | J8: =H5 -> 639.3 | M8: =C110 -> 0 | N8: =H5 -> 639.3
B9: 📈 | C9: Saldo do Mês | D9: =D5-D8 -> 3570.12 | E9: =IF(D5=0,0,D9/D5) -> 0.55844205 | F9: 🤝 | G9: DOA (5%) | H9: =D5*'Configuração'!D34 -> 319.65 | J9: =H6 -> 639.3 | M9: =C111 -> 0 | N9: =H6 -> 639.3
B10: 🏦 | C10: SALDO FINAL | D10: =D4+D9 -> 2385.22 | E10: =D10 -> 2385.22 | J10: =H7 -> 639.3 | M10: =C112 -> 0 | N10: =H7 -> 639.3
J11: =H8 -> 639.3 | M11: =C113 -> 0 | N11: =H8 -> 639.3
B12: 💰 RECEITAS DO MÊS — DE ONDE VEM SEU DINHEIRO | J12: =H9 -> 319.65 | M12: =C114 -> 0 | N12: =H9 -> 319.65
B13: # | C13: Data | D13: Descrição da Receita | E13: Valor (R$) | F13: Fonte de Receita | G13: Recebido? | H13: Observação | M13: =C115 -> 0
B14: 1 | C14: 46358 | D14: Auxilio Maternidade | E14: 4310 | F14: Governo | G14: Sim | H14: Incomum | M14: =C116 -> 0
B15: 2 | C15: 13/02/2026 | D15: Cataliad | E15: 1000 | F15: Cataliad | G15: Sim | H15: Renda variável / mês | M15: =C117 -> 0
B16: 3 | C16: 14/02/2026 | D16: Cataliad (parcela pensemed) | E16: 333 | F16: Cataliad | G16: Sim | H16: Renda variável / mês | M16: =C118 -> 0
B17: 4 | C17: 16/02/2026 | D17: Bolsa família | E17: 750 | F17: Governo | G17: Sim | H17: Renda fixa
B18: 5
B19: 6
B20: 7
B21: 8
B22: 9 | M22: =G109 -> 200
B23: 10 | M23: =G110 -> 584.98
B24: 11 | M24: =G111 -> 310
B25: 12 | M25: =G112 -> 101
B26: 13 | M26: =G113 -> 470
B27: 14 | M27: =G114 -> 59.9
B28: 15 | M28: =G115 -> 142
B29: 💰 | C29: TOTAL RECEITAS DO MÊS | E29: =SUM(E14:E28) -> 6393 | M29: =G116 -> 160
M30: =G117 -> 0
B31: 🔒 DESPESAS FIXAS — AUTOMÁTICAS DA CONFIGURAÇÃO (edite valores se precisar) | M31: =G118 -> 0
B32: # | C32: Venc. | D32: Descrição | E32: Valor (R$) | F32: Categoria | G32: Pago? ✅/❌ | H32: Observação | M32: =G119 -> 0
B33: 1 | C33: ='Configuração'!F39 -> 5 | D33: ='Configuração'!C39 -> Aluguel / Financiamento | E33: ='Configuração'!D39 | F33: ='Configuração'!E39 -> Moradia | M33: =G120 -> 0
B34: 2 | C34: ='Configuração'!F40 -> 10 | D34: ='Configuração'!C40 -> Condomínio | E34: ='Configuração'!D40 | F34: ='Configuração'!E40 -> Moradia | M34: =G121 -> 0
B35: 3 | C35: ='Configuração'!F41 -> 15 | D35: ='Configuração'!C41 -> IPTU (parcela) | E35: ='Configuração'!D41 | F35: ='Configuração'!E41 -> Impostos | M35: =G122 -> 0
B36: 4 | C36: ='Configuração'!F42 -> 10 | D36: ='Configuração'!C42 -> Energia Elétrica | E36: ='Configuração'!D42 -> 200 | F36: ='Configuração'!E42 -> Moradia | G36: ✅
B37: 5 | C37: ='Configuração'!F43 -> 15 | D37: ='Configuração'!C43 -> Água / Saneamento | E37: ='Configuração'!D43 | F37: ='Configuração'!E43 -> Moradia
B38: 6 | C38: ='Configuração'!F44 -> 20 | D38: ='Configuração'!C44 -> Gás | E38: ='Configuração'!D44 | F38: ='Configuração'!E44 -> Moradia
B39: 7 | C39: ='Configuração'!F45 -> 10 | D39: ='Configuração'!C45 -> Internet | E39: ='Configuração'!D45 -> 100 | F39: ='Configuração'!E45 -> Tecnologia | G39: ❌
B40: 8 | C40: ='Configuração'!F46 -> 12 | D40: ='Configuração'!C46 -> Celular | E40: ='Configuração'!D46 -> 60 | F40: ='Configuração'!E46 -> Tecnologia | G40: ❌
B41: 9 | C41: ='Configuração'!F47 -> 5 | D41: ='Configuração'!C47 -> Plano de Saúde | E41: ='Configuração'!D47 | F41: ='Configuração'!E47 -> Saúde
B42: 10 | C42: ='Configuração'!F48 -> 15 | D42: ='Configuração'!C48 -> Seguro (carro/vida) | E42: ='Configuração'!D48 | F42: ='Configuração'!E48 -> Seguros
B43: 11 | C43: ='Configuração'!F49 -> 1 | D43: ='Configuração'!C49 -> Transporte / Combustível | E43: ='Configuração'!D49 -> 200 | F43: ='Configuração'!E49 -> Transporte | G43: ❌
B44: 12 | C44: ='Configuração'!F50 -> 1 | D44: ='Configuração'!C50 -> Supermercado (base) | E44: ='Configuração'!D50 | F44: ='Configuração'!E50 -> Alimentação
B45: 13 | C45: ='Configuração'!F51 -> 1 | D45: ='Configuração'!C51 -> Farmácia / Medicamentos | E45: ='Configuração'!D51 | F45: ='Configuração'!E51 -> Saúde
B46: 14 | C46: ='Configuração'!F52 -> 5 | D46: ='Configuração'!C52 -> Academia | E46: ='Configuração'!D52 | F46: ='Configuração'!E52 -> Saúde
B47: 15 | C47: ='Configuração'!F53 -> 1 | D47: ='Configuração'!C53 -> Streaming / Entretenimento | E47: ='Configuração'!D53 -> 59.9 | F47: ='Configuração'!E53 -> Lazer / Diversão
B48: 16 | C48: ='Configuração'!F54 -> 1 | D48: ='Configuração'!C54 -> Assinaturas / SaaS | E48: ='Configuração'!D54 | F48: ='Configuração'!E54 -> Assinaturas
B49: 17 | C49: ='Configuração'!F55 -> 1 | D49: ='Configuração'!C55 -> Educação / Cursos | E49: ='Configuração'!D55 | F49: ='Configuração'!E55 -> Educação
B50: 18 | C50: ='Configuração'!F56 -> 1 | D50: ='Configuração'!C56 -> Investimento Automático (CFL) | E50: ='Configuração'!D56 -> 0 | F50: ='Configuração'!E56 -> Investimentos
B51: 19 | C51: ='Configuração'!F57 -> 1 | D51: ='Configuração'!C57 -> Poupança LP (PELP) | E51: ='Configuração'!D57 -> 0 | F51: ='Configuração'!E57 -> Investimentos
B52: 20 | C52: ='Configuração'!F58 -> 1 | D52: ='Configuração'!C58 -> Doações Fixas | E52: ='Configuração'!D58 -> 0 | F52: ='Configuração'!E58 -> Doações
B53: 21 | C53: ='Configuração'!F59 -> 28 | D53: ='Configuração'!C59 -> Escola Aurora | E53: ='Configuração'!D59 -> 470 | F53: ='Configuração'!E59 -> Educação | G53: ❌
B54: 22 | C54: ='Configuração'!F60 | D54: ='Configuração'!C60 -> Serasa | E54: ='Configuração'!D60 -> 95 | F54: ='Configuração'!E60 -> Dívida | G54: ❌
B55: 23 | C55: ='Configuração'!F61 | D55: ='Configuração'!C61 | E55: ='Configuração'!D61 | F55: ='Configuração'!E61
B56: 24 | C56: ='Configuração'!F62 | D56: ='Configuração'!C62 | E56: ='Configuração'!D62 | F56: ='Configuração'!E62
B57: 25 | C57: ='Configuração'!F63 | D57: ='Configuração'!C63 | E57: ='Configuração'!D63 | F57: ='Configuração'!E63
B58: 26 | C58: ='Configuração'!F64 | D58: ='Configuração'!C64 | E58: ='Configuração'!D64 | F58: ='Configuração'!E64
B59: 27 | C59: ='Configuração'!F65 | D59: ='Configuração'!C65 | E59: ='Configuração'!D65 | F59: ='Configuração'!E65
B60: 28 | C60: ='Configuração'!F66 | D60: ='Configuração'!C66 | E60: ='Configuração'!D66 | F60: ='Configuração'!E66
B61: 29 | C61: ='Configuração'!F67 | D61: ='Configuração'!C67 | E61: ='Configuração'!D67 | F61: ='Configuração'!E67
B62: 30 | C62: ='Configuração'!F68 | D62: ='Configuração'!C68 | E62: ='Configuração'!D68 | F62: ='Configuração'!E68
B63: 🔒 | C63: TOTAL DESPESAS FIXAS | E63: =SUM(E33:E62) -> 1184.9
B65: 🛒 DESPESAS VARIÁVEIS — ANOTE AQUI TODAS AS SUAS DESPESAS DO DIA A DIA
B66: 👉 ANOTE AQUI: compras, alimentação fora, uber, café, roupas, presentes... TUDO que não é fixo. Cada real anotado deduz do seu saldo!
B67: # | C67: Data | D67: Descrição da Despesa | E67: Valor (R$) | F67: Categoria | G67: Jarro | H67: Forma Pgto | I67: Obs
B68: 1 | C68: 13/02/2026 | D68: Moto Taxi (ontem e hoje) | E68: 60 | F68: Transporte | H68: Pix | I68: Gasto incomum
B69: 2 | C69: 46358 | D69: Biscoito para Aurora | E69: 4.5 | F69: Alimentação | H69: Pix
B70: 3 | C70: 13/02/2026 | D70: 2 Hambúrguer Chefão - Gordin | E70: 76 | F70: Alimentação | H70: Pix
B71: 4 | C71: 13/02/2026 | D71: Moto taxi levar aurora no hospital | E71: 20 | F71: Transporte | H71: Pix
B72: 5 | C72: 13/02/2026 | D72: Remédios Aurora tosse e garganta | E72: 101 | F72: Saúde | H72: Pix
B73: 6 | C73: 13/02/2026 | D73: Biscoito para Aurora | E73: 4.5 | F73: Alimentação | H73: Pix
B74: 7 | C74: 13/02/2026 | D74: Lanche | E74: 17 | F74: Alimentação | H74: Pix
B75: 8 | C75: 13/02/2026 | D75: Sebastião (Papelada) | E75: 400 | F75: Documentação | H75: Pix
B76: 9 | C76: 14/02/2026 | D76: Moto taxi ir no supermercado | E76: 30 | F76: Transporte | H76: Pix
B77: 10 | C77: 14/02/2026 | D77: Supermercado | E77: 118.98 | F77: Alimentação | H77: Pix
B78: 11 | C78: 14/02/2026 | D78: Meia | E78: 20 | F78: Vestuário | H78: Pix
B79: 12 | C79: 14/02/2026 | D79: Frauda | E79: 122 | F79: Vestuário | H79: Pix
B80: 13 | C80: 14/02/2026 | D80: Ensaio fotográfico Débora | E80: 150 | F80: Lazer | H80: Pix
B81: 14 | C81: 14/02/2026 | D81: Açaí | E81: 18 | F81: Alimentação | H81: Pix
... B86: 19 | C86: 16/02/2026 | D86: Ensaio fotográfico Débora (restante) | E86: 150 | F86: Lazer | H86: Pix
B87: 20
B88: 21
B89: 22
B90: 23
B91: 24
B92: 25
B93: 26
B94: 27
B95: 28
B96: 29
B97: 30
B98: 31
... B101: 34
B102: 🛒 | C102: TOTAL DESPESAS VARIÁVEIS | E102: =SUM(E68:E101) -> 1637.98
B104: 🏦 SALDO FINAL DO MÊS | D104: =D10 -> 2385.22 | F104: =IF(D9>=0,"✅ Mês positivo! Parabéns!","⚠️ Gastou mais do que ganhou — revise seus gastos") -> ✅ Mês positivo! Parabéns!
B107: 💵 RECEITAS POR FONTE | F107: 💸 DESPESAS POR CATEGORIA
B108: Fonte | C108: Valor | D108: % Total | F108: Categoria | G108: Valor | H108: % Desp. | I108: Alerta
B109: Salário CLT | C109: =SUMIF(F14:F28,"Salário CLT",E14:E28) -> 0 | D109: =IF(E29=0,0,C109/E29) -> 0 | F109: Moradia | G109: =SUMIF(F33:F62,"Moradia",E33:E62)+SUMIF(F68:F101,"Moradia",E68:E101) -> 200 | H109: =IF(D8=0,0,G109/D8) -> 0.070849629 | I109: =IF(H109>0.25,"🔴",IF(H109>0.1,"🟡","🟢")) -> 🟢
B110: Freelance / Projetos | C110: =SUMIF(F14:F28,"Freelance / Projetos",E14:E28) -> 0 | D110: =IF(E29=0,0,C110/E29) -> 0 | F110: Alimentação | G110: =SUMIF(F33:F62,"Alimentação",E33:E62)+SUMIF(F68:F101,"Alimentação",E68:E101) -> 584.98 | H110: =IF(D8=0,0,G110/D8) -> 0.20722808 | I110: =IF(H110>0.25,"🔴",IF(H110>0.1,"🟡","🟢")) -> 🟡
B111: Vendas Online | C111: =SUMIF(F14:F28,"Vendas Online",E14:E28) -> 0 | D111: =IF(E29=0,0,C111/E29) -> 0 | F111: Transporte | G111: =SUMIF(F33:F62,"Transporte",E33:E62)+SUMIF(F68:F101,"Transporte",E68:E101) -> 310 | H111: =IF(D8=0,0,G111/D8) -> 0.10981692 | I111: =IF(H111>0.25,"🔴",IF(H111>0.1,"🟡","🟢")) -> 🟡
...

Sheet Março
B1: 📅 MARÇO 2026 — CONTROLE COMPLETO
B3: 🏦 SALDO EM TEMPO REAL | F3: 🏺 JARROS DO MÊS
B4: 🔙 | C4: Saldo Inicial | D4: =Fevereiro!E10 -> 2385.22 | E4: =D5 -> 0 | F4: 🏠 | G4: NEC (55%) | H4: =D5*'Configuração'!D29 -> 0
B5: 💵 | C5: Total Entradas | D5: =E29 -> 0 | E5: =D5 -> 0 | F5: 💎 | G5: CFL (10%) | H5: =D5*'Configuração'!D30 -> 0
B6: 🔒 | C6: Despesas Fixas | D6: =E63 -> 1184.9 | F6: 🏦 | G6: PELP (10%) | H6: =D5*'Configuração'!D31 -> 0
B7: 🛒 | C7: Despesas Variáveis | D7: =E102 -> 0 | F7: 📚 | G7: EDU (10%) | H7: =D5*'Configuração'!D32 -> 0 | J7: =H4 -> 0 | M7: =C109 -> 0 | N7: =H4 -> 0
B8: 💸 | C8: Total Saídas | D8: =D6+D7 -> 1184.9 | E8: =IF(D5=0,0,D8/D5) -> 0 | F8: 🎉 | G8: DIV (10%) | H8: =D5*'Configuração'!D33 -> 0 | J8: =H5 -> 0 | M8: =C110 -> 0 | N8: =H5 -> 0
B9: 📈 | C9: Saldo do Mês | D9: =D5-D8 -> -1184.9 | E9: =IF(D5=0,0,D9/D5) -> 0 | F9: 🤝 | G9: DOA (5%) | H9: =D5*'Configuração'!D34 -> 0 | J9: =H6 -> 0 | M9: =C111 -> 0 | N9: =H6 -> 0
B10: 🏦 | C10: SALDO FINAL | D10: =D4+D9 -> 1200.32 | E10: =D10 -> 1200.32 | J10: =H7 -> 0 | M10: =C112 -> 0 | N10: =H7 -> 0
J11: =H8 -> 0 | M11: =C113 -> 0 | N11: =H8 -> 0
B12: 💰 RECEITAS DO MÊS — DE ONDE VEM SEU DINHEIRO | J12: =H9 -> 0 | M12: =C114 -> 0 | N12: =H9 -> 0
B13: # | C13: Data | D13: Descrição da Receita | E13: Valor (R$) | F13: Fonte de Receita | G13: Recebido? | H13: Observação | M13: =C115 -> 0
B14: 1 | M14: =C116 -> 0
B15: 2 | M15: =C117 -> 0
B16: 3 | M16: =C118 -> 0
B17: 4
B18: 5
B19: 6
B20: 7
B21: 8
B22: 9 | M22: =G109 -> 200
B23: 10 | M23: =G110 -> 0
B24: 11 | M24: =G111 -> 200
B25: 12 | M25: =G112 -> 0
B26: 13 | M26: =G113 -> 470
B27: 14 | M27: =G114 -> 59.9
B28: 15 | M28: =G115 -> 0
B29: 💰 | C29: TOTAL RECEITAS DO MÊS | E29: =SUM(E14:E28) -> 0 | M29: =G116 -> 160
M30: =G117 -> 0
B31: 🔒 DESPESAS FIXAS — AUTOMÁTICAS DA CONFIGURAÇÃO (edite valores se precisar) | M31: =G118 -> 0
B32: # | C32: Venc. | D32: Descrição | E32: Valor (R$) | F32: Categoria | G32: Pago? ✅/❌ | H32: Observação | M32: =G119 -> 0
B33: 1 | C33: ='Configuração'!F39 -> 5 | D33: ='Configuração'!C39 -> Aluguel / Financiamento | E33: ='Configuração'!D39 | F33: ='Configuração'!E39 -> Moradia | M33: =G120 -> 0
B34: 2 | C34: ='Configuração'!F40 -> 10 | D34: ='Configuração'!C40 -> Condomínio | E34: ='Configuração'!D40 | F34: ='Configuração'!E40 -> Moradia | M34: =G121 -> 0
B35: 3 | C35: ='Configuração'!F41 -> 15 | D35: ='Configuração'!C41 -> IPTU (parcela) | E35: ='Configuração'!D41 | F35: ='Configuração'!E41 -> Impostos | M35: =G122 -> 0
B36: 4 | C36: ='Configuração'!F42 -> 10 | D36: ='Configuração'!C42 -> Energia Elétrica | E36: ='Configuração'!D42 -> 200 | F36: ='Configuração'!E42 -> Moradia
B37: 5 | C37: ='Configuração'!F43 -> 15 | D37: ='Configuração'!C43 -> Água / Saneamento | E37: ='Configuração'!D43 | F37: ='Configuração'!E43 -> Moradia
B38: 6 | C38: ='Configuração'!F44 -> 20 | D38: ='Configuração'!C44 -> Gás | E38: ='Configuração'!D44 | F38: ='Configuração'!E44 -> Moradia
B39: 7 | C39: ='Configuração'!F45 -> 10 | D39: ='Configuração'!C45 -> Internet | E39: ='Configuração'!D45 -> 100 | F39: ='Configuração'!E45 -> Tecnologia
B40: 8 | C40: ='Configuração'!F46 -> 12 | D40: ='Configuração'!C46 -> Celular | E40: ='Configuração'!D46 -> 60 | F40: ='Configuração'!E46 -> Tecnologia
B41: 9 | C41: ='Configuração'!F47 -> 5 | D41: ='Configuração'!C47 -> Plano de Saúde | E41: ='Configuração'!D47 | F41: ='Configuração'!E47 -> Saúde
B42: 10 | C42: ='Configuração'!F48 -> 15 | D42: ='Configuração'!C48 -> Seguro (carro/vida) | E42: ='Configuração'!D48 | F42: ='Configuração'!E48 -> Seguros
B43: 11 | C43: ='Configuração'!F49 -> 1 | D43: ='Configuração'!C49 -> Transporte / Combustível | E43: ='Configuração'!D49 -> 200 | F43: ='Configuração'!E49 -> Transporte
B44: 12 | C44: ='Configuração'!F50 -> 1 | D44: ='Configuração'!C50 -> Supermercado (base) | E44: ='Configuração'!D50 | F44: ='Configuração'!E50 -> Alimentação
B45: 13 | C45: ='Configuração'!F51 -> 1 | D45: ='Configuração'!C51 -> Farmácia / Medicamentos | E45: ='Configuração'!D51 | F45: ='Configuração'!E51 -> Saúde
B46: 14 | C46: ='Configuração'!F52 -> 5 | D46: ='Configuração'!C52 -> Academia | E46: ='Configuração'!D52 | F46: ='Configuração'!E52 -> Saúde
B47: 15 | C47: ='Configuração'!F53 -> 1 | D47: ='Configuração'!C53 -> Streaming / Entretenimento | E47: ='Configuração'!D53 -> 59.9 | F47: ='Configuração'!E53 -> Lazer / Diversão
... B62: 30 | C62: ='Configuração'!F68 | D62: ='Configuração'!C68 | E62: ='Configuração'!D68 | F62: ='Configuração'!E68
B63: 🔒 | C63: TOTAL DESPESAS FIXAS | E63: =SUM(E33:E62) -> 1184.9
B65: 🛒 DESPESAS VARIÁVEIS — ANOTE AQUI TODAS AS SUAS DESPESAS DO DIA A DIA
B66: 👉 ANOTE AQUI: compras, alimentação fora, uber, café, roupas, presentes... TUDO que não é fixo. Cada real anotado deduz do seu saldo!
B67: # | C67: Data | D67: Descrição da Despesa | E67: Valor (R$) | F67: Categoria | G67: Jarro | H67: Forma Pgto | I67: Obs
B68: 1
B69: 2
B70: 3
B71: 4
B72: 5
B73: 6
B74: 7
B75: 8
B76: 9
B77: 10
B78: 11
B79: 12
... B101: 34
B102: 🛒 | C102: TOTAL DESPESAS VARIÁVEIS | E102: =SUM(E68:E101) -> 0
B104: 🏦 SALDO FINAL DO MÊS | D104: =D10 -> 1200.32 | F104: =IF(D9>=0,"✅ Mês positivo! Parabéns!","⚠️ Gastou mais do que ganhou — revise seus gastos") -> ⚠️ Gastou mais do que ganhou — revise seus gastos
B107: 💵 RECEITAS POR FONTE | F107: 💸 DESPESAS POR CATEGORIA
B108: Fonte | C108: Valor | D108: % Total | F108: Categoria | G108: Valor | H108: % Desp. | I108: Alerta
B109: Salário CLT | C109: =SUMIF(F14:F28,"Salário CLT",E14:E28) -> 0 | D109: =IF(E29=0,0,C109/E29) -> 0 | F109: Moradia | G109: =SUMIF(F33:F62,"Moradia",E33:E62)+SUMIF(F68:F101,"Moradia",E68:E101) -> 200 | H109: =IF(D8=0,0,G109/D8) -> 0.16879062 | I109: =IF(H109>0.25,"🔴",IF(H109>0.1,"🟡","🟢")) -> 🟡
B110: Freelance / Projetos | C110: =SUMIF(F14:F28,"Freelance / Projetos",E14:E28) -> 0 | D110: =IF(E29=0,0,C110/E29) -> 0 | F110: Alimentação | G110: =SUMIF(F33:F62,"Alimentação",E33:E62)+SUMIF(F68:F101,"Alimentação",E68:E101) -> 0 | H110: =IF(D8=0,0,G110/D8) -> 0 | I110: =IF(H110>0.25,"🔴",IF(H110>0.1,"🟡","🟢")) -> 🟢
B111: Vendas Online | C111: =SUMIF(F14:F28,"Vendas Online",E14:E28) -> 0 | D111: =IF(E29=0,0,C111/E29) -> 0 | F111: Transporte | G111: =SUMIF(F33:F62,"Transporte",E33:E62)+SUMIF(F68:F101,"Transporte",E68:E101) -> 200 | H111: =IF(D8=0,0,G111/D8) -> 0.16879062 | I111: =IF(H111>0.25,"🔴",IF(H111>0.1,"🟡","🟢")) -> 🟡
B112: Consultoria | C112: =SUMIF(F14:F28,"Consultoria",E14:E28) -> 0 | D112: =IF(E29=0,0,C112/E29) -> 0 | F112: Saúde | G112: =SUMIF(F33:F62,"Saúde",E33:E62)+SUMIF(F68:F101,"Saúde",E68:E101) -> 0 | H112: =IF(D8=0,0,G112/D8) -> 0 | I112: =IF(H112>0.25,"🔴",IF(H112>0.1,"🟡","🟢")) -> 🟢
B113: Rendimentos / Investimentos | C113: =SUMIF(F14:F28,"Rendimentos / Investimentos",E14:E28) -> 0 | D113: =IF(E29=0,0,C113/E29) -> 0 | F113: Educação | G113: =SUMIF(F33:F62,"Educação",E33:E62)+SUMIF(F68:F101,"Educação",E68:E101) -> 470 | H113: =IF(D8=0,0,G113/D8) -> 0.39665795 | I113: =IF(H113>0.25,"🔴",IF(H113>0.1,"🟡","🟢")) -> 🔴
B114: Aluguel Recebido | C114: =SUMIF(F14:F28,"Aluguel Recebido",E14:E28) -> 0 | D114: =IF(E29=0,0,C114/E29) -> 0 | F114: Lazer / Diversão | G114: =SUMIF(F33:F62,"Lazer / Diversão",E33:E62)+SUMIF(F68:F101,"Lazer / Diversão",E68:E101) -> 59.9 | H114: =IF(D8=0,0,G114/D8) -> 0.050552789 | I114: =IF(H114>0.25,"🔴",IF(H114>0.1,"🟡","🟢")) -> 🟢
B115: Comissões | C115: =SUMIF(F14:F28,"Comissões",E14:E28) -> 0 | D115: =IF(E29=0,0,C115/E29) -> 0 | F115: Vestuário | G115: =SUMIF(F33:F62,"Vestuário",E33:E62)+SUMIF(F68:F101,"Vestuário",E68:E101) -> 0 | H115: =IF(D8=0,0,G115/D8) -> 0 | I115: =IF(H115>0.25,"🔴",IF(H115>0.1,"🟡","🟢")) -> 🟢
B116: Bônus / Participação | C116: =SUMIF(F14:F28,"Bônus / Participação",E14:E28) -> 0 | D116: =IF(E29=0,0,C116/E29) -> 0 | F116: Tecnologia | G116: =SUMIF(F33:F62,"Tecnologia",E33:E62)+SUMIF(F68:F101,"Tecnologia",E68:E101) -> 160 | H116: =IF(D8=0,0,G116/D8) -> 0.13503249 | I116: =IF(H116>0.25,"🔴",IF(H116>0.1,"🟡","🟢")) -> 🟡
B117: Renda Extra / Bico | C117: =SUMIF(F14:F28,"Renda Extra / Bico",E14:E28) -> 0 | D117: =IF(E29=0,0,C117/E29) -> 0 | F117: Assinaturas | G117: =SUMIF(F33:F62,"Assinaturas",E33:E62)+SUMIF(F68:F101,"Assinaturas",E68:E101) -> 0 | H117: =IF(D8=0,0,G117/D8) -> 0 | I117: =IF(H117>0.25,"🔴",IF(H117>0.1,"🟡","🟢")) -> 🟢
B118: Outros | C118: =SUMIF(F14:F28,"Outros",E14:E28) -> 0 | D118: =IF(E29=0,0,C118/E29) -> 0 | F118: Seguros | G118: =SUMIF(F33:F62,"Seguros",E33:E62)+SUMIF(F68:F101,"Seguros",E68:E101) -> 0 | H118: =IF(D8=0,0,G118/D8) -> 0 | I118: =IF(H118>0.25,"🔴",IF(H118>0.1,"🟡","🟢")) -> 🟢
F119: Impostos | G119: =SUMIF(F33:F62,"Impostos",E33:E62)+SUMIF(F68:F101,"Impostos",E68:E101) -> 0 | H119: =IF(D8=0,0,G119/D8) -> 0 | I119: =IF(H119>0.25,"🔴",IF(H119>0.1,"🟡","🟢")) -> 🟢
F120: Investimentos | G120: =SUMIF(F33:F62,"Investimentos",E33:E62)+SUMIF(F68:F101,"Investimentos",E68:E101) -> 0 | H120: =IF(D8=0,0,G120/D8) -> 0 | I120: =IF(H120>0.25,"🔴",IF(H120>0.1,"🟡","🟢")) -> 🟢
F121: Doações | G121: =SUMIF(F33:F62,"Doações",E33:E62)+SUMIF(F68:F101,"Doações",E68:E101) -> 0 | H121: =IF(D8=0,0,G121/D8) -> 0 | I121: =IF(H121>0.25,"🔴",IF(H121>0.1,"🟡","🟢")) -> 🟢
F122: Outros | G122: =SUMIF(F33:F62,"Outros",E33:E62)+SUMIF(F68:F101,"Outros",E68:E101) -> 0 | H122: =IF(D8=0,0,G122/D8) -> 0 | I122: =IF(H122>0.25,"🔴",IF(H122>0.1,"🟡","🟢")) -> 🟢

Sheet Abril
B1: 📅 ABRIL 2026 — CONTROLE COMPLETO
B3: 🏦 SALDO EM TEMPO REAL | F3: 🏺 JARROS DO MÊS
B4: 🔙 | C4: Saldo Inicial | D4: ='Março'!E10 -> 1200.32 | E4: =D5 -> 0 | F4: 🏠 | G4: NEC (55%) | H4: =D5*'Configuração'!D29 -> 0
B5: 💵 | C5: Total Entradas | D5: =E29 -> 0 | E5: =D5 -> 0 | F5: 💎 | G5: CFL (10%) | H5: =D5*'Configuração'!D30 -> 0
B6: 🔒 | C6: Despesas Fixas | D6: =E63 -> 1184.9 | F6: 🏦 | G6: PELP (10%) | H6: =D5*'Configuração'!D31 -> 0
B7: 🛒 | C7: Despesas Variáveis | D7: =E102 -> 0 | F7: 📚 | G7: EDU (10%) | H7: =D5*'Configuração'!D32 -> 0 | J7: =H4 -> 0 | M7: =C109 -> 0 | N7: =H4 -> 0
B8: 💸 | C8: Total Saídas | D8: =D6+D7 -> 1184.9 | E8: =IF(D5=0,0,D8/D5) -> 0 | F8: 🎉 | G8: DIV (10%) | H8: =D5*'Configuração'!D33 -> 0 | J8: =H5 -> 0 | M8: =C110 -> 0 | N8: =H5 -> 0
B9: 📈 | C9: Saldo do Mês | D9: =D5-D8 -> -1184.9 | E9: =IF(D5=0,0,D9/D5) -> 0 | F9: 🤝 | G9: DOA (5%) | H9: =D5*'Configuração'!D34 -> 0 | J9: =H6 -> 0 | M9: =C111 -> 0 | N9: =H6 -> 0
B10: 🏦 | C10: SALDO FINAL | D10: =D4+D9 -> 15.42 | E10: =D10 -> 15.42 | J10: =H7 -> 0 | M10: =C112 -> 0 | N10: =H7 -> 0
J11: =H8 -> 0 | M11: =C113 -> 0 | N11: =H8 -> 0
B12: 💰 RECEITAS DO MÊS — DE ONDE VEM SEU DINHEIRO | J12: =H9 -> 0 | M12: =C114 -> 0 | N12: =H9 -> 0
B13: # | C13: Data | D13: Descrição da Receita | E13: Valor (R$) | F13: Fonte de Receita | G13: Recebido? | H13: Observação | M13: =C115 -> 0
B14: 1 | M14: =C116 -> 0
B15: 2 | M15: =C117 -> 0
B16: 3 | M16: =C118 -> 0
B17: 4
B18: 5
B19: 6
B20: 7
B21: 8
B22: 9 | M22: =G109 -> 200
B23: 10 | M23: =G110 -> 0
B24: 11 | M24: =G111 -> 200
B25: 12 | M25: =G112 -> 0
B26: 13 | M26: =G113 -> 470
B27: 14 | M27: =G114 -> 59.9
B28: 15 | M28: =G115 -> 0
B29: 💰 | C29: TOTAL RECEITAS DO MÊS | E29: =SUM(E14:E28) -> 0 | M29: =G116 -> 160
M30: =G117 -> 0
B31: 🔒 DESPESAS FIXAS — AUTOMÁTICAS DA CONFIGURAÇÃO (edite valores se precisar) | M31: =G118 -> 0
B32: # | C32: Venc. | D32: Descrição | E32: Valor (R$) | F32: Categoria | G32: Pago? ✅/❌ | H32: Observação | M32: =G119 -> 0
B33: 1 | C33: ='Configuração'!F39 -> 5 | D33: ='Configuração'!C39 -> Aluguel / Financiamento | E33: ='Configuração'!D39 | F33: ='Configuração'!E39 -> Moradia | M33: =G120 -> 0
B34: 2 | C34: ='Configuração'!F40 -> 10 | D34: ='Configuração'!C40 -> Condomínio | E34: ='Configuração'!D40 | F34: ='Configuração'!E40 -> Moradia | M34: =G121 -> 0
B35: 3 | C35: ='Configuração'!F41 -> 15 | D35: ='Configuração'!C41 -> IPTU (parcela) | E35: ='Configuração'!D41 | F35: ='Configuração'!E41 -> Impostos | M35: =G122 -> 0
B36: 4 | C36: ='Configuração'!F42 -> 10 | D36: ='Configuração'!C42 -> Energia Elétrica | E36: ='Configuração'!D42 -> 200 | F36: ='Configuração'!E42 -> Moradia
B37: 5 | C37: ='Configuração'!F43 -> 15 | D37: ='Configuração'!C43 -> Água / Saneamento | E37: ='Configuração'!D43 | F37: ='Configuração'!E43 -> Moradia
B38: 6 | C38: ='Configuração'!F44 -> 20 | D38: ='Configuração'!C44 -> Gás | E38: ='Configuração'!D44 | F38: ='Configuração'!E44 -> Moradia
B39: 7 | C39: ='Configuração'!F45 -> 10 | D39: ='Configuração'!C45 -> Internet | E39: ='Configuração'!D45 -> 100 | F39: ='Configuração'!E45 -> Tecnologia
B40: 8 | C40: ='Configuração'!F46 -> 12 | D40: ='Configuração'!C46 -> Celular | E40: ='Configuração'!D46 -> 60 | F40: ='Configuração'!E46 -> Tecnologia
B41: 9 | C41: ='Configuração'!F47 -> 5 | D41: ='Configuração'!C47 -> Plano de Saúde | E41: ='Configuração'!D47 | F41: ='Configuração'!E47 -> Saúde
B42: 10 | C42: ='Configuração'!F48 -> 15 | D42: ='Configuração'!C48 -> Seguro (carro/vida) | E42: ='Configuração'!D48 | F42: ='Configuração'!E48 -> Seguros
B43: 11 | C43: ='Configuração'!F49 -> 1 | D43: ='Configuração'!C49 -> Transporte / Combustível | E43: ='Configuração'!D49 -> 200 | F43: ='Configuração'!E49 -> Transporte
B44: 12 | C44: ='Configuração'!F50 -> 1 | D44: ='Configuração'!C50 -> Supermercado (base) | E44: ='Configuração'!D50 | F44: ='Configuração'!E50 -> Alimentação
B45: 13 | C45: ='Configuração'!F51 -> 1 | D45: ='Configuração'!C51 -> Farmácia / Medicamentos | E45: ='Configuração'!D51 | F45: ='Configuração'!E51 -> Saúde
B46: 14 | C46: ='Configuração'!F52 -> 5 | D46: ='Configuração'!C52 -> Academia | E46: ='Configuração'!D52 | F46: ='Configuração'!E52 -> Saúde
B47: 15 | C47: ='Configuração'!F53 -> 1 | D47: ='Configuração'!C53 -> Streaming / Entretenimento | E47: ='Configuração'!D53 -> 59.9 | F47: ='Configuração'!E53 -> Lazer / Diversão
... B62: 30 | C62: ='Configuração'!F68 | D62: ='Configuração'!C68 | E62: ='Configuração'!D68 | F62: ='Configuração'!E68
B63: 🔒 | C63: TOTAL DESPESAS FIXAS | E63: =SUM(E33:E62) -> 1184.9
B65: 🛒 DESPESAS VARIÁVEIS — ANOTE AQUI TODAS AS SUAS DESPESAS DO DIA A DIA
B66: 👉 ANOTE AQUI: compras, alimentação fora, uber, café, roupas, presentes... TUDO que não é fixo. Cada real anotado deduz do seu saldo!
B67: # | C67: Data | D67: Descrição da Despesa | E67: Valor (R$) | F67: Categoria | G67: Jarro | H67: Forma Pgto | I67: Obs
B68: 1
B69: 2
B70: 3
B71: 4
B72: 5
B73: 6
B74: 7
B75: 8
B76: 9
B77: 10
B78: 11
B79: 12
... B101: 34
B102: 🛒 | C102: TOTAL DESPESAS VARIÁVEIS | E102: =SUM(E68:E101) -> 0
B104: 🏦 SALDO FINAL DO MÊS | D104: =D10 -> 15.42 | F104: =IF(D9>=0,"✅ Mês positivo! Parabéns!","⚠️ Gastou mais do que ganhou — revise seus gastos") -> ⚠️ Gastou mais do que ganhou — revise seus gastos
B107: 💵 RECEITAS POR FONTE | F107: 💸 DESPESAS POR CATEGORIA
B108: Fonte | C108: Valor | D108: % Total | F108: Categoria | G108: Valor | H108: % Desp. | I108: Alerta
B109: Salário CLT | C109: =SUMIF(F14:F28,"Salário CLT",E14:E28) -> 0 | D109: =IF(E29=0,0,C109/E29) -> 0 | F109: Moradia | G109: =SUMIF(F33:F62,"Moradia",E33:E62)+SUMIF(F68:F101,"Moradia",E68:E101) -> 200 | H109: =IF(D8=0,0,G109/D8) -> 0.16879062 | I109: =IF(H109>0.25,"🔴",IF(H109>0.1,"🟡","🟢")) -> 🟡
B110: Freelance / Projetos | C110: =SUMIF(F14:F28,"Freelance / Projetos",E14:E28) -> 0 | D110: =IF(E29=0,0,C110/E29) -> 0 | F110: Alimentação | G110: =SUMIF(F33:F62,"Alimentação",E33:E62)+SUMIF(F68:F101,"Alimentação",E68:E101) -> 0 | H110: =IF(D8=0,0,G110/D8) -> 0 | I110: =IF(H110>0.25,"🔴",IF(H110>0.1,"🟡","🟢")) -> 🟢
B111: Vendas Online | C111: =SUMIF(F14:F28,"Vendas Online",E14:E28) -> 0 | D111: =IF(E29=0,0,C111/E29) -> 0 | F111: Transporte | G111: =SUMIF(F33:F62,"Transporte",E33:E62)+SUMIF(F68:F101,"Transporte",E68:E101) -> 200 | H111: =IF(D8=0,0,G111/D8) -> 0.16879062 | I111: =IF(H111>0.25,"🔴",IF(H111>0.1,"🟡","🟢")) -> 🟡
B112: Consultoria | C112: =SUMIF(F14:F28,"Consultoria",E14:E28) -> 0 | D112: =IF(E29=0,0,C112/E29) -> 0 | F112: Saúde | G112: =SUMIF(F33:F62,"Saúde",E33:E62)+SUMIF(F68:F101,"Saúde",E68:E101) -> 0 | H112: =IF(D8=0,0,G112/D8) -> 0 | I112: =IF(H112>0.25,"🔴",IF(H112>0.1,"🟡","🟢")) -> 🟢
B113: Rendimentos / Investimentos | C113: =SUMIF(F14:F28,"Rendimentos / Investimentos",E14:E28) -> 0 | D113: =IF(E29=0,0,C113/E29) -> 0 | F113: Educação | G113: =SUMIF(F33:F62,"Educação",E33:E62)+SUMIF(F68:F101,"Educação",E68:E101) -> 470 | H113: =IF(D8=0,0,G113/D8) -> 0.39665795 | I113: =IF(H113>0.25,"🔴",IF(H113>0.1,"🟡","🟢")) -> 🔴
B114: Aluguel Recebido | C114: =SUMIF(F14:F28,"Aluguel Recebido",E14:E28) -> 0 | D114: =IF(E29=0,0,C114/E29) -> 0 | F114: Lazer / Diversão | G114: =SUMIF(F33:F62,"Lazer / Diversão",E33:E62)+SUMIF(F68:F101,"Lazer / Diversão",E68:E101) -> 59.9 | H114: =IF(D8=0,0,G114/D8) -> 0.050552789 | I114: =IF(H114>0.25,"🔴",IF(H114>0.1,"🟡","🟢")) -> 🟢
B115: Comissões | C115: =SUMIF(F14:F28,"Comissões",E14:E28) -> 0 | D115: =IF(E29=0,0,C115/E29) -> 0 | F115: Vestuário | G115: =SUMIF(F33:F62,"Vestuário",E33:E62)+SUMIF(F68:F101,"Vestuário",E68:E101) -> 0 | H115: =IF(D8=0,0,G115/D8) -> 0 | I115: =IF(H115>0.25,"🔴",IF(H115>0.1,"🟡","🟢")) -> 🟢
B116: Bônus / Participação | C116: =SUMIF(F14:F28,"Bônus / Participação",E14:E28) -> 0 | D116: =IF(E29=0,0,C116/E29) -> 0 | F116: Tecnologia | G116: =SUMIF(F33:F62,"Tecnologia",E33:E62)+SUMIF(F68:F101,"Tecnologia",E68:E101) -> 160 | H116: =IF(D8=0,0,G116/D8) -> 0.13503249 | I116: =IF(H116>0.25,"🔴",IF(H116>0.1,"🟡","🟢")) -> 🟡
B117: Renda Extra / Bico | C117: =SUMIF(F14:F28,"Renda Extra / Bico",E14:E28) -> 0 | D117: =IF(E29=0,0,C117/E29) -> 0 | F117: Assinaturas | G117: =SUMIF(F33:F62,"Assinaturas",E33:E62)+SUMIF(F68:F101,"Assinaturas",E68:E101) -> 0 | H117: =IF(D8=0,0,G117/D8) -> 0 | I117: =IF(H117>0.25,"🔴",IF(H117>0.1,"🟡","🟢")) -> 🟢
B118: Outros | C118: =SUMIF(F14:F28,"Outros",E14:E28) -> 0 | D118: =IF(E29=0,0,C118/E29) -> 0 | F118: Seguros | G118: =SUMIF(F33:F62,"Seguros",E33:E62)+SUMIF(F68:F101,"Seguros",E68:E101) -> 0 | H118: =IF(D8=0,0,G118/D8) -> 0 | I118: =IF(H118>0.25,"🔴",IF(H118>0.1,"🟡","🟢")) -> 🟢
F119: Impostos | G119: =SUMIF(F33:F62,"Impostos",E33:E62)+SUMIF(F68:F101,"Impostos",E68:E101) -> 0 | H119: =IF(D8=0,0,G119/D8) -> 0 | I119: =IF(H119>0.25,"🔴",IF(H119>0.1,"🟡","🟢")) -> 🟢
F120: Investimentos | G120: =SUMIF(F33:F62,"Investimentos",E33:E62)+SUMIF(F68:F101,"Investimentos",E68:E101) -> 0 | H120: =IF(D8=0,0,G120/D8) -> 0 | I120: =IF(H120>0.25,"🔴",IF(H120>0.1,"🟡","🟢")) -> 🟢
F121: Doações | G121: =SUMIF(F33:F62,"Doações",E33:E62)+SUMIF(F68:F101,"Doações",E68:E101) -> 0 | H121: =IF(D8=0,0,G121/D8) -> 0 | I121: =IF(H121>0.25,"🔴",IF(H121>0.1,"🟡","🟢")) -> 🟢
F122: Outros | G122: =SUMIF(F33:F62,"Outros",E33:E62)+SUMIF(F68:F101,"Outros",E68:E101) -> 0 | H122: =IF(D8=0,0,G122/D8) -> 0 | I122: =IF(H122>0.25,"🔴",IF(H122>0.1,"🟡","🟢")) -> 🟢

Sheet Maio
B1: 📅 MAIO 2026 — CONTROLE COMPLETO
B3: 🏦 SALDO EM TEMPO REAL | F3: 🏺 JARROS DO MÊS
B4: 🔙 | C4: Saldo Inicial | D4: =Abril!E10 -> 15.42 | E4: =D5 -> 0 | F4: 🏠 | G4: NEC (55%) | H4: =D5*'Configuração'!D29 -> 0
B5: 💵 | C5: Total Entradas | D5: =E29 -> 0 | E5: =D5 -> 0 | F5: 💎 | G5: CFL (10%) | H5: =D5*'Configuração'!D30 -> 0
B6: 🔒 | C6: Despesas Fixas | D6: =E63 -> 1184.9 | F6: 🏦 | G6: PELP (10%) | H6: =D5*'Configuração'!D31 -> 0
B7: 🛒 | C7: Despesas Variáveis | D7: =E102 -> 0 | F7: 📚 | G7: EDU (10%) | H7: =D5*'Configuração'!D32 -> 0 | J7: =H4 -> 0 | M7: =C109 -> 0 | N7: =H4 -> 0
B8: 💸 | C8: Total Saídas | D8: =D6+D7 -> 1184.9 | E8: =IF(D5=0,0,D8/D5) -> 0 | F8: 🎉 | G8: DIV (10%) | H8: =D5*'Configuração'!D33 -> 0 | J8: =H5 -> 0 | M8: =C110 -> 0 | N8: =H5 -> 0
B9: 📈 | C9: Saldo do Mês | D9: =D5-D8 -> -1184.9 | E9: =IF(D5=0,0,D9/D5) -> 0 | F9: 🤝 | G9: DOA (5%) | H9: =D5*'Configuração'!D34 -> 0 | J9: =H6 -> 0 | M9: =C111 -> 0 | N9: =H6 -> 0
B10: 🏦 | C10: SALDO FINAL | D10: =D4+D9 -> -1169.48 | E10: =D10 -> -1169.48 | J10: =H7 -> 0 | M10: =C112 -> 0 | N10: =H7 -> 0
J11: =H8 -> 0 | M11: =C113 -> 0 | N11: =H8 -> 0
B12: 💰 RECEITAS DO MÊS — DE ONDE VEM SEU DINHEIRO | J12: =H9 -> 0 | M12: =C114 -> 0 | N12: =H9 -> 0
B13: # | C13: Data | D13: Descrição da Receita | E13: Valor (R$) | F13: Fonte de Receita | G13: Recebido? | H13: Observação | M13: =C115 -> 0
B14: 1 | M14: =C116 -> 0
B15: 2 | M15: =C117 -> 0
B16: 3 | M16: =C118 -> 0
B17: 4
B18: 5
B19: 6
B20: 7
B21: 8
B22: 9 | M22: =G109 -> 200
B23: 10 | M23: =G110 -> 0
B24: 11 | M24: =G111 -> 200
B25: 12 | M25: =G112 -> 0
B26: 13 | M26: =G113 -> 470
B27: 14 | M27: =G114 -> 59.9
B28: 15 | M28: =G115 -> 0
B29: 💰 | C29: TOTAL RECEITAS DO MÊS | E29: =SUM(E14:E28) -> 0 | M29: =G116 -> 160
M30: =G117 -> 0
B31: 🔒 DESPESAS FIXAS — AUTOMÁTICAS DA CONFIGURAÇÃO (edite valores se precisar) | M31: =G118 -> 0
B32: # | C32: Venc. | D32: Descrição | E32: Valor (R$) | F32: Categoria | G32: Pago? ✅/❌ | H32: Observação | M32: =G119 -> 0
B33: 1 | C33: ='Configuração'!F39 -> 5 | D33: ='Configuração'!C39 -> Aluguel / Financiamento | E33: ='Configuração'!D39 | F33: ='Configuração'!E39 -> Moradia | M33: =G120 -> 0
B34: 2 | C34: ='Configuração'!F40 -> 10 | D34: ='Configuração'!C40 -> Condomínio | E34: ='Configuração'!D40 | F34: ='Configuração'!E40 -> Moradia | M34: =G121 -> 0
B35: 3 | C35: ='Configuração'!F41 -> 15 | D35: ='Configuração'!C41 -> IPTU (parcela) | E35: ='Configuração'!D41 | F35: ='Configuração'!E41 -> Impostos | M35: =G122 -> 0
B36: 4 | C36: ='Configuração'!F42 -> 10 | D36: ='Configuração'!C42 -> Energia Elétrica | E36: ='Configuração'!D42 -> 200 | F36: ='Configuração'!E42 -> Moradia
B37: 5 | C37: ='Configuração'!F43 -> 15 | D37: ='Configuração'!C43 -> Água / Saneamento | E37: ='Configuração'!D43 | F37: ='Configuração'!E43 -> Moradia
B38: 6 | C38: ='Configuração'!F44 -> 20 | D38: ='Configuração'!C44 -> Gás | E38: ='Configuração'!D44 | F38: ='Configuração'!E44 -> Moradia
B39: 7 | C39: ='Configuração'!F45 -> 10 | D39: ='Configuração'!C45 -> Internet | E39: ='Configuração'!D45 -> 100 | F39: ='Configuração'!E45 -> Tecnologia
B40: 8 | C40: ='Configuração'!F46 -> 12 | D40: ='Configuração'!C46 -> Celular | E40: ='Configuração'!D46 -> 60 | F40: ='Configuração'!E46 -> Tecnologia
B41: 9 | C41: ='Configuração'!F47 -> 5 | D41: ='Configuração'!C47 -> Plano de Saúde | E41: ='Configuração'!D47 | F41: ='Configuração'!E47 -> Saúde
B42: 10 | C42: ='Configuração'!F48 -> 15 | D42: ='Configuração'!C48 -> Seguro (carro/vida) | E42: ='Configuração'!D48 | F42: ='Configuração'!E48 -> Seguros
B43: 11 | C43: ='Configuração'!F49 -> 1 | D43: ='Configuração'!C49 -> Transporte / Combustível | E43: ='Configuração'!D49 -> 200 | F43: ='Configuração'!E49 -> Transporte
B44: 12 | C44: ='Configuração'!F50 -> 1 | D44: ='Configuração'!C50 -> Supermercado (base) | E44: ='Configuração'!D50 | F44: ='Configuração'!E50 -> Alimentação
B45: 13 | C45: ='Configuração'!F51 -> 1 | D45: ='Configuração'!C51 -> Farmácia / Medicamentos | E45: ='Configuração'!D51 | F45: ='Configuração'!E51 -> Saúde
B46: 14 | C46: ='Configuração'!F52 -> 5 | D46: ='Configuração'!C52 -> Academia | E46: ='Configuração'!D52 | F46: ='Configuração'!E52 -> Saúde
B47: 15 | C47: ='Configuração'!F53 -> 1 | D47: ='Configuração'!C53 -> Streaming / Entretenimento | E47: ='Configuração'!D53 -> 59.9 | F47: ='Configuração'!E53 -> Lazer / Diversão
... B62: 30 | C62: ='Configuração'!F68 | D62: ='Configuração'!C68 | E62: ='Configuração'!D68 | F62: ='Configuração'!E68
B63: 🔒 | C63: TOTAL DESPESAS FIXAS | E63: =SUM(E33:E62) -> 1184.9
B65: 🛒 DESPESAS VARIÁVEIS — ANOTE AQUI TODAS AS SUAS DESPESAS DO DIA A DIA
B66: 👉 ANOTE AQUI: compras, alimentação fora, uber, café, roupas, presentes... TUDO que não é fixo. Cada real anotado deduz do seu saldo!
B67: # | C67: Data | D67: Descrição da Despesa | E67: Valor (R$) | F67: Categoria | G67: Jarro | H67: Forma Pgto | I67: Obs
B68: 1
B69: 2
B70: 3
B71: 4
B72: 5
B73: 6
B74: 7
B75: 8
B76: 9
B77: 10
B78: 11
B79: 12
... B101: 34
B102: 🛒 | C102: TOTAL DESPESAS VARIÁVEIS | E102: =SUM(E68:E101) -> 0
B104: 🏦 SALDO FINAL DO MÊS | D104: =D10 -> -1169.48 | F104: =IF(D9>=0,"✅ Mês positivo! Parabéns!","⚠️ Gastou mais do que ganhou — revise seus gastos") -> ⚠️ Gastou mais do que ganhou — revise seus gastos
B107: 💵 RECEITAS POR FONTE | F107: 💸 DESPESAS POR CATEGORIA
B108: Fonte | C108: Valor | D108: % Total | F108: Categoria | G108: Valor | H108: % Desp. | I108: Alerta
B109: Salário CLT | C109: =SUMIF(F14:F28,"Salário CLT",E14:E28) -> 0 | D109: =IF(E29=0,0,C109/E29) -> 0 | F109: Moradia | G109: =SUMIF(F33:F62,"Moradia",E33:E62)+SUMIF(F68:F101,"Moradia",E68:E101) -> 200 | H109: =IF(D8=0,0,G109/D8) -> 0.16879062 | I109: =IF(H109>0.25,"🔴",IF(H109>0.1,"🟡","🟢")) -> 🟡
B110: Freelance / Projetos | C110: =SUMIF(F14:F28,"Freelance / Projetos",E14:E28) -> 0 | D110: =IF(E29=0,0,C110/E29) -> 0 | F110: Alimentação | G110: =SUMIF(F33:F62,"Alimentação",E33:E62)+SUMIF(F68:F101,"Alimentação",E68:E101) -> 0 | H110: =IF(D8=0,0,G110/D8) -> 0 | I110: =IF(H110>0.25,"🔴",IF(H110>0.1,"🟡","🟢")) -> 🟢
B111: Vendas Online | C111: =SUMIF(F14:F28,"Vendas Online",E14:E28) -> 0 | D111: =IF(E29=0,0,C111/E29) -> 0 | F111: Transporte | G111: =SUMIF(F33:F62,"Transporte",E33:E62)+SUMIF(F68:F101,"Transporte",E68:E101) -> 200 | H111: =IF(D8=0,0,G111/D8) -> 0.16879062 | I111: =IF(H111>0.25,"🔴",IF(H111>0.1,"🟡","🟢")) -> 🟡
B112: Consultoria | C112: =SUMIF(F14:F28,"Consultoria",E14:E28) -> 0 | D112: =IF(E29=0,0,C112/E29) -> 0 | F112: Saúde | G112: =SUMIF(F33:F62,"Saúde",E33:E62)+SUMIF(F68:F101,"Saúde",E68:E101) -> 0 | H112: =IF(D8=0,0,G112/D8) -> 0 | I112: =IF(H112>0.25,"🔴",IF(H112>0.1,"🟡","🟢")) -> 🟢
B113: Rendimentos / Investimentos | C113: =SUMIF(F14:F28,"Rendimentos / Investimentos",E14:E28) -> 0 | D113: =IF(E29=0,0,C113/E29) -> 0 | F113: Educação | G113: =SUMIF(F33:F62,"Educação",E33:E62)+SUMIF(F68:F101,"Educação",E68:E101) -> 470 | H113: =IF(D8=0,0,G113/D8) -> 0.39665795 | I113: =IF(H113>0.25,"🔴",IF(H113>0.1,"🟡","🟢")) -> 🔴
B114: Aluguel Recebido | C114: =SUMIF(F14:F28,"Aluguel Recebido",E14:E28) -> 0 | D114: =IF(E29=0,0,C114/E29) -> 0 | F114: Lazer / Diversão | G114: =SUMIF(F33:F62,"Lazer / Diversão",E33:E62)+SUMIF(F68:F101,"Lazer / Diversão",E68:E101) -> 59.9 | H114: =IF(D8=0,0,G114/D8) -> 0.050552789 | I114: =IF(H114>0.25,"🔴",IF(H114>0.1,"🟡","🟢")) -> 🟢
B115: Comissões | C115: =SUMIF(F14:F28,"Comissões",E14:E28) -> 0 | D115: =IF(E29=0,0,C115/E29) -> 0 | F115: Vestuário | G115: =SUMIF(F33:F62,"Vestuário",E33:E62)+SUMIF(F68:F101,"Vestuário",E68:E101) -> 0 | H115: =IF(D8=0,0,G115/D8) -> 0 | I115: =IF(H115>0.25,"🔴",IF(H115>0.1,"🟡","🟢")) -> 🟢
B116: Bônus / Participação | C116: =SUMIF(F14:F28,"Bônus / Participação",E14:E28) -> 0 | D116: =IF(E29=0,0,C116/E29) -> 0 | F116: Tecnologia | G116: =SUMIF(F33:F62,"Tecnologia",E33:E62)+SUMIF(F68:F101,"Tecnologia",E68:E101) -> 160 | H116: =IF(D8=0,0,G116/D8) -> 0.13503249 | I116: =IF(H116>0.25,"🔴",IF(H116>0.1,"🟡","🟢")) -> 🟡
B117: Renda Extra / Bico | C117: =SUMIF(F14:F28,"Renda Extra / Bico",E14:E28) -> 0 | D117: =IF(E29=0,0,C117/E29) -> 0 | F117: Assinaturas | G117: =SUMIF(F33:F62,"Assinaturas",E33:E62)+SUMIF(F68:F101,"Assinaturas",E68:E101) -> 0 | H117: =IF(D8=0,0,G117/D8) -> 0 | I117: =IF(H117>0.25,"🔴",IF(H117>0.1,"🟡","🟢")) -> 🟢
B118: Outros | C118: =SUMIF(F14:F28,"Outros",E14:E28) -> 0 | D118: =IF(E29=0,0,C118/E29) -> 0 | F118: Seguros | G118: =SUMIF(F33:F62,"Seguros",E33:E62)+SUMIF(F68:F101,"Seguros",E68:E101) -> 0 | H118: =IF(D8=0,0,G118/D8) -> 0 | I118: =IF(H118>0.25,"🔴",IF(H118>0.1,"🟡","🟢")) -> 🟢
F119: Impostos | G119: =SUMIF(F33:F62,"Impostos",E33:E62)+SUMIF(F68:F101,"Impostos",E68:E101) -> 0 | H119: =IF(D8=0,0,G119/D8) -> 0 | I119: =IF(H119>0.25,"🔴",IF(H119>0.1,"🟡","🟢")) -> 🟢
F120: Investimentos | G120: =SUMIF(F33:F62,"Investimentos",E33:E62)+SUMIF(F68:F101,"Investimentos",E68:E101) -> 0 | H120: =IF(D8=0,0,G120/D8) -> 0 | I120: =IF(H120>0.25,"🔴",IF(H120>0.1,"🟡","🟢")) -> 🟢
F121: Doações | G121: =SUMIF(F33:F62,"Doações",E33:E62)+SUMIF(F68:F101,"Doações",E68:E101) -> 0 | H121: =IF(D8=0,0,G121/D8) -> 0 | I121: =IF(H121>0.25,"🔴",IF(H121>0.1,"🟡","🟢")) -> 🟢
F122: Outros | G122: =SUMIF(F33:F62,"Outros",E33:E62)+SUMIF(F68:F101,"Outros",E68:E101) -> 0 | H122: =IF(D8=0,0,G122/D8) -> 0 | I122: =IF(H122>0.25,"🔴",IF(H122>0.1,"🟡","🟢")) -> 🟢

Sheet Junho
B1: 📅 JUNHO 2026 — CONTROLE COMPLETO
B3: 🏦 SALDO EM TEMPO REAL | F3: 🏺 JARROS DO MÊS
B4: 🔙 | C4: Saldo Inicial | D4: =Maio!E10 -> -1169.48 | E4: =D5 -> 0 | F4: 🏠 | G4: NEC (55%) | H4: =D5*'Configuração'!D29 -> 0
B5: 💵 | C5: Total Entradas | D5: =E29 -> 0 | E5: =D5 -> 0 | F5: 💎 | G5: CFL (10%) | H5: =D5*'Configuração'!D30 -> 0
B6: 🔒 | C6: Despesas Fixas | D6: =E63 -> 1184.9 | F6: 🏦 | G6: PELP (10%) | H6: =D5*'Configuração'!D31 -> 0
B7: 🛒 | C7: Despesas Variáveis | D7: =E102 -> 0 | F7: 📚 | G7: EDU (10%) | H7: =D5*'Configuração'!D32 -> 0 | J7: =H4 -> 0 | M7: =C109 -> 0 | N7: =H4 -> 0
B8: 💸 | C8: Total Saídas | D8: =D6+D7 -> 1184.9 | E8: =IF(D5=0,0,D8/D5) -> 0 | F8: 🎉 | G8: DIV (10%) | H8: =D5*'Configuração'!D33 -> 0 | J8: =H5 -> 0 | M8: =C110 -> 0 | N8: =H5 -> 0
B9: 📈 | C9: Saldo do Mês | D9: =D5-D8 -> -1184.9 | E9: =IF(D5=0,0,D9/D5) -> 0 | F9: 🤝 | G9: DOA (5%) | H9: =D5*'Configuração'!D34 -> 0 | J9: =H6 -> 0 | M9: =C111 -> 0 | N9: =H6 -> 0
B10: 🏦 | C10: SALDO FINAL | D10: =D4+D9 -> -2354.38 | E10: =D10 -> -2354.38 | J10: =H7 -> 0 | M10: =C112 -> 0 | N10: =H7 -> 0
J11: =H8 -> 0 | M11: =C113 -> 0 | N11: =H8 -> 0
B12: 💰 RECEITAS DO MÊS — DE ONDE VEM SEU DINHEIRO | J12: =H9 -> 0 | M12: =C114 -> 0 | N12: =H9 -> 0
B13: # | C13: Data | D13: Descrição da Receita | E13: Valor (R$) | F13: Fonte de Receita | G13: Recebido? | H13: Observação | M13: =C115 -> 0
B14: 1 | M14: =C116 -> 0
B15: 2 | M15: =C117 -> 0
B16: 3 | M16: =C118 -> 0
B17: 4
B18: 5
B19: 6
B20: 7
B21: 8
B22: 9 | M22: =G109 -> 200
B23: 10 | M23: =G110 -> 0
B24: 11 | M24: =G111 -> 200
B25: 12 | M25: =G112 -> 0
B26: 13 | M26: =G113 -> 470
B27: 14 | M27: =G114 -> 59.9
B28: 15 | M28: =G115 -> 0
B29: 💰 | C29: TOTAL RECEITAS DO MÊS | E29: =SUM(E14:E28) -> 0 | M29: =G116 -> 160
M30: =G117 -> 0
B31: 🔒 DESPESAS FIXAS — AUTOMÁTICAS DA CONFIGURAÇÃO (edite valores se precisar) | M31: =G118 -> 0
B32: # | C32: Venc. | D32: Descrição | E32: Valor (R$) | F32: Categoria | G32: Pago? ✅/❌ | H32: Observação | M32: =G119 -> 0
B33: 1 | C33: ='Configuração'!F39 -> 5 | D33: ='Configuração'!C39 -> Aluguel / Financiamento | E33: ='Configuração'!D39 | F33: ='Configuração'!E39 -> Moradia | M33: =G120 -> 0
B34: 2 | C34: ='Configuração'!F40 -> 10 | D34: ='Configuração'!C40 -> Condomínio | E34: ='Configuração'!D40 | F34: ='Configuração'!E40 -> Moradia | M34: =G121 -> 0
B35: 3 | C35: ='Configuração'!F41 -> 15 | D35: ='Configuração'!C41 -> IPTU (parcela) | E35: ='Configuração'!D41 | F35: ='Configuração'!E41 -> Impostos | M35: =G122 -> 0
B36: 4 | C36: ='Configuração'!F42 -> 10 | D36: ='Configuração'!C42 -> Energia Elétrica | E36: ='Configuração'!D42 -> 200 | F36: ='Configuração'!E42 -> Moradia
B37: 5 | C37: ='Configuração'!F43 -> 15 | D37: ='Configuração'!C43 -> Água / Saneamento | E37: ='Configuração'!D43 | F37: ='Configuração'!E43 -> Moradia
B38: 6 | C38: ='Configuração'!F44 -> 20 | D38: ='Configuração'!C44 -> Gás | E38: ='Configuração'!D44 | F38: ='Configuração'!E44 -> Moradia
B39: 7 | C39: ='Configuração'!F45 -> 10 | D39: ='Configuração'!C45 -> Internet | E39: ='Configuração'!D45 -> 100 | F39: ='Configuração'!E45 -> Tecnologia
B40: 8 | C40: ='Configuração'!F46 -> 12 | D40: ='Configuração'!C46 -> Celular | E40: ='Configuração'!D46 -> 60 | F40: ='Configuração'!E46 -> Tecnologia
B41: 9 | C41: ='Configuração'!F47 -> 5 | D41: ='Configuração'!C47 -> Plano de Saúde | E41: ='Configuração'!D47 | F41: ='Configuração'!E47 -> Saúde
B42: 10 | C42: ='Configuração'!F48 -> 15 | D42: ='Configuração'!C48 -> Seguro (carro/vida) | E42: ='Configuração'!D48 | F42: ='Configuração'!E48 -> Seguros
B43: 11 | C43: ='Configuração'!F49 -> 1 | D43: ='Configuração'!C49 -> Transporte / Combustível | E43: ='Configuração'!D49 -> 200 | F43: ='Configuração'!E49 -> Transporte
B44: 12 | C44: ='Configuração'!F50 -> 1 | D44: ='Configuração'!C50 -> Supermercado (base) | E44: ='Configuração'!D50 | F44: ='Configuração'!E50 -> Alimentação
B45: 13 | C45: ='Configuração'!F51 -> 1 | D45: ='Configuração'!C51 -> Farmácia / Medicamentos | E45: ='Configuração'!D51 | F45: ='Configuração'!E51 -> Saúde
B46: 14 | C46: ='Configuração'!F52 -> 5 | D46: ='Configuração'!C52 -> Academia | E46: ='Configuração'!D52 | F46: ='Configuração'!E52 -> Saúde
B47: 15 | C47: ='Configuração'!F53 -> 1 | D47: ='Configuração'!C53 -> Streaming / Entretenimento | E47: ='Configuração'!D53 -> 59.9 | F47: ='Configuração'!E53 -> Lazer / Diversão
... B62: 30 | C62: ='Configuração'!F68 | D62: ='Configuração'!C68 | E62: ='Configuração'!D68 | F62: ='Configuração'!E68
B63: 🔒 | C63: TOTAL DESPESAS FIXAS | E63: =SUM(E33:E62) -> 1184.9
B65: 🛒 DESPESAS VARIÁVEIS — ANOTE AQUI TODAS AS SUAS DESPESAS DO DIA A DIA
B66: 👉 ANOTE AQUI: compras, alimentação fora, uber, café, roupas, presentes... TUDO que não é fixo. Cada real anotado deduz do seu saldo!
B67: # | C67: Data | D67: Descrição da Despesa | E67: Valor (R$) | F67: Categoria | G67: Jarro | H67: Forma Pgto | I67: Obs
B68: 1
B69: 2
B70: 3
B71: 4
B72: 5
B73: 6
B74: 7
B75: 8
B76: 9
B77: 10
B78: 11
B79: 12
... B101: 34
B102: 🛒 | C102: TOTAL DESPESAS VARIÁVEIS | E102: =SUM(E68:E101) -> 0
B104: 🏦 SALDO FINAL DO MÊS | D104: =D10 -> -2354.38 | F104: =IF(D9>=0,"✅ Mês positivo! Parabéns!","⚠️ Gastou mais do que ganhou — revise seus gastos") -> ⚠️ Gastou mais do que ganhou — revise seus gastos
B107: 💵 RECEITAS POR FONTE | F107: 💸 DESPESAS POR CATEGORIA
B108: Fonte | C108: Valor | D108: % Total | F108: Categoria | G108: Valor | H108: % Desp. | I108: Alerta
B109: Salário CLT | C109: =SUMIF(F14:F28,"Salário CLT",E14:E28) -> 0 | D109: =IF(E29=0,0,C109/E29) -> 0 | F109: Moradia | G109: =SUMIF(F33:F62,"Moradia",E33:E62)+SUMIF(F68:F101,"Moradia",E68:E101) -> 200 | H109: =IF(D8=0,0,G109/D8) -> 0.16879062 | I109: =IF(H109>0.25,"🔴",IF(H109>0.1,"🟡","🟢")) -> 🟡
B110: Freelance / Projetos | C110: =SUMIF(F14:F28,"Freelance / Projetos",E14:E28) -> 0 | D110: =IF(E29=0,0,C110/E29) -> 0 | F110: Alimentação | G110: =SUMIF(F33:F62,"Alimentação",E33:E62)+SUMIF(F68:F101,"Alimentação",E68:E101) -> 0 | H110: =IF(D8=0,0,G110/D8) -> 0 | I110: =IF(H110>0.25,"🔴",IF(H110>0.1,"🟡","🟢")) -> 🟢
B111: Vendas Online | C111: =SUMIF(F14:F28,"Vendas Online",E14:E28) -> 0 | D111: =IF(E29=0,0,C111/E29) -> 0 | F111: Transporte | G111: =SUMIF(F33:F62,"Transporte",E33:E62)+SUMIF(F68:F101,"Transporte",E68:E101) -> 200 | H111: =IF(D8=0,0,G111/D8) -> 0.16879062 | I111: =IF(H111>0.25,"🔴",IF(H111>0.1,"🟡","🟢")) -> 🟡
B112: Consultoria | C112: =SUMIF(F14:F28,"Consultoria",E14:E28) -> 0 | D112: =IF(E29=0,0,C112/E29) -> 0 | F112: Saúde | G112: =SUMIF(F33:F62,"Saúde",E33:E62)+SUMIF(F68:F101,"Saúde",E68:E101) -> 0 | H112: =IF(D8=0,0,G112/D8) -> 0 | I112: =IF(H112>0.25,"🔴",IF(H112>0.1,"🟡","🟢")) -> 🟢
B113: Rendimentos / Investimentos | C113: =SUMIF(F14:F28,"Rendimentos / Investimentos",E14:E28) -> 0 | D113: =IF(E29=0,0,C113/E29) -> 0 | F113: Educação | G113: =SUMIF(F33:F62,"Educação",E33:E62)+SUMIF(F68:F101,"Educação",E68:E101) -> 470 | H113: =IF(D8=0,0,G113/D8) -> 0.39665795 | I113: =IF(H113>0.25,"🔴",IF(H113>0.1,"🟡","🟢")) -> 🔴
B114: Aluguel Recebido | C114: =SUMIF(F14:F28,"Aluguel Recebido",E14:E28) -> 0 | D114: =IF(E29=0,0,C114/E29) -> 0 | F114: Lazer / Diversão | G114: =SUMIF(F33:F62,"Lazer / Diversão",E33:E62)+SUMIF(F68:F101,"Lazer / Diversão",E68:E101) -> 59.9 | H114: =IF(D8=0,0,G114/D8) -> 0.050552789 | I114: =IF(H114>0.25,"🔴",IF(H114>0.1,"🟡","🟢")) -> 🟢
B115: Comissões | C115: =SUMIF(F14:F28,"Comissões",E14:E28) -> 0 | D115: =IF(E29=0,0,C115/E29) -> 0 | F115: Vestuário | G115: =SUMIF(F33:F62,"Vestuário",E33:E62)+SUMIF(F68:F101,"Vestuário",E68:E101) -> 0 | H115: =IF(D8=0,0,G115/D8) -> 0 | I115: =IF(H115>0.25,"🔴",IF(H115>0.1,"🟡","🟢")) -> 🟢
B116: Bônus / Participação | C116: =SUMIF(F14:F28,"Bônus / Participação",E14:E28) -> 0 | D116: =IF(E29=0,0,C116/E29) -> 0 | F116: Tecnologia | G116: =SUMIF(F33:F62,"Tecnologia",E33:E62)+SUMIF(F68:F101,"Tecnologia",E68:E101) -> 160 | H116: =IF(D8=0,0,G116/D8) -> 0.13503249 | I116: =IF(H116>0.25,"🔴",IF(H116>0.1,"🟡","🟢")) -> 🟡
B117: Renda Extra / Bico | C117: =SUMIF(F14:F28,"Renda Extra / Bico",E14:E28) -> 0 | D117: =IF(E29=0,0,C117/E29) -> 0 | F117: Assinaturas | G117: =SUMIF(F33:F62,"Assinaturas",E33:E62)+SUMIF(F68:F101,"Assinaturas",E68:E101) -> 0 | H117: =IF(D8=0,0,G117/D8) -> 0 | I117: =IF(H117>0.25,"🔴",IF(H117>0.1,"🟡","🟢")) -> 🟢
B118: Outros | C118: =SUMIF(F14:F28,"Outros",E14:E28) -> 0 | D118: =IF(E29=0,0,C118/E29) -> 0 | F118: Seguros | G118: =SUMIF(F33:F62,"Seguros",E33:E62)+SUMIF(F68:F101,"Seguros",E68:E101) -> 0 | H118: =IF(D8=0,0,G118/D8) -> 0 | I118: =IF(H118>0.25,"🔴",IF(H118>0.1,"🟡","🟢")) -> 🟢
F119: Impostos | G119: =SUMIF(F33:F62,"Impostos",E33:E62)+SUMIF(F68:F101,"Impostos",E68:E101) -> 0 | H119: =IF(D8=0,0,G119/D8) -> 0 | I119: =IF(H119>0.25,"🔴",IF(H119>0.1,"🟡","🟢")) -> 🟢
F120: Investimentos | G120: =SUMIF(F33:F62,"Investimentos",E33:E62)+SUMIF(F68:F101,"Investimentos",E68:E101) -> 0 | H120: =IF(D8=0,0,G120/D8) -> 0 | I120: =IF(H120>0.25,"🔴",IF(H120>0.1,"🟡","🟢")) -> 🟢
F121: Doações | G121: =SUMIF(F33:F62,"Doações",E33:E62)+SUMIF(F68:F101,"Doações",E68:E101) -> 0 | H121: =IF(D8=0,0,G121/D8) -> 0 | I121: =IF(H121>0.25,"🔴",IF(H121>0.1,"🟡","🟢")) -> 🟢
F122: Outros | G122: =SUMIF(F33:F62,"Outros",E33:E62)+SUMIF(F68:F101,"Outros",E68:E101) -> 0 | H122: =IF(D8=0,0,G122/D8) -> 0 | I122: =IF(H122>0.25,"🔴",IF(H122>0.1,"🟡","🟢")) -> 🟢

Sheet Julho
B1: 📅 JULHO 2026 — CONTROLE COMPLETO
B3: 🏦 SALDO EM TEMPO REAL | F3: 🏺 JARROS DO MÊS
B4: 🔙 | C4: Saldo Inicial | D4: =Junho!E10 -> -2354.38 | E4: =D5 -> 0 | F4: 🏠 | G4: NEC (55%) | H4: =D5*'Configuração'!D29 -> 0
B5: 💵 | C5: Total Entradas | D5: =E29 -> 0 | E5: =D5 -> 0 | F5: 💎 | G5: CFL (10%) | H5: =D5*'Configuração'!D30 -> 0
B6: 🔒 | C6: Despesas Fixas | D6: =E63 -> 1184.9 | F6: 🏦 | G6: PELP (10%) | H6: =D5*'Configuração'!D31 -> 0
B7: 🛒 | C7: Despesas Variáveis | D7: =E102 -> 0 | F7: 📚 | G7: EDU (10%) | H7: =D5*'Configuração'!D32 -> 0 | J7: =H4 -> 0 | M7: =C109 -> 0 | N7: =H4 -> 0
B8: 💸 | C8: Total Saídas | D8: =D6+D7 -> 1184.9 | E8: =IF(D5=0,0,D8/D5) -> 0 | F8: 🎉 | G8: DIV (10%) | H8: =D5*'Configuração'!D33 -> 0 | J8: =H5 -> 0 | M8: =C110 -> 0 | N8: =H5 -> 0
B9: 📈 | C9: Saldo do Mês | D9: =D5-D8 -> -1184.9 | E9: =IF(D5=0,0,D9/D5) -> 0 | F9: 🤝 | G9: DOA (5%) | H9: =D5*'Configuração'!D34 -> 0 | J9: =H6 -> 0 | M9: =C111 -> 0 | N9: =H6 -> 0
B10: 🏦 | C10: SALDO FINAL | D10: =D4+D9 -> -3539.28 | E10: =D10 -> -3539.28 | J10: =H7 -> 0 | M10: =C112 -> 0 | N10: =H7 -> 0
J11: =H8 -> 0 | M11: =C113 -> 0 | N11: =H8 -> 0
B12: 💰 RECEITAS DO MÊS — DE ONDE VEM SEU DINHEIRO | J12: =H9 -> 0 | M12: =C114 -> 0 | N12: =H9 -> 0
B13: # | C13: Data | D13: Descrição da Receita | E13: Valor (R$) | F13: Fonte de Receita | G13: Recebido? | H13: Observação | M13: =C115 -> 0
B14: 1 | M14: =C116 -> 0
B15: 2 | M15: =C117 -> 0
B16: 3 | M16: =C118 -> 0
B17: 4
B18: 5
B19: 6
B20: 7
B21: 8
B22: 9 | M22: =G109 -> 200
B23: 10 | M23: =G110 -> 0
B24: 11 | M24: =G111 -> 200
B25: 12 | M25: =G112 -> 0
B26: 13 | M26: =G113 -> 470
B27: 14 | M27: =G114 -> 59.9
B28: 15 | M28: =G115 -> 0
B29: 💰 | C29: TOTAL RECEITAS DO MÊS | E29: =SUM(E14:E28) -> 0 | M29: =G116 -> 160
M30: =G117 -> 0
B31: 🔒 DESPESAS FIXAS — AUTOMÁTICAS DA CONFIGURAÇÃO (edite valores se precisar) | M31: =G118 -> 0
B32: # | C32: Venc. | D32: Descrição | E32: Valor (R$) | F32: Categoria | G32: Pago? ✅/❌ | H32: Observação | M32: =G119 -> 0
B33: 1 | C33: ='Configuração'!F39 -> 5 | D33: ='Configuração'!C39 -> Aluguel / Financiamento | E33: ='Configuração'!D39 | F33: ='Configuração'!E39 -> Moradia | M33: =G120 -> 0
B34: 2 | C34: ='Configuração'!F40 -> 10 | D34: ='Configuração'!C40 -> Condomínio | E34: ='Configuração'!D40 | F34: ='Configuração'!E40 -> Moradia | M34: =G121 -> 0
B35: 3 | C35: ='Configuração'!F41 -> 15 | D35: ='Configuração'!C41 -> IPTU (parcela) | E35: ='Configuração'!D41 | F35: ='Configuração'!E41 -> Impostos | M35: =G122 -> 0
B36: 4 | C36: ='Configuração'!F42 -> 10 | D36: ='Configuração'!C42 -> Energia Elétrica | E36: ='Configuração'!D42 -> 200 | F36: ='Configuração'!E42 -> Moradia
B37: 5 | C37: ='Configuração'!F43 -> 15 | D37: ='Configuração'!C43 -> Água / Saneamento | E37: ='Configuração'!D43 | F37: ='Configuração'!E43 -> Moradia
B38: 6 | C38: ='Configuração'!F44 -> 20 | D38: ='Configuração'!C44 -> Gás | E38: ='Configuração'!D44 | F38: ='Configuração'!E44 -> Moradia
B39: 7 | C39: ='Configuração'!F45 -> 10 | D39: ='Configuração'!C45 -> Internet | E39: ='Configuração'!D45 -> 100 | F39: ='Configuração'!E45 -> Tecnologia
B40: 8 | C40: ='Configuração'!F46 -> 12 | D40: ='Configuração'!C46 -> Celular | E40: ='Configuração'!D46 -> 60 | F40: ='Configuração'!E46 -> Tecnologia
B41: 9 | C41: ='Configuração'!F47 -> 5 | D41: ='Configuração'!C47 -> Plano de Saúde | E41: ='Configuração'!D47 | F41: ='Configuração'!E47 -> Saúde
B42: 10 | C42: ='Configuração'!F48 -> 15 | D42: ='Configuração'!C48 -> Seguro (carro/vida) | E42: ='Configuração'!D48 | F42: ='Configuração'!E48 -> Seguros
B43: 11 | C43: ='Configuração'!F49 -> 1 | D43: ='Configuração'!C49 -> Transporte / Combustível | E43: ='Configuração'!D49 -> 200 | F43: ='Configuração'!E49 -> Transporte
B44: 12 | C44: ='Configuração'!F50 -> 1 | D44: ='Configuração'!C50 -> Supermercado (base) | E44: ='Configuração'!D50 | F44: ='Configuração'!E50 -> Alimentação
B45: 13 | C45: ='Configuração'!F51 -> 1 | D45: ='Configuração'!C51 -> Farmácia / Medicamentos | E45: ='Configuração'!D51 | F45: ='Configuração'!E51 -> Saúde
B46: 14 | C46: ='Configuração'!F52 -> 5 | D46: ='Configuração'!C52 -> Academia | E46: ='Configuração'!D52 | F46: ='Configuração'!E52 -> Saúde
B47: 15 | C47: ='Configuração'!F53 -> 1 | D47: ='Configuração'!C53 -> Streaming / Entretenimento | E47: ='Configuração'!D53 -> 59.9 | F47: ='Configuração'!E53 -> Lazer / Diversão
... B62: 30 | C62: ='Configuração'!F68 | D62: ='Configuração'!C68 | E62: ='Configuração'!D68 | F62: ='Configuração'!E68
B63: 🔒 | C63: TOTAL DESPESAS FIXAS | E63: =SUM(E33:E62) -> 1184.9
B65: 🛒 DESPESAS VARIÁVEIS — ANOTE AQUI TODAS AS SUAS DESPESAS DO DIA A DIA
B66: 👉 ANOTE AQUI: compras, alimentação fora, uber, café, roupas, presentes... TUDO que não é fixo. Cada real anotado deduz do seu saldo!
B67: # | C67: Data | D67: Descrição da Despesa | E67: Valor (R$) | F67: Categoria | G67: Jarro | H67: Forma Pgto | I67: Obs
B68: 1
B69: 2
B70: 3
B71: 4
B72: 5
B73: 6
B74: 7
B75: 8
B76: 9
B77: 10
B78: 11
B79: 12
... B101: 34
B102: 🛒 | C102: TOTAL DESPESAS VARIÁVEIS | E102: =SUM(E68:E101) -> 0
B104: 🏦 SALDO FINAL DO MÊS | D104: =D10 -> -3539.28 | F104: =IF(D9>=0,"✅ Mês positivo! Parabéns!","⚠️ Gastou mais do que ganhou — revise seus gastos") -> ⚠️ Gastou mais do que ganhou — revise seus gastos
B107: 💵 RECEITAS POR FONTE | F107: 💸 DESPESAS POR CATEGORIA
B108: Fonte | C108: Valor | D108: % Total | F108: Categoria | G108: Valor | H108: % Desp. | I108: Alerta
B109: Salário CLT | C109: =SUMIF(F14:F28,"Salário CLT",E14:E28) -> 0 | D109: =IF(E29=0,0,C109/E29) -> 0 | F109: Moradia | G109: =SUMIF(F33:F62,"Moradia",E33:E62)+SUMIF(F68:F101,"Moradia",E68:E101) -> 200 | H109: =IF(D8=0,0,G109/D8) -> 0.16879062 | I109: =IF(H109>0.25,"🔴",IF(H109>0.1,"🟡","🟢")) -> 🟡
B110: Freelance / Projetos | C110: =SUMIF(F14:F28,"Freelance / Projetos",E14:E28) -> 0 | D110: =IF(E29=0,0,C110/E29) -> 0 | F110: Alimentação | G110: =SUMIF(F33:F62,"Alimentação",E33:E62)+SUMIF(F68:F101,"Alimentação",E68:E101) -> 0 | H110: =IF(D8=0,0,G110/D8) -> 0 | I110: =IF(H110>0.25,"🔴",IF(H110>0.1,"🟡","🟢")) -> 🟢
B111: Vendas Online | C111: =SUMIF(F14:F28,"Vendas Online",E14:E28) -> 0 | D111: =IF(E29=0,0,C111/E29) -> 0 | F111: Transporte | G111: =SUMIF(F33:F62,"Transporte",E33:E62)+SUMIF(F68:F101,"Transporte",E68:E101) -> 200 | H111: =IF(D8=0,0,G111/D8) -> 0.16879062 | I111: =IF(H111>0.25,"🔴",IF(H111>0.1,"🟡","🟢")) -> 🟡
B112: Consultoria | C112: =SUMIF(F14:F28,"Consultoria",E14:E28) -> 0 | D112: =IF(E29=0,0,C112/E29) -> 0 | F112: Saúde | G112: =SUMIF(F33:F62,"Saúde",E33:E62)+SUMIF(F68:F101,"Saúde",E68:E101) -> 0 | H112: =IF(D8=0,0,G112/D8) -> 0 | I112: =IF(H112>0.25,"🔴",IF(H112>0.1,"🟡","🟢")) -> 🟢
B113: Rendimentos / Investimentos | C113: =SUMIF(F14:F28,"Rendimentos / Investimentos",E14:E28) -> 0 | D113: =IF(E29=0,0,C113/E29) -> 0 | F113: Educação | G113: =SUMIF(F33:F62,"Educação",E33:E62)+SUMIF(F68:F101,"Educação",E68:E101) -> 470 | H113: =IF(D8=0,0,G113/D8) -> 0.39665795 | I113: =IF(H113>0.25,"🔴",IF(H113>0.1,"🟡","🟢")) -> 🔴
B114: Aluguel Recebido | C114: =SUMIF(F14:F28,"Aluguel Recebido",E14:E28) -> 0 | D114: =IF(E29=0,0,C114/E29) -> 0 | F114: Lazer / Diversão | G114: =SUMIF(F33:F62,"Lazer / Diversão",E33:E62)+SUMIF(F68:F101,"Lazer / Diversão",E68:E101) -> 59.9 | H114: =IF(D8=0,0,G114/D8) -> 0.050552789 | I114: =IF(H114>0.25,"🔴",IF(H114>0.1,"🟡","🟢")) -> 🟢
B115: Comissões | C115: =SUMIF(F14:F28,"Comissões",E14:E28) -> 0 | D115: =IF(E29=0,0,C115/E29) -> 0 | F115: Vestuário | G115: =SUMIF(F33:F62,"Vestuário",E33:E62)+SUMIF(F68:F101,"Vestuário",E68:E101) -> 0 | H115: =IF(D8=0,0,G115/D8) -> 0 | I115: =IF(H115>0.25,"🔴",IF(H115>0.1,"🟡","🟢")) -> 🟢
B116: Bônus / Participação | C116: =SUMIF(F14:F28,"Bônus / Participação",E14:E28) -> 0 | D116: =IF(E29=0,0,C116/E29) -> 0 | F116: Tecnologia | G116: =SUMIF(F33:F62,"Tecnologia",E33:E62)+SUMIF(F68:F101,"Tecnologia",E68:E101) -> 160 | H116: =IF(D8=0,0,G116/D8) -> 0.13503249 | I116: =IF(H116>0.25,"🔴",IF(H116>0.1,"🟡","🟢")) -> 🟡
B117: Renda Extra / Bico | C117: =SUMIF(F14:F28,"Renda Extra / Bico",E14:E28) -> 0 | D117: =IF(E29=0,0,C117/E29) -> 0 | F117: Assinaturas | G117: =SUMIF(F33:F62,"Assinaturas",E33:E62)+SUMIF(F68:F101,"Assinaturas",E68:E101) -> 0 | H117: =IF(D8=0,0,G117/D8) -> 0 | I117: =IF(H117>0.25,"🔴",IF(H117>0.1,"🟡","🟢")) -> 🟢
B118: Outros | C118: =SUMIF(F14:F28,"Outros",E14:E28) -> 0 | D118: =IF(E29=0,0,C118/E29) -> 0 | F118: Seguros | G118: =SUMIF(F33:F62,"Seguros",E33:E62)+SUMIF(F68:F101,"Seguros",E68:E101) -> 0 | H118: =IF(D8=0,0,G118/D8) -> 0 | I118: =IF(H118>0.25,"🔴",IF(H118>0.1,"🟡","🟢")) -> 🟢
F119: Impostos | G119: =SUMIF(F33:F62,"Impostos",E33:E62)+SUMIF(F68:F101,"Impostos",E68:E101) -> 0 | H119: =IF(D8=0,0,G119/D8) -> 0 | I119: =IF(H119>0.25,"🔴",IF(H119>0.1,"🟡","🟢")) -> 🟢
F120: Investimentos | G120: =SUMIF(F33:F62,"Investimentos",E33:E62)+SUMIF(F68:F101,"Investimentos",E68:E101) -> 0 | H120: =IF(D8=0,0,G120/D8) -> 0 | I120: =IF(H120>0.25,"🔴",IF(H120>0.1,"🟡","🟢")) -> 🟢
F121: Doações | G121: =SUMIF(F33:F62,"Doações",E33:E62)+SUMIF(F68:F101,"Doações",E68:E101) -> 0 | H121: =IF(D8=0,0,G121/D8) -> 0 | I121: =IF(H121>0.25,"🔴",IF(H121>0.1,"🟡","🟢")) -> 🟢
F122: Outros | G122: =SUMIF(F33:F62,"Outros",E33:E62)+SUMIF(F68:F101,"Outros",E68:E101) -> 0 | H122: =IF(D8=0,0,G122/D8) -> 0 | I122: =IF(H122>0.25,"🔴",IF(H122>0.1,"🟡","🟢")) -> 🟢

Sheet Agosto
B1: 📅 AGOSTO 2026 — CONTROLE COMPLETO
B3: 🏦 SALDO EM TEMPO REAL | F3: 🏺 JARROS DO MÊS
B4: 🔙 | C4: Saldo Inicial | D4: =Julho!E10 -> -3539.28 | E4: =D5 -> 0 | F4: 🏠 | G4: NEC (55%) | H4: =D5*'Configuração'!D29 -> 0
B5: 💵 | C5: Total Entradas | D5: =E29 -> 0 | E5: =D5 -> 0 | F5: 💎 | G5: CFL (10%) | H5: =D5*'Configuração'!D30 -> 0
B6: 🔒 | C6: Despesas Fixas | D6: =E63 -> 1184.9 | F6: 🏦 | G6: PELP (10%) | H6: =D5*'Configuração'!D31 -> 0
B7: 🛒 | C7: Despesas Variáveis | D7: =E102 -> 0 | F7: 📚 | G7: EDU (10%) | H7: =D5*'Configuração'!D32 -> 0 | J7: =H4 -> 0 | M7: =C109 -> 0 | N7: =H4 -> 0
B8: 💸 | C8: Total Saídas | D8: =D6+D7 -> 1184.9 | E8: =IF(D5=0,0,D8/D5) -> 0 | F8: 🎉 | G8: DIV (10%) | H8: =D5*'Configuração'!D33 -> 0 | J8: =H5 -> 0 | M8: =C110 -> 0 | N8: =H5 -> 0
B9: 📈 | C9: Saldo do Mês | D9: =D5-D8 -> -1184.9 | E9: =IF(D5=0,0,D9/D5) -> 0 | F9: 🤝 | G9: DOA (5%) | H9: =D5*'Configuração'!D34 -> 0 | J9: =H6 -> 0 | M9: =C111 -> 0 | N9: =H6 -> 0
B10: 🏦 | C10: SALDO FINAL | D10: =D4+D9 -> -4724.18 | E10: =D10 -> -4724.18 | J10: =H7 -> 0 | M10: =C112 -> 0 | N10: =H7 -> 0
J11: =H8 -> 0 | M11: =C113 -> 0 | N11: =H8 -> 0
B12: 💰 RECEITAS DO MÊS — DE ONDE VEM SEU DINHEIRO | J12: =H9 -> 0 | M12: =C114 -> 0 | N12: =H9 -> 0
B13: # | C13: Data | D13: Descrição da Receita | E13: Valor (R$) | F13: Fonte de Receita | G13: Recebido? | H13: Observação | M13: =C115 -> 0
B14: 1 | M14: =C116 -> 0
B15: 2 | M15: =C117 -> 0
B16: 3 | M16: =C118 -> 0
B17: 4
B18: 5
B19: 6
B20: 7
B21: 8
B22: 9 | M22: =G109 -> 200
B23: 10 | M23: =G110 -> 0
B24: 11 | M24: =G111 -> 200
B25: 12 | M25: =G112 -> 0
B26: 13 | M26: =G113 -> 470
B27: 14 | M27: =G114 -> 59.9
B28: 15 | M28: =G115 -> 0
B29: 💰 | C29: TOTAL RECEITAS DO MÊS | E29: =SUM(E14:E28) -> 0 | M29: =G116 -> 160
M30: =G117 -> 0
B31: 🔒 DESPESAS FIXAS — AUTOMÁTICAS DA CONFIGURAÇÃO (edite valores se precisar) | M31: =G118 -> 0
B32: # | C32: Venc. | D32: Descrição | E32: Valor (R$) | F32: Categoria | G32: Pago? ✅/❌ | H32: Observação | M32: =G119 -> 0
B33: 1 | C33: ='Configuração'!F39 -> 5 | D33: ='Configuração'!C39 -> Aluguel / Financiamento | E33: ='Configuração'!D39 | F33: ='Configuração'!E39 -> Moradia | M33: =G120 -> 0
B34: 2 | C34: ='Configuração'!F40 -> 10 | D34: ='Configuração'!C40 -> Condomínio | E34: ='Configuração'!D40 | F34: ='Configuração'!E40 -> Moradia | M34: =G121 -> 0
B35: 3 | C35: ='Configuração'!F41 -> 15 | D35: ='Configuração'!C41 -> IPTU (parcela) | E35: ='Configuração'!D41 | F35: ='Configuração'!E41 -> Impostos | M35: =G122 -> 0
B36: 4 | C36: ='Configuração'!F42 -> 10 | D36: ='Configuração'!C42 -> Energia Elétrica | E36: ='Configuração'!D42 -> 200 | F36: ='Configuração'!E42 -> Moradia
B37: 5 | C37: ='Configuração'!F43 -> 15 | D37: ='Configuração'!C43 -> Água / Saneamento | E37: ='Configuração'!D43 | F37: ='Configuração'!E43 -> Moradia
B38: 6 | C38: ='Configuração'!F44 -> 20 | D38: ='Configuração'!C44 -> Gás | E38: ='Configuração'!D44 | F38: ='Configuração'!E44 -> Moradia
B39: 7 | C39: ='Configuração'!F45 -> 10 | D39: ='Configuração'!C45 -> Internet | E39: ='Configuração'!D45 -> 100 | F39: ='Configuração'!E45 -> Tecnologia
B40: 8 | C40: ='Configuração'!F46 -> 12 | D40: ='Configuração'!C46 -> Celular | E40: ='Configuração'!D46 -> 60 | F40: ='Configuração'!E46 -> Tecnologia
B41: 9 | C41: ='Configuração'!F47 -> 5 | D41: ='Configuração'!C47 -> Plano de Saúde | E41: ='Configuração'!D47 | F41: ='Configuração'!E47 -> Saúde
B42: 10 | C42: ='Configuração'!F48 -> 15 | D42: ='Configuração'!C48 -> Seguro (carro/vida) | E42: ='Configuração'!D48 | F42: ='Configuração'!E48 -> Seguros
B43: 11 | C43: ='Configuração'!F49 -> 1 | D43: ='Configuração'!C49 -> Transporte / Combustível | E43: ='Configuração'!D49 -> 200 | F43: ='Configuração'!E49 -> Transporte
B44: 12 | C44: ='Configuração'!F50 -> 1 | D44: ='Configuração'!C50 -> Supermercado (base) | E44: ='Configuração'!D50 | F44: ='Configuração'!E50 -> Alimentação
B45: 13 | C45: ='Configuração'!F51 -> 1 | D45: ='Configuração'!C51 -> Farmácia / Medicamentos | E45: ='Configuração'!D51 | F45: ='Configuração'!E51 -> Saúde
B46: 14 | C46: ='Configuração'!F52 -> 5 | D46: ='Configuração'!C52 -> Academia | E46: ='Configuração'!D52 | F46: ='Configuração'!E52 -> Saúde
B47: 15 | C47: ='Configuração'!F53 -> 1 | D47: ='Configuração'!C53 -> Streaming / Entretenimento | E47: ='Configuração'!D53 -> 59.9 | F47: ='Configuração'!E53 -> Lazer / Diversão
... B62: 30 | C62: ='Configuração'!F68 | D62: ='Configuração'!C68 | E62: ='Configuração'!D68 | F62: ='Configuração'!E68
B63: 🔒 | C63: TOTAL DESPESAS FIXAS | E63: =SUM(E33:E62) -> 1184.9
B65: 🛒 DESPESAS VARIÁVEIS — ANOTE AQUI TODAS AS SUAS DESPESAS DO DIA A DIA
B66: 👉 ANOTE AQUI: compras, alimentação fora, uber, café, roupas, presentes... TUDO que não é fixo. Cada real anotado deduz do seu saldo!
B67: # | C67: Data | D67: Descrição da Despesa | E67: Valor (R$) | F67: Categoria | G67: Jarro | H67: Forma Pgto | I67: Obs
B68: 1
B69: 2
B70: 3
B71: 4
B72: 5
B73: 6
B74: 7
B75: 8
B76: 9
B77: 10
B78: 11
B79: 12
... B101: 34
B102: 🛒 | C102: TOTAL DESPESAS VARIÁVEIS | E102: =SUM(E68:E101) -> 0
B104: 🏦 SALDO FINAL DO MÊS | D104: =D10 -> -4724.18 | F104: =IF(D9>=0,"✅ Mês positivo! Parabéns!","⚠️ Gastou mais do que ganhou — revise seus gastos") -> ⚠️ Gastou mais do que ganhou — revise seus gastos
B107: 💵 RECEITAS POR FONTE | F107: 💸 DESPESAS POR CATEGORIA
B108: Fonte | C108: Valor | D108: % Total | F108: Categoria | G108: Valor | H108: % Desp. | I108: Alerta
B109: Salário CLT | C109: =SUMIF(F14:F28,"Salário CLT",E14:E28) -> 0 | D109: =IF(E29=0,0,C109/E29) -> 0 | F109: Moradia | G109: =SUMIF(F33:F62,"Moradia",E33:E62)+SUMIF(F68:F101,"Moradia",E68:E101) -> 200 | H109: =IF(D8=0,0,G109/D8) -> 0.16879062 | I109: =IF(H109>0.25,"🔴",IF(H109>0.1,"🟡","🟢")) -> 🟡
B110: Freelance / Projetos | C110: =SUMIF(F14:F28,"Freelance / Projetos",E14:E28) -> 0 | D110: =IF(E29=0,0,C110/E29) -> 0 | F110: Alimentação | G110: =SUMIF(F33:F62,"Alimentação",E33:E62)+SUMIF(F68:F101,"Alimentação",E68:E101) -> 0 | H110: =IF(D8=0,0,G110/D8) -> 0 | I110: =IF(H110>0.25,"🔴",IF(H110>0.1,"🟡","🟢")) -> 🟢
B111: Vendas Online | C111: =SUMIF(F14:F28,"Vendas Online",E14:E28) -> 0 | D111: =IF(E29=0,0,C111/E29) -> 0 | F111: Transporte | G111: =SUMIF(F33:F62,"Transporte",E33:E62)+SUMIF(F68:F101,"Transporte",E68:E101) -> 200 | H111: =IF(D8=0,0,G111/D8) -> 0.16879062 | I111: =IF(H111>0.25,"🔴",IF(H111>0.1,"🟡","🟢")) -> 🟡
B112: Consultoria | C112: =SUMIF(F14:F28,"Consultoria",E14:E28) -> 0 | D112: =IF(E29=0,0,C112/E29) -> 0 | F112: Saúde | G112: =SUMIF(F33:F62,"Saúde",E33:E62)+SUMIF(F68:F101,"Saúde",E68:E101) -> 0 | H112: =IF(D8=0,0,G112/D8) -> 0 | I112: =IF(H112>0.25,"🔴",IF(H112>0.1,"🟡","🟢")) -> 🟢
B113: Rendimentos / Investimentos | C113: =SUMIF(F14:F28,"Rendimentos / Investimentos",E14:E28) -> 0 | D113: =IF(E29=0,0,C113/E29) -> 0 | F113: Educação | G113: =SUMIF(F33:F62,"Educação",E33:E62)+SUMIF(F68:F101,"Educação",E68:E101) -> 470 | H113: =IF(D8=0,0,G113/D8) -> 0.39665795 | I113: =IF(H113>0.25,"🔴",IF(H113>0.1,"🟡","🟢")) -> 🔴
B114: Aluguel Recebido | C114: =SUMIF(F14:F28,"Aluguel Recebido",E14:E28) -> 0 | D114: =IF(E29=0,0,C114/E29) -> 0 | F114: Lazer / Diversão | G114: =SUMIF(F33:F62,"Lazer / Diversão",E33:E62)+SUMIF(F68:F101,"Lazer / Diversão",E68:E101) -> 59.9 | H114: =IF(D8=0,0,G114/D8) -> 0.050552789 | I114: =IF(H114>0.25,"🔴",IF(H114>0.1,"🟡","🟢")) -> 🟢
B115: Comissões | C115: =SUMIF(F14:F28,"Comissões",E14:E28) -> 0 | D115: =IF(E29=0,0,C115/E29) -> 0 | F115: Vestuário | G115: =SUMIF(F33:F62,"Vestuário",E33:E62)+SUMIF(F68:F101,"Vestuário",E68:E101) -> 0 | H115: =IF(D8=0,0,G115/D8) -> 0 | I115: =IF(H115>0.25,"🔴",IF(H115>0.1,"🟡","🟢")) -> 🟢
B116: Bônus / Participação | C116: =SUMIF(F14:F28,"Bônus / Participação",E14:E28) -> 0 | D116: =IF(E29=0,0,C116/E29) -> 0 | F116: Tecnologia | G116: =SUMIF(F33:F62,"Tecnologia",E33:E62)+SUMIF(F68:F101,"Tecnologia",E68:E101) -> 160 | H116: =IF(D8=0,0,G116/D8) -> 0.13503249 | I116: =IF(H116>0.25,"🔴",IF(H116>0.1,"🟡","🟢")) -> 🟡
B117: Renda Extra / Bico | C117: =SUMIF(F14:F28,"Renda Extra / Bico",E14:E28) -> 0 | D117: =IF(E29=0,0,C117/E29) -> 0 | F117: Assinaturas | G117: =SUMIF(F33:F62,"Assinaturas",E33:E62)+SUMIF(F68:F101,"Assinaturas",E68:E101) -> 0 | H117: =IF(D8=0,0,G117/D8) -> 0 | I117: =IF(H117>0.25,"🔴",IF(H117>0.1,"🟡","🟢")) -> 🟢
B118: Outros | C118: =SUMIF(F14:F28,"Outros",E14:E28) -> 0 | D118: =IF(E29=0,0,C118/E29) -> 0 | F118: Seguros | G118: =SUMIF(F33:F62,"Seguros",E33:E62)+SUMIF(F68:F101,"Seguros",E68:E101) -> 0 | H118: =IF(D8=0,0,G118/D8) -> 0 | I118: =IF(H118>0.25,"🔴",IF(H118>0.1,"🟡","🟢")) -> 🟢
F119: Impostos | G119: =SUMIF(F33:F62,"Impostos",E33:E62)+SUMIF(F68:F101,"Impostos",E68:E101) -> 0 | H119: =IF(D8=0,0,G119/D8) -> 0 | I119: =IF(H119>0.25,"🔴",IF(H119>0.1,"🟡","🟢")) -> 🟢
F120: Investimentos | G120: =SUMIF(F33:F62,"Investimentos",E33:E62)+SUMIF(F68:F101,"Investimentos",E68:E101) -> 0 | H120: =IF(D8=0,0,G120/D8) -> 0 | I120: =IF(H120>0.25,"🔴",IF(H120>0.1,"🟡","🟢")) -> 🟢
F121: Doações | G121: =SUMIF(F33:F62,"Doações",E33:E62)+SUMIF(F68:F101,"Doações",E68:E101) -> 0 | H121: =IF(D8=0,0,G121/D8) -> 0 | I121: =IF(H121>0.25,"🔴",IF(H121>0.1,"🟡","🟢")) -> 🟢
F122: Outros | G122: =SUMIF(F33:F62,"Outros",E33:E62)+SUMIF(F68:F101,"Outros",E68:E101) -> 0 | H122: =IF(D8=0,0,G122/D8) -> 0 | I122: =IF(H122>0.25,"🔴",IF(H122>0.1,"🟡","🟢")) -> 🟢

Sheet Setembro
B1: 📅 SETEMBRO 2026 — CONTROLE COMPLETO
B3: 🏦 SALDO EM TEMPO REAL | F3: 🏺 JARROS DO MÊS
B4: 🔙 | C4: Saldo Inicial | D4: =Agosto!E10 -> -4724.18 | E4: =D5 -> 0 | F4: 🏠 | G4: NEC (55%) | H4: =D5*'Configuração'!D29 -> 0
B5: 💵 | C5: Total Entradas | D5: =E29 -> 0 | E5: =D5 -> 0 | F5: 💎 | G5: CFL (10%) | H5: =D5*'Configuração'!D30 -> 0
B6: 🔒 | C6: Despesas Fixas | D6: =E63 -> 1184.9 | F6: 🏦 | G6: PELP (10%) | H6: =D5*'Configuração'!D31 -> 0
B7: 🛒 | C7: Despesas Variáveis | D7: =E102 -> 0 | F7: 📚 | G7: EDU (10%) | H7: =D5*'Configuração'!D32 -> 0 | J7: =H4 -> 0 | M7: =C109 -> 0 | N7: =H4 -> 0
B8: 💸 | C8: Total Saídas | D8: =D6+D7 -> 1184.9 | E8: =IF(D5=0,0,D8/D5) -> 0 | F8: 🎉 | G8: DIV (10%) | H8: =D5*'Configuração'!D33 -> 0 | J8: =H5 -> 0 | M8: =C110 -> 0 | N8: =H5 -> 0
B9: 📈 | C9: Saldo do Mês | D9: =D5-D8 -> -1184.9 | E9: =IF(D5=0,0,D9/D5) -> 0 | F9: 🤝 | G9: DOA (5%) | H9: =D5*'Configuração'!D34 -> 0 | J9: =H6 -> 0 | M9: =C111 -> 0 | N9: =H6 -> 0
B10: 🏦 | C10: SALDO FINAL | D10: =D4+D9 -> -5909.08 | E10: =D10 -> -5909.08 | J10: =H7 -> 0 | M10: =C112 -> 0 | N10: =H7 -> 0
J11: =H8 -> 0 | M11: =C113 -> 0 | N11: =H8 -> 0
B12: 💰 RECEITAS DO MÊS — DE ONDE VEM SEU DINHEIRO | J12: =H9 -> 0 | M12: =C114 -> 0 | N12: =H9 -> 0
B13: # | C13: Data | D13: Descrição da Receita | E13: Valor (R$) | F13: Fonte de Receita | G13: Recebido? | H13: Observação | M13: =C115 -> 0
B14: 1 | M14: =C116 -> 0
B15: 2 | M15: =C117 -> 0
B16: 3 | M16: =C118 -> 0
B17: 4
B18: 5
B19: 6
B20: 7
B21: 8
B22: 9 | M22: =G109 -> 200
B23: 10 | M23: =G110 -> 0
B24: 11 | M24: =G111 -> 200
B25: 12 | M25: =G112 -> 0
B26: 13 | M26: =G113 -> 470
B27: 14 | M27: =G114 -> 59.9
B28: 15 | M28: =G115 -> 0
B29: 💰 | C29: TOTAL RECEITAS DO MÊS | E29: =SUM(E14:E28) -> 0 | M29: =G116 -> 160
M30: =G117 -> 0
B31: 🔒 DESPESAS FIXAS — AUTOMÁTICAS DA CONFIGURAÇÃO (edite valores se precisar) | M31: =G118 -> 0
B32: # | C32: Venc. | D32: Descrição | E32: Valor (R$) | F32: Categoria | G32: Pago? ✅/❌ | H32: Observação | M32: =G119 -> 0
B33: 1 | C33: ='Configuração'!F39 -> 5 | D33: ='Configuração'!C39 -> Aluguel / Financiamento | E33: ='Configuração'!D39 | F33: ='Configuração'!E39 -> Moradia | M33: =G120 -> 0
B34: 2 | C34: ='Configuração'!F40 -> 10 | D34: ='Configuração'!C40 -> Condomínio | E34: ='Configuração'!D40 | F34: ='Configuração'!E40 -> Moradia | M34: =G121 -> 0
B35: 3 | C35: ='Configuração'!F41 -> 15 | D35: ='Configuração'!C41 -> IPTU (parcela) | E35: ='Configuração'!D41 | F35: ='Configuração'!E41 -> Impostos | M35: =G122 -> 0
B36: 4 | C36: ='Configuração'!F42 -> 10 | D36: ='Configuração'!C42 -> Energia Elétrica | E36: ='Configuração'!D42 -> 200 | F36: ='Configuração'!E42 -> Moradia
B37: 5 | C37: ='Configuração'!F43 -> 15 | D37: ='Configuração'!C43 -> Água / Saneamento | E37: ='Configuração'!D43 | F37: ='Configuração'!E43 -> Moradia
B38: 6 | C38: ='Configuração'!F44 -> 20 | D38: ='Configuração'!C44 -> Gás | E38: ='Configuração'!D44 | F38: ='Configuração'!E44 -> Moradia
B39: 7 | C39: ='Configuração'!F45 -> 10 | D39: ='Configuração'!C45 -> Internet | E39: ='Configuração'!D45 -> 100 | F39: ='Configuração'!E45 -> Tecnologia
B40: 8 | C40: ='Configuração'!F46 -> 12 | D40: ='Configuração'!C46 -> Celular | E40: ='Configuração'!D46 -> 60 | F40: ='Configuração'!E46 -> Tecnologia
B41: 9 | C41: ='Configuração'!F47 -> 5 | D41: ='Configuração'!C47 -> Plano de Saúde | E41: ='Configuração'!D47 | F41: ='Configuração'!E47 -> Saúde
B42: 10 | C42: ='Configuração'!F48 -> 15 | D42: ='Configuração'!C48 -> Seguro (carro/vida) | E42: ='Configuração'!D48 | F42: ='Configuração'!E48 -> Seguros
B43: 11 | C43: ='Configuração'!F49 -> 1 | D43: ='Configuração'!C49 -> Transporte / Combustível | E43: ='Configuração'!D49 -> 200 | F43: ='Configuração'!E49 -> Transporte
B44: 12 | C44: ='Configuração'!F50 -> 1 | D44: ='Configuração'!C50 -> Supermercado (base) | E44: ='Configuração'!D50 | F44: ='Configuração'!E50 -> Alimentação
B45: 13 | C45: ='Configuração'!F51 -> 1 | D45: ='Configuração'!C51 -> Farmácia / Medicamentos | E45: ='Configuração'!D51 | F45: ='Configuração'!E51 -> Saúde
B46: 14 | C46: ='Configuração'!F52 -> 5 | D46: ='Configuração'!C52 -> Academia | E46: ='Configuração'!D52 | F46: ='Configuração'!E52 -> Saúde
B47: 15 | C47: ='Configuração'!F53 -> 1 | D47: ='Configuração'!C53 -> Streaming / Entretenimento | E47: ='Configuração'!D53 -> 59.9 | F47: ='Configuração'!E53 -> Lazer / Diversão
... B62: 30 | C62: ='Configuração'!F68 | D62: ='Configuração'!C68 | E62: ='Configuração'!D68 | F62: ='Configuração'!E68
B63: 🔒 | C63: TOTAL DESPESAS FIXAS | E63: =SUM(E33:E62) -> 1184.9
B65: 🛒 DESPESAS VARIÁVEIS — ANOTE AQUI TODAS AS SUAS DESPESAS DO DIA A DIA
B66: 👉 ANOTE AQUI: compras, alimentação fora, uber, café, roupas, presentes... TUDO que não é fixo. Cada real anotado deduz do seu saldo!
B67: # | C67: Data | D67: Descrição da Despesa | E67: Valor (R$) | F67: Categoria | G67: Jarro | H67: Forma Pgto | I67: Obs
B68: 1
B69: 2
B70: 3
B71: 4
B72: 5
B73: 6
B74: 7
B75: 8
B76: 9
B77: 10
B78: 11
B79: 12
... B101: 34
B102: 🛒 | C102: TOTAL DESPESAS VARIÁVEIS | E102: =SUM(E68:E101) -> 0
B104: 🏦 SALDO FINAL DO MÊS | D104: =D10 -> -5909.08 | F104: =IF(D9>=0,"✅ Mês positivo! Parabéns!","⚠️ Gastou mais do que ganhou — revise seus gastos") -> ⚠️ Gastou mais do que ganhou — revise seus gastos
B107: 💵 RECEITAS POR FONTE | F107: 💸 DESPESAS POR CATEGORIA
B108: Fonte | C108: Valor | D108: % Total | F108: Categoria | G108: Valor | H108: % Desp. | I108: Alerta
B109: Salário CLT | C109: =SUMIF(F14:F28,"Salário CLT",E14:E28) -> 0 | D109: =IF(E29=0,0,C109/E29) -> 0 | F109: Moradia | G109: =SUMIF(F33:F62,"Moradia",E33:E62)+SUMIF(F68:F101,"Moradia",E68:E101) -> 200 | H109: =IF(D8=0,0,G109/D8) -> 0.16879062 | I109: =IF(H109>0.25,"🔴",IF(H109>0.1,"🟡","🟢")) -> 🟡
B110: Freelance / Projetos | C110: =SUMIF(F14:F28,"Freelance / Projetos",E14:E28) -> 0 | D110: =IF(E29=0,0,C110/E29) -> 0 | F110: Alimentação | G110: =SUMIF(F33:F62,"Alimentação",E33:E62)+SUMIF(F68:F101,"Alimentação",E68:E101) -> 0 | H110: =IF(D8=0,0,G110/D8) -> 0 | I110: =IF(H110>0.25,"🔴",IF(H110>0.1,"🟡","🟢")) -> 🟢
B111: Vendas Online | C111: =SUMIF(F14:F28,"Vendas Online",E14:E28) -> 0 | D111: =IF(E29=0,0,C111/E29) -> 0 | F111: Transporte | G111: =SUMIF(F33:F62,"Transporte",E33:E62)+SUMIF(F68:F101,"Transporte",E68:E101) -> 200 | H111: =IF(D8=0,0,G111/D8) -> 0.16879062 | I111: =IF(H111>0.25,"🔴",IF(H111>0.1,"🟡","🟢")) -> 🟡
B112: Consultoria | C112: =SUMIF(F14:F28,"Consultoria",E14:E28) -> 0 | D112: =IF(E29=0,0,C112/E29) -> 0 | F112: Saúde | G112: =SUMIF(F33:F62,"Saúde",E33:E62)+SUMIF(F68:F101,"Saúde",E68:E101) -> 0 | H112: =IF(D8=0,0,G112/D8) -> 0 | I112: =IF(H112>0.25,"🔴",IF(H112>0.1,"🟡","🟢")) -> 🟢
B113: Rendimentos / Investimentos | C113: =SUMIF(F14:F28,"Rendimentos / Investimentos",E14:E28) -> 0 | D113: =IF(E29=0,0,C113/E29) -> 0 | F113: Educação | G113: =SUMIF(F33:F62,"Educação",E33:E62)+SUMIF(F68:F101,"Educação",E68:E101) -> 470 | H113: =IF(D8=0,0,G113/D8) -> 0.39665795 | I113: =IF(H113>0.25,"🔴",IF(H113>0.1,"🟡","🟢")) -> 🔴
B114: Aluguel Recebido | C114: =SUMIF(F14:F28,"Aluguel Recebido",E14:E28) -> 0 | D114: =IF(E29=0,0,C114/E29) -> 0 | F114: Lazer / Diversão | G114: =SUMIF(F33:F62,"Lazer / Diversão",E33:E62)+SUMIF(F68:F101,"Lazer / Diversão",E68:E101) -> 59.9 | H114: =IF(D8=0,0,G114/D8) -> 0.050552789 | I114: =IF(H114>0.25,"🔴",IF(H114>0.1,"🟡","🟢")) -> 🟢
B115: Comissões | C115: =SUMIF(F14:F28,"Comissões",E14:E28) -> 0 | D115: =IF(E29=0,0,C115/E29) -> 0 | F115: Vestuário | G115: =SUMIF(F33:F62,"Vestuário",E33:E62)+SUMIF(F68:F101,"Vestuário",E68:E101) -> 0 | H115: =IF(D8=0,0,G115/D8) -> 0 | I115: =IF(H115>0.25,"🔴",IF(H115>0.1,"🟡","🟢")) -> 🟢
B116: Bônus / Participação | C116: =SUMIF(F14:F28,"Bônus / Participação",E14:E28) -> 0 | D116: =IF(E29=0,0,C116/E29) -> 0 | F116: Tecnologia | G116: =SUMIF(F33:F62,"Tecnologia",E33:E62)+SUMIF(F68:F101,"Tecnologia",E68:E101) -> 160 | H116: =IF(D8=0,0,G116/D8) -> 0.13503249 | I116: =IF(H116>0.25,"🔴",IF(H116>0.1,"🟡","🟢")) -> 🟡
B117: Renda Extra / Bico | C117: =SUMIF(F14:F28,"Renda Extra / Bico",E14:E28) -> 0 | D117: =IF(E29=0,0,C117/E29) -> 0 | F117: Assinaturas | G117: =SUMIF(F33:F62,"Assinaturas",E33:E62)+SUMIF(F68:F101,"Assinaturas",E68:E101) -> 0 | H117: =IF(D8=0,0,G117/D8) -> 0 | I117: =IF(H117>0.25,"🔴",IF(H117>0.1,"🟡","🟢")) -> 🟢
B118: Outros | C118: =SUMIF(F14:F28,"Outros",E14:E28) -> 0 | D118: =IF(E29=0,0,C118/E29) -> 0 | F118: Seguros | G118: =SUMIF(F33:F62,"Seguros",E33:E62)+SUMIF(F68:F101,"Seguros",E68:E101) -> 0 | H118: =IF(D8=0,0,G118/D8) -> 0 | I118: =IF(H118>0.25,"🔴",IF(H118>0.1,"🟡","🟢")) -> 🟢
F119: Impostos | G119: =SUMIF(F33:F62,"Impostos",E33:E62)+SUMIF(F68:F101,"Impostos",E68:E101) -> 0 | H119: =IF(D8=0,0,G119/D8) -> 0 | I119: =IF(H119>0.25,"🔴",IF(H119>0.1,"🟡","🟢")) -> 🟢
F120: Investimentos | G120: =SUMIF(F33:F62,"Investimentos",E33:E62)+SUMIF(F68:F101,"Investimentos",E68:E101) -> 0 | H120: =IF(D8=0,0,G120/D8) -> 0 | I120: =IF(H120>0.25,"🔴",IF(H120>0.1,"🟡","🟢")) -> 🟢
F121: Doações | G121: =SUMIF(F33:F62,"Doações",E33:E62)+SUMIF(F68:F101,"Doações",E68:E101) -> 0 | H121: =IF(D8=0,0,G121/D8) -> 0 | I121: =IF(H121>0.25,"🔴",IF(H121>0.1,"🟡","🟢")) -> 🟢
F122: Outros | G122: =SUMIF(F33:F62,"Outros",E33:E62)+SUMIF(F68:F101,"Outros",E68:E101) -> 0 | H122: =IF(D8=0,0,G122/D8) -> 0 | I122: =IF(H122>0.25,"🔴",IF(H122>0.1,"🟡","🟢")) -> 🟢

Sheet Outubro
B1: 📅 OUTUBRO 2026 — CONTROLE COMPLETO
B3: 🏦 SALDO EM TEMPO REAL | F3: 🏺 JARROS DO MÊS
B4: 🔙 | C4: Saldo Inicial | D4: =Setembro!E10 -> -5909.08 | E4: =D5 -> 0 | F4: 🏠 | G4: NEC (55%) | H4: =D5*'Configuração'!D29 -> 0
B5: 💵 | C5: Total Entradas | D5: =E29 -> 0 | E5: =D5 -> 0 | F5: 💎 | G5: CFL (10%) | H5: =D5*'Configuração'!D30 -> 0
B6: 🔒 | C6: Despesas Fixas | D6: =E63 -> 1184.9 | F6: 🏦 | G6: PELP (10%) | H6: =D5*'Configuração'!D31 -> 0
B7: 🛒 | C7: Despesas Variáveis | D7: =E102 -> 0 | F7: 📚 | G7: EDU (10%) | H7: =D5*'Configuração'!D32 -> 0 | J7: =H4 -> 0 | M7: =C109 -> 0 | N7: =H4 -> 0
B8: 💸 | C8: Total Saídas | D8: =D6+D7 -> 1184.9 | E8: =IF(D5=0,0,D8/D5) -> 0 | F8: 🎉 | G8: DIV (10%) | H8: =D5*'Configuração'!D33 -> 0 | J8: =H5 -> 0 | M8: =C110 -> 0 | N8: =H5 -> 0
B9: 📈 | C9: Saldo do Mês | D9: =D5-D8 -> -1184.9 | E9: =IF(D5=0,0,D9/D5) -> 0 | F9: 🤝 | G9: DOA (5%) | H9: =D5*'Configuração'!D34 -> 0 | J9: =H6 -> 0 | M9: =C111 -> 0 | N9: =H6 -> 0
B10: 🏦 | C10: SALDO FINAL | D10: =D4+D9 -> -7093.98 | E10: =D10 -> -7093.98 | J10: =H7 -> 0 | M10: =C112 -> 0 | N10: =H7 -> 0
J11: =H8 -> 0 | M11: =C113 -> 0 | N11: =H8 -> 0
B12: 💰 RECEITAS DO MÊS — DE ONDE VEM SEU DINHEIRO | J12: =H9 -> 0 | M12: =C114 -> 0 | N12: =H9 -> 0
B13: # | C13: Data | D13: Descrição da Receita | E13: Valor (R$) | F13: Fonte de Receita | G13: Recebido? | H13: Observação | M13: =C115 -> 0
B14: 1 | M14: =C116 -> 0
B15: 2 | M15: =C117 -> 0
B16: 3 | M16: =C118 -> 0
B17: 4
B18: 5
B19: 6
B20: 7
B21: 8
B22: 9 | M22: =G109 -> 200
B23: 10 | M23: =G110 -> 0
B24: 11 | M24: =G111 -> 200
B25: 12 | M25: =G112 -> 0
B26: 13 | M26: =G113 -> 470
B27: 14 | M27: =G114 -> 59.9
B28: 15 | M28: =G115 -> 0
B29: 💰 | C29: TOTAL RECEITAS DO MÊS | E29: =SUM(E14:E28) -> 0 | M29: =G116 -> 160
M30: =G117 -> 0
B31: 🔒 DESPESAS FIXAS — AUTOMÁTICAS DA CONFIGURAÇÃO (edite valores se precisar) | M31: =G118 -> 0
B32: # | C32: Venc. | D32: Descrição | E32: Valor (R$) | F32: Categoria | G32: Pago? ✅/❌ | H32: Observação | M32: =G119 -> 0
B33: 1 | C33: ='Configuração'!F39 -> 5 | D33: ='Configuração'!C39 -> Aluguel / Financiamento | E33: ='Configuração'!D39 | F33: ='Configuração'!E39 -> Moradia | M33: =G120 -> 0
B34: 2 | C34: ='Configuração'!F40 -> 10 | D34: ='Configuração'!C40 -> Condomínio | E34: ='Configuração'!D40 | F34: ='Configuração'!E40 -> Moradia | M34: =G121 -> 0
B35: 3 | C35: ='Configuração'!F41 -> 15 | D35: ='Configuração'!C41 -> IPTU (parcela) | E35: ='Configuração'!D41 | F35: ='Configuração'!E41 -> Impostos | M35: =G122 -> 0
B36: 4 | C36: ='Configuração'!F42 -> 10 | D36: ='Configuração'!C42 -> Energia Elétrica | E36: ='Configuração'!D42 -> 200 | F36: ='Configuração'!E42 -> Moradia
B37: 5 | C37: ='Configuração'!F43 -> 15 | D37: ='Configuração'!C43 -> Água / Saneamento | E37: ='Configuração'!D43 | F37: ='Configuração'!E43 -> Moradia
B38: 6 | C38: ='Configuração'!F44 -> 20 | D38: ='Configuração'!C44 -> Gás | E38: ='Configuração'!D44 | F38: ='Configuração'!E44 -> Moradia
B39: 7 | C39: ='Configuração'!F45 -> 10 | D39: ='Configuração'!C45 -> Internet | E39: ='Configuração'!D45 -> 100 | F39: ='Configuração'!E45 -> Tecnologia
B40: 8 | C40: ='Configuração'!F46 -> 12 | D40: ='Configuração'!C46 -> Celular | E40: ='Configuração'!D46 -> 60 | F40: ='Configuração'!E46 -> Tecnologia
B41: 9 | C41: ='Configuração'!F47 -> 5 | D41: ='Configuração'!C47 -> Plano de Saúde | E41: ='Configuração'!D47 | F41: ='Configuração'!E47 -> Saúde
B42: 10 | C42: ='Configuração'!F48 -> 15 | D42: ='Configuração'!C48 -> Seguro (carro/vida) | E42: ='Configuração'!D48 | F42: ='Configuração'!E48 -> Seguros
B43: 11 | C43: ='Configuração'!F49 -> 1 | D43: ='Configuração'!C49 -> Transporte / Combustível | E43: ='Configuração'!D49 -> 200 | F43: ='Configuração'!E49 -> Transporte
B44: 12 | C44: ='Configuração'!F50 -> 1 | D44: ='Configuração'!C50 -> Supermercado (base) | E44: ='Configuração'!D50 | F44: ='Configuração'!E50 -> Alimentação
B45: 13 | C45: ='Configuração'!F51 -> 1 | D45: ='Configuração'!C51 -> Farmácia / Medicamentos | E45: ='Configuração'!D51 | F45: ='Configuração'!E51 -> Saúde
B46: 14 | C46: ='Configuração'!F52 -> 5 | D46: ='Configuração'!C52 -> Academia | E46: ='Configuração'!D52 | F46: ='Configuração'!E52 -> Saúde
B47: 15 | C47: ='Configuração'!F53 -> 1 | D47: ='Configuração'!C53 -> Streaming / Entretenimento | E47: ='Configuração'!D53 -> 59.9 | F47: ='Configuração'!E53 -> Lazer / Diversão
... B62: 30 | C62: ='Configuração'!F68 | D62: ='Configuração'!C68 | E62: ='Configuração'!D68 | F62: ='Configuração'!E68
B63: 🔒 | C63: TOTAL DESPESAS FIXAS | E63: =SUM(E33:E62) -> 1184.9
B65: 🛒 DESPESAS VARIÁVEIS — ANOTE AQUI TODAS AS SUAS DESPESAS DO DIA A DIA
B66: 👉 ANOTE AQUI: compras, alimentação fora, uber, café, roupas, presentes... TUDO que não é fixo. Cada real anotado deduz do seu saldo!
B67: # | C67: Data | D67: Descrição da Despesa | E67: Valor (R$) | F67: Categoria | G67: Jarro | H67: Forma Pgto | I67: Obs
B68: 1
B69: 2
B70: 3
B71: 4
B72: 5
B73: 6
B74: 7
B75: 8
B76: 9
B77: 10
B78: 11
B79: 12
... B101: 34
B102: 🛒 | C102: TOTAL DESPESAS VARIÁVEIS | E102: =SUM(E68:E101) -> 0
B104: 🏦 SALDO FINAL DO MÊS | D104: =D10 -> -7093.98 | F104: =IF(D9>=0,"✅ Mês positivo! Parabéns!","⚠️ Gastou mais do que ganhou — revise seus gastos") -> ⚠️ Gastou mais do que ganhou — revise seus gastos
B107: 💵 RECEITAS POR FONTE | F107: 💸 DESPESAS POR CATEGORIA
B108: Fonte | C108: Valor | D108: % Total | F108: Categoria | G108: Valor | H108: % Desp. | I108: Alerta
B109: Salário CLT | C109: =SUMIF(F14:F28,"Salário CLT",E14:E28) -> 0 | D109: =IF(E29=0,0,C109/E29) -> 0 | F109: Moradia | G109: =SUMIF(F33:F62,"Moradia",E33:E62)+SUMIF(F68:F101,"Moradia",E68:E101) -> 200 | H109: =IF(D8=0,0,G109/D8) -> 0.16879062 | I109: =IF(H109>0.25,"🔴",IF(H109>0.1,"🟡","🟢")) -> 🟡
B110: Freelance / Projetos | C110: =SUMIF(F14:F28,"Freelance / Projetos",E14:E28) -> 0 | D110: =IF(E29=0,0,C110/E29) -> 0 | F110: Alimentação | G110: =SUMIF(F33:F62,"Alimentação",E33:E62)+SUMIF(F68:F101,"Alimentação",E68:E101) -> 0 | H110: =IF(D8=0,0,G110/D8) -> 0 | I110: =IF(H110>0.25,"🔴",IF(H110>0.1,"🟡","🟢")) -> 🟢
B111: Vendas Online | C111: =SUMIF(F14:F28,"Vendas Online",E14:E28) -> 0 | D111: =IF(E29=0,0,C111/E29) -> 0 | F111: Transporte | G111: =SUMIF(F33:F62,"Transporte",E33:E62)+SUMIF(F68:F101,"Transporte",E68:E101) -> 200 | H111: =IF(D8=0,0,G111/D8) -> 0.16879062 | I111: =IF(H111>0.25,"🔴",IF(H111>0.1,"🟡","🟢")) -> 🟡
B112: Consultoria | C112: =SUMIF(F14:F28,"Consultoria",E14:E28) -> 0 | D112: =IF(E29=0,0,C112/E29) -> 0 | F112: Saúde | G112: =SUMIF(F33:F62,"Saúde",E33:E62)+SUMIF(F68:F101,"Saúde",E68:E101) -> 0 | H112: =IF(D8=0,0,G112/D8) -> 0 | I112: =IF(H112>0.25,"🔴",IF(H112>0.1,"🟡","🟢")) -> 🟢
B113: Rendimentos / Investimentos | C113: =SUMIF(F14:F28,"Rendimentos / Investimentos",E14:E28) -> 0 | D113: =IF(E29=0,0,C113/E29) -> 0 | F113: Educação | G113: =SUMIF(F33:F62,"Educação",E33:E62)+SUMIF(F68:F101,"Educação",E68:E101) -> 470 | H113: =IF(D8=0,0,G113/D8) -> 0.39665795 | I113: =IF(H113>0.25,"🔴",IF(H113>0.1,"🟡","🟢")) -> 🔴
B114: Aluguel Recebido | C114: =SUMIF(F14:F28,"Aluguel Recebido",E14:E28) -> 0 | D114: =IF(E29=0,0,C114/E29) -> 0 | F114: Lazer / Diversão | G114: =SUMIF(F33:F62,"Lazer / Diversão",E33:E62)+SUMIF(F68:F101,"Lazer / Diversão",E68:E101) -> 59.9 | H114: =IF(D8=0,0,G114/D8) -> 0.050552789 | I114: =IF(H114>0.25,"🔴",IF(H114>0.1,"🟡","🟢")) -> 🟢
B115: Comissões | C115: =SUMIF(F14:F28,"Comissões",E14:E28) -> 0 | D115: =IF(E29=0,0,C115/E29) -> 0 | F115: Vestuário | G115: =SUMIF(F33:F62,"Vestuário",E33:E62)+SUMIF(F68:F101,"Vestuário",E68:E101) -> 0 | H115: =IF(D8=0,0,G115/D8) -> 0 | I115: =IF(H115>0.25,"🔴",IF(H115>0.1,"🟡","🟢")) -> 🟢
B116: Bônus / Participação | C116: =SUMIF(F14:F28,"Bônus / Participação",E14:E28) -> 0 | D116: =IF(E29=0,0,C116/E29) -> 0 | F116: Tecnologia | G116: =SUMIF(F33:F62,"Tecnologia",E33:E62)+SUMIF(F68:F101,"Tecnologia",E68:E101) -> 160 | H116: =IF(D8=0,0,G116/D8) -> 0.13503249 | I116: =IF(H116>0.25,"🔴",IF(H116>0.1,"🟡","🟢")) -> 🟡
B117: Renda Extra / Bico | C117: =SUMIF(F14:F28,"Renda Extra / Bico",E14:E28) -> 0 | D117: =IF(E29=0,0,C117/E29) -> 0 | F117: Assinaturas | G117: =SUMIF(F33:F62,"Assinaturas",E33:E62)+SUMIF(F68:F101,"Assinaturas",E68:E101) -> 0 | H117: =IF(D8=0,0,G117/D8) -> 0 | I117: =IF(H117>0.25,"🔴",IF(H117>0.1,"🟡","🟢")) -> 🟢
B118: Outros | C118: =SUMIF(F14:F28,"Outros",E14:E28) -> 0 | D118: =IF(E29=0,0,C118/E29) -> 0 | F118: Seguros | G118: =SUMIF(F33:F62,"Seguros",E33:E62)+SUMIF(F68:F101,"Seguros",E68:E101) -> 0 | H118: =IF(D8=0,0,G118/D8) -> 0 | I118: =IF(H118>0.25,"🔴",IF(H118>0.1,"🟡","🟢")) -> 🟢
F119: Impostos | G119: =SUMIF(F33:F62,"Impostos",E33:E62)+SUMIF(F68:F101,"Impostos",E68:E101) -> 0 | H119: =IF(D8=0,0,G119/D8) -> 0 | I119: =IF(H119>0.25,"🔴",IF(H119>0.1,"🟡","🟢")) -> 🟢
F120: Investimentos | G120: =SUMIF(F33:F62,"Investimentos",E33:E62)+SUMIF(F68:F101,"Investimentos",E68:E101) -> 0 | H120: =IF(D8=0,0,G120/D8) -> 0 | I120: =IF(H120>0.25,"🔴",IF(H120>0.1,"🟡","🟢")) -> 🟢
F121: Doações | G121: =SUMIF(F33:F62,"Doações",E33:E62)+SUMIF(F68:F101,"Doações",E68:E101) -> 0 | H121: =IF(D8=0,0,G121/D8) -> 0 | I121: =IF(H121>0.25,"🔴",IF(H121>0.1,"🟡","🟢")) -> 🟢
F122: Outros | G122: =SUMIF(F33:F62,"Outros",E33:E62)+SUMIF(F68:F101,"Outros",E68:E101) -> 0 | H122: =IF(D8=0,0,G122/D8) -> 0 | I122: =IF(H122>0.25,"🔴",IF(H122>0.1,"🟡","🟢")) -> 🟢

Sheet Novembro
B1: 📅 NOVEMBRO 2026 — CONTROLE COMPLETO
B3: 🏦 SALDO EM TEMPO REAL | F3: 🏺 JARROS DO MÊS
B4: 🔙 | C4: Saldo Inicial | D4: =Outubro!E10 -> -7093.98 | E4: =D5 -> 0 | F4: 🏠 | G4: NEC (55%) | H4: =D5*'Configuração'!D29 -> 0
B5: 💵 | C5: Total Entradas | D5: =E29 -> 0 | E5: =D5 -> 0 | F5: 💎 | G5: CFL (10%) | H5: =D5*'Configuração'!D30 -> 0
B6: 🔒 | C6: Despesas Fixas | D6: =E63 -> 1184.9 | F6: 🏦 | G6: PELP (10%) | H6: =D5*'Configuração'!D31 -> 0
B7: 🛒 | C7: Despesas Variáveis | D7: =E102 -> 0 | F7: 📚 | G7: EDU (10%) | H7: =D5*'Configuração'!D32 -> 0 | J7: =H4 -> 0 | M7: =C109 -> 0 | N7: =H4 -> 0
B8: 💸 | C8: Total Saídas | D8: =D6+D7 -> 1184.9 | E8: =IF(D5=0,0,D8/D5) -> 0 | F8: 🎉 | G8: DIV (10%) | H8: =D5*'Configuração'!D33 -> 0 | J8: =H5 -> 0 | M8: =C110 -> 0 | N8: =H5 -> 0
B9: 📈 | C9: Saldo do Mês | D9: =D5-D8 -> -1184.9 | E9: =IF(D5=0,0,D9/D5) -> 0 | F9: 🤝 | G9: DOA (5%) | H9: =D5*'Configuração'!D34 -> 0 | J9: =H6 -> 0 | M9: =C111 -> 0 | N9: =H6 -> 0
B10: 🏦 | C10: SALDO FINAL | D10: =D4+D9 -> -8278.88 | E10: =D10 -> -8278.88 | J10: =H7 -> 0 | M10: =C112 -> 0 | N10: =H7 -> 0
J11: =H8 -> 0 | M11: =C113 -> 0 | N11: =H8 -> 0
B12: 💰 RECEITAS DO MÊS — DE ONDE VEM SEU DINHEIRO | J12: =H9 -> 0 | M12: =C114 -> 0 | N12: =H9 -> 0
B13: # | C13: Data | D13: Descrição da Receita | E13: Valor (R$) | F13: Fonte de Receita | G13: Recebido? | H13: Observação | M13: =C115 -> 0
B14: 1 | M14: =C116 -> 0
B15: 2 | M15: =C117 -> 0
B16: 3 | M16: =C118 -> 0
B17: 4
B18: 5
B19: 6
B20: 7
B21: 8
B22: 9 | M22: =G109 -> 200
B23: 10 | M23: =G110 -> 0
B24: 11 | M24: =G111 -> 200
B25: 12 | M25: =G112 -> 0
B26: 13 | M26: =G113 -> 470
B27: 14 | M27: =G114 -> 59.9
B28: 15 | M28: =G115 -> 0
B29: 💰 | C29: TOTAL RECEITAS DO MÊS | E29: =SUM(E14:E28) -> 0 | M29: =G116 -> 160
M30: =G117 -> 0
B31: 🔒 DESPESAS FIXAS — AUTOMÁTICAS DA CONFIGURAÇÃO (edite valores se precisar) | M31: =G118 -> 0
B32: # | C32: Venc. | D32: Descrição | E32: Valor (R$) | F32: Categoria | G32: Pago? ✅/❌ | H32: Observação | M32: =G119 -> 0
B33: 1 | C33: ='Configuração'!F39 -> 5 | D33: ='Configuração'!C39 -> Aluguel / Financiamento | E33: ='Configuração'!D39 | F33: ='Configuração'!E39 -> Moradia | M33: =G120 -> 0
B34: 2 | C34: ='Configuração'!F40 -> 10 | D34: ='Configuração'!C40 -> Condomínio | E34: ='Configuração'!D40 | F34: ='Configuração'!E40 -> Moradia | M34: =G121 -> 0
B35: 3 | C35: ='Configuração'!F41 -> 15 | D35: ='Configuração'!C41 -> IPTU (parcela) | E35: ='Configuração'!D41 | F35: ='Configuração'!E41 -> Impostos | M35: =G122 -> 0
B36: 4 | C36: ='Configuração'!F42 -> 10 | D36: ='Configuração'!C42 -> Energia Elétrica | E36: ='Configuração'!D42 -> 200 | F36: ='Configuração'!E42 -> Moradia
B37: 5 | C37: ='Configuração'!F43 -> 15 | D37: ='Configuração'!C43 -> Água / Saneamento | E37: ='Configuração'!D43 | F37: ='Configuração'!E43 -> Moradia
B38: 6 | C38: ='Configuração'!F44 -> 20 | D38: ='Configuração'!C44 -> Gás | E38: ='Configuração'!D44 | F38: ='Configuração'!E44 -> Moradia
B39: 7 | C39: ='Configuração'!F45 -> 10 | D39: ='Configuração'!C45 -> Internet | E39: ='Configuração'!D45 -> 100 | F39: ='Configuração'!E45 -> Tecnologia
B40: 8 | C40: ='Configuração'!F46 -> 12 | D40: ='Configuração'!C46 -> Celular | E40: ='Configuração'!D46 -> 60 | F40: ='Configuração'!E46 -> Tecnologia
B41: 9 | C41: ='Configuração'!F47 -> 5 | D41: ='Configuração'!C47 -> Plano de Saúde | E41: ='Configuração'!D47 | F41: ='Configuração'!E47 -> Saúde
B42: 10 | C42: ='Configuração'!F48 -> 15 | D42: ='Configuração'!C48 -> Seguro (carro/vida) | E42: ='Configuração'!D48 | F42: ='Configuração'!E48 -> Seguros
B43: 11 | C43: ='Configuração'!F49 -> 1 | D43: ='Configuração'!C49 -> Transporte / Combustível | E43: ='Configuração'!D49 -> 200 | F43: ='Configuração'!E49 -> Transporte
B44: 12 | C44: ='Configuração'!F50 -> 1 | D44: ='Configuração'!C50 -> Supermercado (base) | E44: ='Configuração'!D50 | F44: ='Configuração'!E50 -> Alimentação
B45: 13 | C45: ='Configuração'!F51 -> 1 | D45: ='Configuração'!C51 -> Farmácia / Medicamentos | E45: ='Configuração'!D51 | F45: ='Configuração'!E51 -> Saúde
B46: 14 | C46: ='Configuração'!F52 -> 5 | D46: ='Configuração'!C52 -> Academia | E46: ='Configuração'!D52 | F46: ='Configuração'!E52 -> Saúde
B47: 15 | C47: ='Configuração'!F53 -> 1 | D47: ='Configuração'!C53 -> Streaming / Entretenimento | E47: ='Configuração'!D53 -> 59.9 | F47: ='Configuração'!E53 -> Lazer / Diversão
... B62: 30 | C62: ='Configuração'!F68 | D62: ='Configuração'!C68 | E62: ='Configuração'!D68 | F62: ='Configuração'!E68
B63: 🔒 | C63: TOTAL DESPESAS FIXAS | E63: =SUM(E33:E62) -> 1184.9
B65: 🛒 DESPESAS VARIÁVEIS — ANOTE AQUI TODAS AS SUAS DESPESAS DO DIA A DIA
B66: 👉 ANOTE AQUI: compras, alimentação fora, uber, café, roupas, presentes... TUDO que não é fixo. Cada real anotado deduz do seu saldo!
B67: # | C67: Data | D67: Descrição da Despesa | E67: Valor (R$) | F67: Categoria | G67: Jarro | H67: Forma Pgto | I67: Obs
B68: 1
B69: 2
B70: 3
B71: 4
B72: 5
B73: 6
B74: 7
B75: 8
B76: 9
B77: 10
B78: 11
B79: 12
... B101: 34
B102: 🛒 | C102: TOTAL DESPESAS VARIÁVEIS | E102: =SUM(E68:E101) -> 0
B104: 🏦 SALDO FINAL DO MÊS | D104: =D10 -> -8278.88 | F104: =IF(D9>=0,"✅ Mês positivo! Parabéns!","⚠️ Gastou mais do que ganhou — revise seus gastos") -> ⚠️ Gastou mais do que ganhou — revise seus gastos
B107: 💵 RECEITAS POR FONTE | F107: 💸 DESPESAS POR CATEGORIA
B108: Fonte | C108: Valor | D108: % Total | F108: Categoria | G108: Valor | H108: % Desp. | I108: Alerta
B109: Salário CLT | C109: =SUMIF(F14:F28,"Salário CLT",E14:E28) -> 0 | D109: =IF(E29=0,0,C109/E29) -> 0 | F109: Moradia | G109: =SUMIF(F33:F62,"Moradia",E33:E62)+SUMIF(F68:F101,"Moradia",E68:E101) -> 200 | H109: =IF(D8=0,0,G109/D8) -> 0.16879062 | I109: =IF(H109>0.25,"🔴",IF(H109>0.1,"🟡","🟢")) -> 🟡
B110: Freelance / Projetos | C110: =SUMIF(F14:F28,"Freelance / Projetos",E14:E28) -> 0 | D110: =IF(E29=0,0,C110/E29) -> 0 | F110: Alimentação | G110: =SUMIF(F33:F62,"Alimentação",E33:E62)+SUMIF(F68:F101,"Alimentação",E68:E101) -> 0 | H110: =IF(D8=0,0,G110/D8) -> 0 | I110: =IF(H110>0.25,"🔴",IF(H110>0.1,"🟡","🟢")) -> 🟢
B111: Vendas Online | C111: =SUMIF(F14:F28,"Vendas Online",E14:E28) -> 0 | D111: =IF(E29=0,0,C111/E29) -> 0 | F111: Transporte | G111: =SUMIF(F33:F62,"Transporte",E33:E62)+SUMIF(F68:F101,"Transporte",E68:E101) -> 200 | H111: =IF(D8=0,0,G111/D8) -> 0.16879062 | I111: =IF(H111>0.25,"🔴",IF(H111>0.1,"🟡","🟢")) -> 🟡
B112: Consultoria | C112: =SUMIF(F14:F28,"Consultoria",E14:E28) -> 0 | D112: =IF(E29=0,0,C112/E29) -> 0 | F112: Saúde | G112: =SUMIF(F33:F62,"Saúde",E33:E62)+SUMIF(F68:F101,"Saúde",E68:E101) -> 0 | H112: =IF(D8=0,0,G112/D8) -> 0 | I112: =IF(H112>0.25,"🔴",IF(H112>0.1,"🟡","🟢")) -> 🟢
B113: Rendimentos / Investimentos | C113: =SUMIF(F14:F28,"Rendimentos / Investimentos",E14:E28) -> 0 | D113: =IF(E29=0,0,C113/E29) -> 0 | F113: Educação | G113: =SUMIF(F33:F62,"Educação",E33:E62)+SUMIF(F68:F101,"Educação",E68:E101) -> 470 | H113: =IF(D8=0,0,G113/D8) -> 0.39665795 | I113: =IF(H113>0.25,"🔴",IF(H113>0.1,"🟡","🟢")) -> 🔴
B114: Aluguel Recebido | C114: =SUMIF(F14:F28,"Aluguel Recebido",E14:E28) -> 0 | D114: =IF(E29=0,0,C114/E29) -> 0 | F114: Lazer / Diversão | G114: =SUMIF(F33:F62,"Lazer / Diversão",E33:E62)+SUMIF(F68:F101,"Lazer / Diversão",E68:E101) -> 59.9 | H114: =IF(D8=0,0,G114/D8) -> 0.050552789 | I114: =IF(H114>0.25,"🔴",IF(H114>0.1,"🟡","🟢")) -> 🟢
B115: Comissões | C115: =SUMIF(F14:F28,"Comissões",E14:E28) -> 0 | D115: =IF(E29=0,0,C115/E29) -> 0 | F115: Vestuário | G115: =SUMIF(F33:F62,"Vestuário",E33:E62)+SUMIF(F68:F101,"Vestuário",E68:E101) -> 0 | H115: =IF(D8=0,0,G115/D8) -> 0 | I115: =IF(H115>0.25,"🔴",IF(H115>0.1,"🟡","🟢")) -> 🟢
B116: Bônus / Participação | C116: =SUMIF(F14:F28,"Bônus / Participação",E14:E28) -> 0 | D116: =IF(E29=0,0,C116/E29) -> 0 | F116: Tecnologia | G116: =SUMIF(F33:F62,"Tecnologia",E33:E62)+SUMIF(F68:F101,"Tecnologia",E68:E101) -> 160 | H116: =IF(D8=0,0,G116/D8) -> 0.13503249 | I116: =IF(H116>0.25,"🔴",IF(H116>0.1,"🟡","🟢")) -> 🟡
B117: Renda Extra / Bico | C117: =SUMIF(F14:F28,"Renda Extra / Bico",E14:E28) -> 0 | D117: =IF(E29=0,0,C117/E29) -> 0 | F117: Assinaturas | G117: =SUMIF(F33:F62,"Assinaturas",E33:E62)+SUMIF(F68:F101,"Assinaturas",E68:E101) -> 0 | H117: =IF(D8=0,0,G117/D8) -> 0 | I117: =IF(H117>0.25,"🔴",IF(H117>0.1,"🟡","🟢")) -> 🟢
B118: Outros | C118: =SUMIF(F14:F28,"Outros",E14:E28) -> 0 | D118: =IF(E29=0,0,C118/E29) -> 0 | F118: Seguros | G118: =SUMIF(F33:F62,"Seguros",E33:E62)+SUMIF(F68:F101,"Seguros",E68:E101) -> 0 | H118: =IF(D8=0,0,G118/D8) -> 0 | I118: =IF(H118>0.25,"🔴",IF(H118>0.1,"🟡","🟢")) -> 🟢
F119: Impostos | G119: =SUMIF(F33:F62,"Impostos",E33:E62)+SUMIF(F68:F101,"Impostos",E68:E101) -> 0 | H119: =IF(D8=0,0,G119/D8) -> 0 | I119: =IF(H119>0.25,"🔴",IF(H119>0.1,"🟡","🟢")) -> 🟢
F120: Investimentos | G120: =SUMIF(F33:F62,"Investimentos",E33:E62)+SUMIF(F68:F101,"Investimentos",E68:E101) -> 0 | H120: =IF(D8=0,0,G120/D8) -> 0 | I120: =IF(H120>0.25,"🔴",IF(H120>0.1,"🟡","🟢")) -> 🟢
F121: Doações | G121: =SUMIF(F33:F62,"Doações",E33:E62)+SUMIF(F68:F101,"Doações",E68:E101) -> 0 | H121: =IF(D8=0,0,G121/D8) -> 0 | I121: =IF(H121>0.25,"🔴",IF(H121>0.1,"🟡","🟢")) -> 🟢
F122: Outros | G122: =SUMIF(F33:F62,"Outros",E33:E62)+SUMIF(F68:F101,"Outros",E68:E101) -> 0 | H122: =IF(D8=0,0,G122/D8) -> 0 | I122: =IF(H122>0.25,"🔴",IF(H122>0.1,"🟡","🟢")) -> 🟢

Sheet Dezembro
B1: 📅 DEZEMBRO 2026 — CONTROLE COMPLETO
B3: 🏦 SALDO EM TEMPO REAL | F3: 🏺 JARROS DO MÊS
B4: 🔙 | C4: Saldo Inicial | D4: =Novembro!E10 -> -8278.88 | E4: =D5 -> 0 | F4: 🏠 | G4: NEC (55%) | H4: =D5*'Configuração'!D29 -> 0
B5: 💵 | C5: Total Entradas | D5: =E29 -> 0 | E5: =D5 -> 0 | F5: 💎 | G5: CFL (10%) | H5: =D5*'Configuração'!D30 -> 0
B6: 🔒 | C6: Despesas Fixas | D6: =E63 -> 1184.9 | F6: 🏦 | G6: PELP (10%) | H6: =D5*'Configuração'!D31 -> 0
B7: 🛒 | C7: Despesas Variáveis | D7: =E102 -> 0 | F7: 📚 | G7: EDU (10%) | H7: =D5*'Configuração'!D32 -> 0 | J7: =H4 -> 0 | M7: =C109 -> 0 | N7: =H4 -> 0
B8: 💸 | C8: Total Saídas | D8: =D6+D7 -> 1184.9 | E8: =IF(D5=0,0,D8/D5) -> 0 | F8: 🎉 | G8: DIV (10%) | H8: =D5*'Configuração'!D33 -> 0 | J8: =H5 -> 0 | M8: =C110 -> 0 | N8: =H5 -> 0
B9: 📈 | C9: Saldo do Mês | D9: =D5-D8 -> -1184.9 | E9: =IF(D5=0,0,D9/D5) -> 0 | F9: 🤝 | G9: DOA (5%) | H9: =D5*'Configuração'!D34 -> 0 | J9: =H6 -> 0 | M9: =C111 -> 0 | N9: =H6 -> 0
B10: 🏦 | C10: SALDO FINAL | D10: =D4+D9 -> -9463.78 | E10: =D10 -> -9463.78 | J10: =H7 -> 0 | M10: =C112 -> 0 | N10: =H7 -> 0
J11: =H8 -> 0 | M11: =C113 -> 0 | N11: =H8 -> 0
B12: 💰 RECEITAS DO MÊS — DE ONDE VEM SEU DINHEIRO | J12: =H9 -> 0 | M12: =C114 -> 0 | N12: =H9 -> 0
B13: # | C13: Data | D13: Descrição da Receita | E13: Valor (R$) | F13: Fonte de Receita | G13: Recebido? | H13: Observação | M13: =C115 -> 0
B14: 1 | M14: =C116 -> 0
B15: 2 | M15: =C117 -> 0
B16: 3 | M16: =C118 -> 0
B17: 4
B18: 5
B19: 6
B20: 7
B21: 8
B22: 9 | M22: =G109 -> 200
B23: 10 | M23: =G110 -> 0
B24: 11 | M24: =G111 -> 200
B25: 12 | M25: =G112 -> 0
B26: 13 | M26: =G113 -> 470
B27: 14 | M27: =G114 -> 59.9
B28: 15 | M28: =G115 -> 0
B29: 💰 | C29: TOTAL RECEITAS DO MÊS | E29: =SUM(E14:E28) -> 0 | M29: =G116 -> 160
M30: =G117 -> 0
B31: 🔒 DESPESAS FIXAS — AUTOMÁTICAS DA CONFIGURAÇÃO (edite valores se precisar) | M31: =G118 -> 0
B32: # | C32: Venc. | D32: Descrição | E32: Valor (R$) | F32: Categoria | G32: Pago? ✅/❌ | H32: Observação | M32: =G119 -> 0
B33: 1 | C33: ='Configuração'!F39 -> 5 | D33: ='Configuração'!C39 -> Aluguel / Financiamento | E33: ='Configuração'!D39 | F33: ='Configuração'!E39 -> Moradia | M33: =G120 -> 0
B34: 2 | C34: ='Configuração'!F40 -> 10 | D34: ='Configuração'!C40 -> Condomínio | E34: ='Configuração'!D40 | F34: ='Configuração'!E40 -> Moradia | M34: =G121 -> 0
B35: 3 | C35: ='Configuração'!F41 -> 15 | D35: ='Configuração'!C41 -> IPTU (parcela) | E35: ='Configuração'!D41 | F35: ='Configuração'!E41 -> Impostos | M35: =G122 -> 0
B36: 4 | C36: ='Configuração'!F42 -> 10 | D36: ='Configuração'!C42 -> Energia Elétrica | E36: ='Configuração'!D42 -> 200 | F36: ='Configuração'!E42 -> Moradia
B37: 5 | C37: ='Configuração'!F43 -> 15 | D37: ='Configuração'!C43 -> Água / Saneamento | E37: ='Configuração'!D43 | F37: ='Configuração'!E43 -> Moradia
B38: 6 | C38: ='Configuração'!F44 -> 20 | D38: ='Configuração'!C44 -> Gás | E38: ='Configuração'!D44 | F38: ='Configuração'!E44 -> Moradia
B39: 7 | C39: ='Configuração'!F45 -> 10 | D39: ='Configuração'!C45 -> Internet | E39: ='Configuração'!D45 -> 100 | F39: ='Configuração'!E45 -> Tecnologia
B40: 8 | C40: ='Configuração'!F46 -> 12 | D40: ='Configuração'!C46 -> Celular | E40: ='Configuração'!D46 -> 60 | F40: ='Configuração'!E46 -> Tecnologia
B41: 9 | C41: ='Configuração'!F47 -> 5 | D41: ='Configuração'!C47 -> Plano de Saúde | E41: ='Configuração'!D47 | F41: ='Configuração'!E47 -> Saúde
B42: 10 | C42: ='Configuração'!F48 -> 15 | D42: ='Configuração'!C48 -> Seguro (carro/vida) | E42: ='Configuração'!D48 | F42: ='Configuração'!E48 -> Seguros
B43: 11 | C43: ='Configuração'!F49 -> 1 | D43: ='Configuração'!C49 -> Transporte / Combustível | E43: ='Configuração'!D49 -> 200 | F43: ='Configuração'!E49 -> Transporte
B44: 12 | C44: ='Configuração'!F50 -> 1 | D44: ='Configuração'!C50 -> Supermercado (base) | E44: ='Configuração'!D50 | F44: ='Configuração'!E50 -> Alimentação
B45: 13 | C45: ='Configuração'!F51 -> 1 | D45: ='Configuração'!C51 -> Farmácia / Medicamentos | E45: ='Configuração'!D51 | F45: ='Configuração'!E51 -> Saúde
B46: 14 | C46: ='Configuração'!F52 -> 5 | D46: ='Configuração'!C52 -> Academia | E46: ='Configuração'!D52 | F46: ='Configuração'!E52 -> Saúde
B47: 15 | C47: ='Configuração'!F53 -> 1 | D47: ='Configuração'!C53 -> Streaming / Entretenimento | E47: ='Configuração'!D53 -> 59.9 | F47: ='Configuração'!E53 -> Lazer / Diversão
... B62: 30 | C62: ='Configuração'!F68 | D62: ='Configuração'!C68 | E62: ='Configuração'!D68 | F62: ='Configuração'!E68
B63: 🔒 | C63: TOTAL DESPESAS FIXAS | E63: =SUM(E33:E62) -> 1184.9
B65: 🛒 DESPESAS VARIÁVEIS — ANOTE AQUI TODAS AS SUAS DESPESAS DO DIA A DIA
B66: 👉 ANOTE AQUI: compras, alimentação fora, uber, café, roupas, presentes... TUDO que não é fixo. Cada real anotado deduz do seu saldo!
B67: # | C67: Data | D67: Descrição da Despesa | E67: Valor (R$) | F67: Categoria | G67: Jarro | H67: Forma Pgto | I67: Obs
B68: 1
B69: 2
B70: 3
B71: 4
B72: 5
B73: 6
B74: 7
B75: 8
B76: 9
B77: 10
B78: 11
B79: 12
... B101: 34
B102: 🛒 | C102: TOTAL DESPESAS VARIÁVEIS | E102: =SUM(E68:E101) -> 0
B104: 🏦 SALDO FINAL DO MÊS | D104: =D10 -> -9463.78 | F104: =IF(D9>=0,"✅ Mês positivo! Parabéns!","⚠️ Gastou mais do que ganhou — revise seus gastos") -> ⚠️ Gastou mais do que ganhou — revise seus gastos
B107: 💵 RECEITAS POR FONTE | F107: 💸 DESPESAS POR CATEGORIA
B108: Fonte | C108: Valor | D108: % Total | F108: Categoria | G108: Valor | H108: % Desp. | I108: Alerta
B109: Salário CLT | C109: =SUMIF(F14:F28,"Salário CLT",E14:E28) -> 0 | D109: =IF(E29=0,0,C109/E29) -> 0 | F109: Moradia | G109: =SUMIF(F33:F62,"Moradia",E33:E62)+SUMIF(F68:F101,"Moradia",E68:E101) -> 200 | H109: =IF(D8=0,0,G109/D8) -> 0.16879062 | I109: =IF(H109>0.25,"🔴",IF(H109>0.1,"🟡","🟢")) -> 🟡
B110: Freelance / Projetos | C110: =SUMIF(F14:F28,"Freelance / Projetos",E14:E28) -> 0 | D110: =IF(E29=0,0,C110/E29) -> 0 | F110: Alimentação | G110: =SUMIF(F33:F62,"Alimentação",E33:E62)+SUMIF(F68:F101,"Alimentação",E68:E101) -> 0 | H110: =IF(D8=0,0,G110/D8) -> 0 | I110: =IF(H110>0.25,"🔴",IF(H110>0.1,"🟡","🟢")) -> 🟢
B111: Vendas Online | C111: =SUMIF(F14:F28,"Vendas Online",E14:E28) -> 0 | D111: =IF(E29=0,0,C111/E29) -> 0 | F111: Transporte | G111: =SUMIF(F33:F62,"Transporte",E33:E62)+SUMIF(F68:F101,"Transporte",E68:E101) -> 200 | H111: =IF(D8=0,0,G111/D8) -> 0.16879062 | I111: =IF(H111>0.25,"🔴",IF(H111>0.1,"🟡","🟢")) -> 🟡
B112: Consultoria | C112: =SUMIF(F14:F28,"Consultoria",E14:E28) -> 0 | D112: =IF(E29=0,0,C112/E29) -> 0 | F112: Saúde | G112: =SUMIF(F33:F62,"Saúde",E33:E62)+SUMIF(F68:F101,"Saúde",E68:E101) -> 0 | H112: =IF(D8=0,0,G112/D8) -> 0 | I112: =IF(H112>0.25,"🔴",IF(H112>0.1,"🟡","🟢")) -> 🟢
B113: Rendimentos / Investimentos | C113: =SUMIF(F14:F28,"Rendimentos / Investimentos",E14:E28) -> 0 | D113: =IF(E29=0,0,C113/E29) -> 0 | F113: Educação | G113: =SUMIF(F33:F62,"Educação",E33:E62)+SUMIF(F68:F101,"Educação",E68:E101) -> 470 | H113: =IF(D8=0,0,G113/D8) -> 0.39665795 | I113: =IF(H113>0.25,"🔴",IF(H113>0.1,"🟡","🟢")) -> 🔴
B114: Aluguel Recebido | C114: =SUMIF(F14:F28,"Aluguel Recebido",E14:E28) -> 0 | D114: =IF(E29=0,0,C114/E29) -> 0 | F114: Lazer / Diversão | G114: =SUMIF(F33:F62,"Lazer / Diversão",E33:E62)+SUMIF(F68:F101,"Lazer / Diversão",E68:E101) -> 59.9 | H114: =IF(D8=0,0,G114/D8) -> 0.050552789 | I114: =IF(H114>0.25,"🔴",IF(H114>0.1,"🟡","🟢")) -> 🟢
B115: Comissões | C115: =SUMIF(F14:F28,"Comissões",E14:E28) -> 0 | D115: =IF(E29=0,0,C115/E29) -> 0 | F115: Vestuário | G115: =SUMIF(F33:F62,"Vestuário",E33:E62)+SUMIF(F68:F101,"Vestuário",E68:E101) -> 0 | H115: =IF(D8=0,0,G115/D8) -> 0 | I115: =IF(H115>0.25,"🔴",IF(H115>0.1,"🟡","🟢")) -> 🟢
B116: Bônus / Participação | C116: =SUMIF(F14:F28,"Bônus / Participação",E14:E28) -> 0 | D116: =IF(E29=0,0,C116/E29) -> 0 | F116: Tecnologia | G116: =SUMIF(F33:F62,"Tecnologia",E33:E62)+SUMIF(F68:F101,"Tecnologia",E68:E101) -> 160 | H116: =IF(D8=0,0,G116/D8) -> 0.13503249 | I116: =IF(H116>0.25,"🔴",IF(H116>0.1,"🟡","🟢")) -> 🟡
B117: Renda Extra / Bico | C117: =SUMIF(F14:F28,"Renda Extra / Bico",E14:E28) -> 0 | D117: =IF(E29=0,0,C117/E29) -> 0 | F117: Assinaturas | G117: =SUMIF(F33:F62,"Assinaturas",E33:E62)+SUMIF(F68:F101,"Assinaturas",E68:E101) -> 0 | H117: =IF(D8=0,0,G117/D8) -> 0 | I117: =IF(H117>0.25,"🔴",IF(H117>0.1,"🟡","🟢")) -> 🟢
B118: Outros | C118: =SUMIF(F14:F28,"Outros",E14:E28) -> 0 | D118: =IF(E29=0,0,C118/E29) -> 0 | F118: Seguros | G118: =SUMIF(F33:F62,"Seguros",E33:E62)+SUMIF(F68:F101,"Seguros",E68:E101) -> 0 | H118: =IF(D8=0,0,G118/D8) -> 0 | I118: =IF(H118>0.25,"🔴",IF(H118>0.1,"🟡","🟢")) -> 🟢
F119: Impostos | G119: =SUMIF(F33:F62,"Impostos",E33:E62)+SUMIF(F68:F101,"Impostos",E68:E101) -> 0 | H119: =IF(D8=0,0,G119/D8) -> 0 | I119: =IF(H119>0.25,"🔴",IF(H119>0.1,"🟡","🟢")) -> 🟢
F120: Investimentos | G120: =SUMIF(F33:F62,"Investimentos",E33:E62)+SUMIF(F68:F101,"Investimentos",E68:E101) -> 0 | H120: =IF(D8=0,0,G120/D8) -> 0 | I120: =IF(H120>0.25,"🔴",IF(H120>0.1,"🟡","🟢")) -> 🟢
F121: Doações | G121: =SUMIF(F33:F62,"Doações",E33:E62)+SUMIF(F68:F101,"Doações",E68:E101) -> 0 | H121: =IF(D8=0,0,G121/D8) -> 0 | I121: =IF(H121>0.25,"🔴",IF(H121>0.1,"🟡","🟢")) -> 🟢
F122: Outros | G122: =SUMIF(F33:F62,"Outros",E33:E62)+SUMIF(F68:F101,"Outros",E68:E101) -> 0 | H122: =IF(D8=0,0,G122/D8) -> 0 | I122: =IF(H122>0.25,"🔴",IF(H122>0.1,"🟡","🟢")) -> 🟢

Sheet Raio-X Anual
B1: 🔬 RAIO-X FINANCEIRO ANUAL — ANÁLISE TOTAL
B4: 💵 RECEITAS POR FONTE — EVOLUÇÃO MENSAL
B5: Fonte | C5: Jan | D5: Fev | E5: Mar | F5: Abr | G5: Mai | H5: Jun | I5: Jul | J5: Ago | K5: Set | L5: Out | M5: Nov | N5: Dez | O5: TOTAL
B6: Salário CLT | C6: =Janeiro!M7 -> 0 | D6: =Fevereiro!M7 -> 0 | E6: ='Março'!M7 -> 0 | F6: =Abril!M7 -> 0 | G6: =Maio!M7 -> 0 | H6: =Junho!M7 -> 0 | I6: =Julho!M7 -> 0 | J6: =Agosto!M7 -> 0 | K6: =Setembro!M7 -> 0 | L6: =Outubro!M7 -> 0 | M6: =Novembro!M7 -> 0 | N6: =Dezembro!M7 -> 0 | O6: =SUM(C6:N6) -> 0
B7: Freelance / Projetos | C7: =Janeiro!M8 -> 0 | D7: =Fevereiro!M8 -> 0 | E7: ='Março'!M8 -> 0 | F7: =Abril!M8 -> 0 | G7: =Maio!M8 -> 0 | H7: =Junho!M8 -> 0 | I7: =Julho!M8 -> 0 | J7: =Agosto!M8 -> 0 | K7: =Setembro!M8 -> 0 | L7: =Outubro!M8 -> 0 | M7: =Novembro!M8 -> 0 | N7: =Dezembro!M8 -> 0 | O7: =SUM(C7:N7) -> 0
B8: Vendas Online | C8: =Janeiro!M9 -> 0 | D8: =Fevereiro!M9 -> 0 | E8: ='Março'!M9 -> 0 | F8: =Abril!M9 -> 0 | G8: =Maio!M9 -> 0 | H8: =Junho!M9 -> 0 | I8: =Julho!M9 -> 0 | J8: =Agosto!M9 -> 0 | K8: =Setembro!M9 -> 0 | L8: =Outubro!M9 -> 0 | M8: =Novembro!M9 -> 0 | N8: =Dezembro!M9 -> 0 | O8: =SUM(C8:N8) -> 0
B9: Consultoria | C9: =Janeiro!M10 -> 0 | D9: =Fevereiro!M10 -> 0 | E9: ='Março'!M10 -> 0 | F9: =Abril!M10 -> 0 | G9: =Maio!M10 -> 0 | H9: =Junho!M10 -> 0 | I9: =Julho!M10 -> 0 | J9: =Agosto!M10 -> 0 | K9: =Setembro!M10 -> 0 | L9: =Outubro!M10 -> 0 | M9: =Novembro!M10 -> 0 | N9: =Dezembro!M10 -> 0 | O9: =SUM(C9:N9) -> 0
B10: Rendimentos / Investimentos | C10: =Janeiro!M11 -> 0 | D10: =Fevereiro!M11 -> 0 | E10: ='Março'!M11 -> 0 | F10: =Abril!M11 -> 0 | G10: =Maio!M11 -> 0 | H10: =Junho!M11 -> 0 | I10: =Julho!M11 -> 0 | J10: =Agosto!M11 -> 0 | K10: =Setembro!M11 -> 0 | L10: =Outubro!M11 -> 0 | M10: =Novembro!M11 -> 0 | N10: =Dezembro!M11 -> 0 | O10: =SUM(C10:N10) -> 0
B11: Aluguel Recebido | C11: =Janeiro!M12 -> 0 | D11: =Fevereiro!M12 -> 0 | E11: ='Março'!M12 -> 0 | F11: =Abril!M12 -> 0 | G11: =Maio!M12 -> 0 | H11: =Junho!M12 -> 0 | I11: =Julho!M12 -> 0 | J11: =Agosto!M12 -> 0 | K11: =Setembro!M12 -> 0 | L11: =Outubro!M12 -> 0 | M11: =Novembro!M12 -> 0 | N11: =Dezembro!M12 -> 0 | O11: =SUM(C11:N11) -> 0
B12: Comissões | C12: =Janeiro!M13 -> 0 | D12: =Fevereiro!M13 -> 0 | E12: ='Março'!M13 -> 0 | F12: =Abril!M13 -> 0 | G12: =Maio!M13 -> 0 | H12: =Junho!M13 -> 0 | I12: =Julho!M13 -> 0 | J12: =Agosto!M13 -> 0 | K12: =Setembro!M13 -> 0 | L12: =Outubro!M13 -> 0 | M12: =Novembro!M13 -> 0 | N12: =Dezembro!M13 -> 0 | O12: =SUM(C12:N12) -> 0
B13: Bônus / Participação | C13: =Janeiro!M14 -> 0 | D13: =Fevereiro!M14 -> 0 | E13: ='Março'!M14 -> 0 | F13: =Abril!M14 -> 0 | G13: =Maio!M14 -> 0 | H13: =Junho!M14 -> 0 | I13: =Julho!M14 -> 0 | J13: =Agosto!M14 -> 0 | K13: =Setembro!M14 -> 0 | L13: =Outubro!M14 -> 0 | M13: =Novembro!M14 -> 0 | N13: =Dezembro!M14 -> 0 | O13: =SUM(C13:N13) -> 0
B14: Renda Extra / Bico | C14: =Janeiro!M15 -> 0 | D14: =Fevereiro!M15 -> 0 | E14: ='Março'!M15 -> 0 | F14: =Abril!M15 -> 0 | G14: =Maio!M15 -> 0 | H14: =Junho!M15 -> 0 | I14: =Julho!M15 -> 0 | J14: =Agosto!M15 -> 0 | K14: =Setembro!M15 -> 0 | L14: =Outubro!M15 -> 0 | M14: =Novembro!M15 -> 0 | N14: =Dezembro!M15 -> 0 | O14: =SUM(C14:N14) -> 0
B15: Outros | C15: =Janeiro!M16 -> 0 | D15: =Fevereiro!M16 -> 0 | E15: ='Março'!M16 -> 0 | F15: =Abril!M16 -> 0 | G15: =Maio!M16 -> 0 | H15: =Junho!M16 -> 0 | I15: =Julho!M16 -> 0 | J15: =Agosto!M16 -> 0 | K15: =Setembro!M16 -> 0 | L15: =Outubro!M16 -> 0 | M15: =Novembro!M16 -> 0 | N15: =Dezembro!M16 -> 0 | O15: =SUM(C15:N15) -> 0
B16: TOTAL | C16: =SUM(C6:C15) -> 0 | D16: =SUM(D6:D15) -> 0 | E16: =SUM(E6:E15) -> 0 | F16: =SUM(F6:F15) -> 0 | G16: =SUM(G6:G15) -> 0 | H16: =SUM(H6:H15) -> 0 | I16: =SUM(I6:I15) -> 0 | J16: =SUM(J6:J15) -> 0 | ... O16: =SUM(O6:O15) -> 0
B35: 💸 DESPESAS POR CATEGORIA — EVOLUÇÃO MENSAL
B36: Categoria | C36: Jan | D36: Fev | E36: Mar | F36: Abr | G36: Mai | H36: Jun | I36: Jul | J36: Ago | K36: Set | L36: Out | M36: Nov | N36: Dez | O36: TOTAL
B37: Moradia | C37: =Janeiro!M22 -> 200 | D37: =Fevereiro!M22 -> 200 | E37: ='Março'!M22 -> 200 | F37: =Abril!M22 -> 200 | G37: =Maio!M22 -> 200 | H37: =Junho!M22 -> 200 | I37: =Julho!M22 -> 200 | J37: =Agosto!M22 -> 200 | K37: =Setembro!M22 -> 200 | L37: =Outubro!M22 -> 200 | M37: =Novembro!M22 -> 200 | N37: =Dezembro!M22 -> 200 | O37: =SUM(C37:N37) -> 2400
B38: Alimentação | C38: =Janeiro!M23 -> 0 | D38: =Fevereiro!M23 -> 584.98 | E38: ='Março'!M23 -> 0 | F38: =Abril!M23 -> 0 | G38: =Maio!M23 -> 0 | H38: =Junho!M23 -> 0 | I38: =Julho!M23 -> 0 | J38: =Agosto!M23 -> 0 | K38: =Setembro!M23 -> 0 | L38: =Outubro!M23 -> 0 | M38: =Novembro!M23 -> 0 | N38: =Dezembro!M23 -> 0 | O38: =SUM(C38:N38) -> 584.98
B39: Transporte | C39: =Janeiro!M24 -> 200 | D39: =Fevereiro!M24 -> 310 | E39: ='Março'!M24 -> 200 | F39: =Abril!M24 -> 200 | G39: =Maio!M24 -> 200 | H39: =Junho!M24 -> 200 | I39: =Julho!M24 -> 200 | J39: =Agosto!M24 -> 200 | K39: =Setembro!M24 -> 200 | L39: =Outubro!M24 -> 200 | M39: =Novembro!M24 -> 200 | N39: =Dezembro!M24 -> 200 | O39: =SUM(C39:N39) -> 2510
B40: Saúde | C40: =Janeiro!M25 -> 0 | D40: =Fevereiro!M25 -> 101 | E40: ='Março'!M25 -> 0 | F40: =Abril!M25 -> 0 | G40: =Maio!M25 -> 0 | H40: =Junho!M25 -> 0 | I40: =Julho!M25 -> 0 | J40: =Agosto!M25 -> 0 | K40: =Setembro!M25 -> 0 | L40: =Outubro!M25 -> 0 | M40: =Novembro!M25 -> 0 | N40: =Dezembro!M25 -> 0 | O40: =SUM(C40:N40) -> 101
B41: Educação | C41: =Janeiro!M26 -> 470 | D41: =Fevereiro!M26 -> 470 | E41: ='Março'!M26 -> 470 | F41: =Abril!M26 -> 470 | G41: =Maio!M26 -> 470 | H41: =Junho!M26 -> 470 | I41: =Julho!M26 -> 470 | J41: =Agosto!M26 -> 470 | K41: =Setembro!M26 -> 470 | L41: =Outubro!M26 -> 470 | M41: =Novembro!M26 -> 470 | N41: =Dezembro!M26 -> 470 | O41: =SUM(C41:N41) -> 5640
B42: Lazer / Diversão | C42: =Janeiro!M27 -> 59.9 | D42: =Fevereiro!M27 -> 59.9 | E42: ='Março'!M27 -> 59.9 | F42: =Abril!M27 -> 59.9 | G42: =Maio!M27 -> 59.9 | H42: =Junho!M27 -> 59.9 | I42: =Julho!M27 -> 59.9 | J42: =Agosto!M27 -> 59.9 | K42: =Setembro!M27 -> 59.9 | L42: =Outubro!M27 -> 59.9 | M42: =Novembro!M27 -> 59.9 | N42: =Dezembro!M27 -> 59.9 | O42: =SUM(C42:N42) -> 718.8
B43: Vestuário | C43: =Janeiro!M28 -> 0 | D43: =Fevereiro!M28 -> 142 | E43: ='Março'!M28 -> 0 | F43: =Abril!M28 -> 0 | G43: =Maio!M28 -> 0 | H43: =Junho!M28 -> 0 | I43: =Julho!M28 -> 0 | J43: =Agosto!M28 -> 0 | K43: =Setembro!M28 -> 0 | L43: =Outubro!M28 -> 0 | M43: =Novembro!M28 -> 0 | N43: =Dezembro!M28 -> 0 | O43: =SUM(C43:N43) -> 142
B44: Tecnologia | C44: =Janeiro!M29 -> 160 | D44: =Fevereiro!M29 -> 160 | E44: ='Março'!M29 -> 160 | F44: =Abril!M29 -> 160 | G44: =Maio!M29 -> 160 | H44: =Junho!M29 -> 160 | I44: =Julho!M29 -> 160 | J44: =Agosto!M29 -> 160 | K44: =Setembro!M29 -> 160 | L44: =Outubro!M29 -> 160 | M44: =Novembro!M29 -> 160 | N44: =Dezembro!M29 -> 160 | O44: =SUM(C44:N44) -> 1920
B45: Assinaturas | C45: =Janeiro!M30 -> 0 | D45: =Fevereiro!M30 -> 0 | E45: ='Março'!M30 -> 0 | F45: =Abril!M30 -> 0 | G45: =Maio!M30 -> 0 | H45: =Junho!M30 -> 0 | I45: =Julho!M30 -> 0 | J45: =Agosto!M30 -> 0 | K45: =Setembro!M30 -> 0 | L45: =Outubro!M30 -> 0 | M45: =Novembro!M30 -> 0 | N45: =Dezembro!M30 -> 0 | O45: =SUM(C45:N45) -> 0
B46: Seguros | C46: =Janeiro!M31 -> 0 | D46: =Fevereiro!M31 -> 0 | E46: ='Março'!M31 -> 0 | F46: =Abril!M31 -> 0 | G46: =Maio!M31 -> 0 | H46: =Junho!M31 -> 0 | I46: =Julho!M31 -> 0 | J46: =Agosto!M31 -> 0 | K46: =Setembro!M31 -> 0 | L46: =Outubro!M31 -> 0 | M46: =Novembro!M31 -> 0 | N46: =Dezembro!M31 -> 0 | O46: =SUM(C46:N46) -> 0
B47: Impostos | C47: =Janeiro!M32 -> 0 | D47: =Fevereiro!M32 -> 0 | E47: ='Março'!M32 -> 0 | F47: =Abril!M32 -> 0 | G47: =Maio!M32 -> 0 | H47: =Junho!M32 -> 0 | I47: =Julho!M32 -> 0 | J47: =Agosto!M32 -> 0 | K47: =Setembro!M32 -> 0 | L47: =Outubro!M32 -> 0 | M47: =Novembro!M32 -> 0 | N47: =Dezembro!M32 -> 0 | O47: =SUM(C47:N47) -> 0
B48: Investimentos | C48: =Janeiro!M33 -> 0 | D48: =Fevereiro!M33 -> 0 | E48: ='Março'!M33 -> 0 | F48: =Abril!M33 -> 0 | G48: =Maio!M33 -> 0 | H48: =Junho!M33 -> 0 | I48: =Julho!M33 -> 0 | J48: =Agosto!M33 -> 0 | K48: =Setembro!M33 -> 0 | L48: =Outubro!M33 -> 0 | M48: =Novembro!M33 -> 0 | N48: =Dezembro!M33 -> 0 | O48: =SUM(C48:N48) -> 0
... B50: Outros | C50: =Janeiro!M35 -> 0 | D50: =Fevereiro!M35 -> 0 | E50: ='Março'!M35 -> 0 | F50: =Abril!M35 -> 0 | G50: =Maio!M35 -> 0 | H50: =Junho!M35 -> 0 | I50: =Julho!M35 -> 0 | J50: =Agosto!M35 -> 0 | K50: =Setembro!M35 -> 0 | L50: =Outubro!M35 -> 0 | M50: =Novembro!M35 -> 0 | N50: =Dezembro!M35 -> 0 | O50: =SUM(C50:N50) -> 0
B51: TOTAL | C51: =SUM(C37:C50) -> 1089.9 | D51: =SUM(D37:D50) -> 2027.88 | E51: =SUM(E37:E50) -> 1089.9 | F51: =SUM(F37:F50) -> 1089.9 | G51: =SUM(G37:G50) -> 1089.9 | H51: =SUM(H37:H50) -> 1089.9 | I51: =SUM(I37:I50) -> 1089.9 | J51: =SUM(J37:J50) -> 1089.9 | ... O51: =SUM(O37:O50) -> 14016.78
B70: 🏺 JARROS — EVOLUÇÃO MENSAL
B71: Jarro | C71: Jan | D71: Fev | E71: Mar | F71: Abr | G71: Mai | H71: Jun | I71: Jul | J71: Ago | K71: Set | L71: Out | M71: Nov | N71: Dez | O71: TOTAL
B72: 🏠 NEC | C72: =Janeiro!N7 -> 0 | D72: =Fevereiro!N7 -> 3516.15 | E72: ='Março'!N7 -> 0 | F72: =Abril!N7 -> 0 | G72: =Maio!N7 -> 0 | H72: =Junho!N7 -> 0 | I72: =Julho!N7 -> 0 | J72: =Agosto!N7 -> 0 | K72: =Setembro!N7 -> 0 | L72: =Outubro!N7 -> 0 | M72: =Novembro!N7 -> 0 | N72: =Dezembro!N7 -> 0 | O72: =SUM(C72:N72) -> 3516.15
B73: 💎 CFL | C73: =Janeiro!N8 -> 0 | D73: =Fevereiro!N8 -> 639.3 | E73: ='Março'!N8 -> 0 | F73: =Abril!N8 -> 0 | G73: =Maio!N8 -> 0 | H73: =Junho!N8 -> 0 | I73: =Julho!N8 -> 0 | J73: =Agosto!N8 -> 0 | K73: =Setembro!N8 -> 0 | L73: =Outubro!N8 -> 0 | M73: =Novembro!N8 -> 0 | N73: =Dezembro!N8 -> 0 | O73: =SUM(C73:N73) -> 639.3
B74: 🏦 PELP | C74: =Janeiro!N9 -> 0 | D74: =Fevereiro!N9 -> 639.3 | E74: ='Março'!N9 -> 0 | F74: =Abril!N9 -> 0 | G74: =Maio!N9 -> 0 | H74: =Junho!N9 -> 0 | I74: =Julho!N9 -> 0 | J74: =Agosto!N9 -> 0 | K74: =Setembro!N9 -> 0 | L74: =Outubro!N9 -> 0 | M74: =Novembro!N9 -> 0 | N74: =Dezembro!N9 -> 0 | O74: =SUM(C74:N74) -> 639.3
B75: 📚 EDU | C75: =Janeiro!N10 -> 0 | D75: =Fevereiro!N10 -> 639.3 | E75: ='Março'!N10 -> 0 | F75: =Abril!N10 -> 0 | G75: =Maio!N10 -> 0 | H75: =Junho!N10 -> 0 | I75: =Julho!N10 -> 0 | J75: =Agosto!N10 -> 0 | K75: =Setembro!N10 -> 0 | L75: =Outubro!N10 -> 0 | M75: =Novembro!N10 -> 0 | N75: =Dezembro!N10 -> 0 | O75: =SUM(C75:N75) -> 639.3
B76: 🎉 DIV | C76: =Janeiro!N11 -> 0 | D76: =Fevereiro!N11 -> 639.3 | E76: ='Março'!N11 -> 0 | F76: =Abril!N11 -> 0 | G76: =Maio!N11 -> 0 | H76: =Junho!N11 -> 0 | I76: =Julho!N11 -> 0 | J76: =Agosto!N11 -> 0 | K76: =Setembro!N11 -> 0 | L76: =Outubro!N11 -> 0 | M76: =Novembro!N11 -> 0 | N76: =Dezembro!N11 -> 0 | O76: =SUM(C76:N76) -> 639.3
B77: 🤝 DOA | C77: =Janeiro!N12 -> 0 | D77: =Fevereiro!N12 -> 319.65 | E77: ='Março'!N12 -> 0 | F77: =Abril!N12 -> 0 | G77: =Maio!N12 -> 0 | H77: =Junho!N12 -> 0 | I77: =Julho!N12 -> 0 | J77: =Agosto!N12 -> 0 | K77: =Setembro!N12 -> 0 | L77: =Outubro!N12 -> 0 | M77: =Novembro!N12 -> 0 | N77: =Dezembro!N12 -> 0 | O77: =SUM(C77:N77) -> 319.65
B78: TOTAL | C78: =SUM(C72:C77) -> 0 | D78: =SUM(D72:D77) -> 6393 | E78: =SUM(E72:E77) -> 0 | F78: =SUM(F72:F77) -> 0 | G78: =SUM(G72:G77) -> 0 | H78: =SUM(H72:H77) -> 0 | I78: =SUM(I72:I77) -> 0 | J78: =SUM(J72:J77) -> 0 | ... O78: =SUM(O72:O77) -> 6393
